Workbook

Sheet CERTIFICACIÓN REV 1
A1: 8000045901 - SERVICIO DE MANTENIMIENTO INTERGRADO Marzo -26
K4: MANTENIMINETO DE AIRE ACONDICIONADO | N4: 0.5
A5: PAGO BASICO MENSUAL | E5: 30832490 | K5: MANTENIMINETO ELECTRICO | N5: 0.4
K6: GRUPO GENERADOR | N6: 0.1
A7: PORCENTAJE CUMPLIMIENTO MENSUAL | E7: 1 | H7: CTA. MAYOR | I7: 41071005 | K7: TOTAL DE SERVICIO | N7: =+SUM(N4:N6) -> 1
A9: MATERIALES - HH A CERTIFICAR | H9: HES
L10: Disponibilidad | N10: 1
A11: TOTAL A CERTIFICAR | E11: =+E5*E7 -> 30832490 | L11: Plan correctivo | N11: 1
A13: IMPUTACIONES SERVICIO BASICO MENSUAL
D14: PLANTA | F14: CUENTA | G14: CeCO | H14: % | I14: Monto
D15: PLANTA CELULOSA | F15: 41071005 | G15: APCES1-348 | H15: 12 | I15: =+($E$11/100)*H15 -> 3699898.8 | J15: =+H15/100 -> 0.12
D16: FORESTAL | F16: 41071005 | G16: APFES1-714 | H16: 4.57 | I16: =+($E$11/100)*H16 -> 1409044.8 | J16: =+H16/100 -> 0.0457
D17: FORESTAL | F17: 41111002 | G17: APFES1-201 | H17: 13.17 | I17: =+($E$11/100)*H17 -> 4060638.9 | J17: =+H17/100 -> 0.1317
D18: FORESTAL | F18: 41071005 | G18: APFES1-713 | H18: 3.48 | I18: =+($E$11/100)*H18 -> 1072970.6 | J18: =+H18/100 -> 0.0348
D19: FORESTAL | F19: 41071005 | G19: APFES1-701 | H19: 5.31 | I19: =+($E$11/100)*H19 -> 1637205.2 | J19: =+H19/100 -> 0.0531
D20: FORESTAL | F20: 41071005 | G20: APFES1-711 | H20: 3.77 | I20: =+($E$11/100)*H20 -> 1162384.9 | J20: =+H20/100 -> 0.0377
D21: SSGG CELULOSA | F21: 41071005 | G21: APOBA1-871 | H21: 8.46 | I21: =+($E$11/100)*H21 -> 2608428.6 | J21: =+H21/100 -> 0.0846
D22: SSGG BOSSEETTI | F22: 41071005 | G22: APOBA1-872 | H22: 11.16 | I22: =+($E$11/100)*H22 -> 3440905.8 | J22: =+H22/100 -> 0.1116
D23: EXPEDICION BOSSETTI | F23: 41071005 | G23: APOBA1-867 | H23: 5 | I23: =+($E$11/100)*H23 -> 1541624.5 | J23: =+H23/100 -> 0.05
D24: HOTEL PTO. PIRAY | F24: 41071005 | G24: APOBA1-875 | H24: 10.56 | I24: =+($E$11/100)*H24 -> 3255910.9 | J24: =+H24/100 -> 0.1056
D25: SSGG YPORA | F25: 41071005 | G25: APOBA1-885 | H25: 9.96 | I25: =+($E$11/100)*H25 -> 3070916 | J25: =+H25/100 -> 0.0996
D26: HOSTERIA | F26: 41071005 | G26: APOBA1-886 | H26: 12.56 | I26: =+($E$11/100)*H26 -> 3872560.7 | J26: =+H26/100 -> 0.1256
A27: TOTAL GRAL | H27: 100 | I27: =+SUM(I15:I26) -> 30832490
A31: % CUMPLIMINETO AIRE | D31: =+(D74+H74+L74+P74)/4 -> 0.4726175 | N31: OBJETIVO | O31: MENSUAL | P31: TRIMESTRALES | Q31: SEMESTRAL | R31: ANUAL | S31: TOTAL/MES
A32: % DE INCIDENCIA DEL SERVICIO | D32: 0.5 | N32: Celulosa | O32: 18 | P32: 4 | Q32: 15 | R32: 43 | S32: =+SUM(O32:R32) -> 80
N33: Bossetti | O33: 5 | P33: 1 | Q33: 8 | R33: 10 | S33: =+SUM(O33:R33) -> 24
N34: Y-Pora | O34: 7 | P34: 5 | Q34: 30 | R34: 41 | S34: =+SUM(O34:R34) -> 83
N35: Piray | O35: 6 | P35: 1 | Q35: 9 | R35: 28 | S35: =+SUM(O35:R35) -> 44
N37: TOTAL/MES | O37: =SUM(O32:O36) -> 36 | P37: =+SUM(P32:P36)/3 -> 3.6666667 | Q37: =+SUM(Q32:Q36)/6 -> 10.333333 | R37: =+SUM(R32:R36)/12 -> 10.166667 | S37: =+SUM(S32:S36) -> 231
A39: INTERVENSIONES REFRIGERACION
A40: N° | B40: MES | C40: MENSUALES 36 equipos | E40: TRIMESTRALES ( 11 equipos) | I40: SEMESTRALES (62 equipos) | M40: ANUALES ( 122 equipos) | Q40: INTERVENCIONES
C41: INTER | D41: CUMPL | E41: INTER | F41: ACUM | G41: ACUM PLA | H41: CUMPL | I41: Intervensiones | J41: Acumulado | K41: Acum. Plan. | L41: Cumplimiento | M41: Intervensiones | N41: Acumulado | O41: Acum. Plan. | P41: Cumplimiento | Q41: Planificadas | R41: No Planif | S41: TOTAL
A42: 1 | B42: 44287 | C42: =COUNTIF('BASE AA'!#REF!,"=1") -> #REF! | D42: =+C42/$O$37 -> #REF! | E42: =COUNTIF('BASE AA'!#REF!,"=2") -> #REF! | F42: =+E42 -> #REF! | G42: =+P37 -> 3.6666667 | H42: =F42/G42 -> #REF! | I42: =COUNTIF('BASE AA'!#REF!,"=3") -> #REF! | J42: =+I42 -> #REF! | K42: =+Q37 -> 10.333333 | L42: =J42/K42 -> #REF! | M42: =COUNTIF('BASE AA'!#REF!,"=4") -> #REF! | N42: =+M42 -> #REF! | O42: =+R37 -> 10.166667 | P42: =+N42/O42 -> #REF! | Q42: =+I42+E42+C42+M42 -> #REF! | R42: 8 | S42: =+R42+Q42 -> #REF!
A43: =+A42+1 -> 2 | B43: 44317 | C43: =COUNTIF('BASE AA'!#REF!,"=1") -> #REF! | D43: =+C43/$O$37 -> #REF! | E43: =COUNTIF('BASE AA'!#REF!,"=2") -> #REF! | F43: =+F42+E43 -> #REF! | G43: =A43*$G$42 -> 7.3333333 | H43: =F43/G43 -> #REF! | I43: =COUNTIF('BASE AA'!#REF!,"=3") -> #REF! | J43: =+J42+I43 -> #REF! | K43: =A43*$K$42 -> 20.666667 | L43: =J43/K43 -> #REF! | M43: =COUNTIF('BASE AA'!#REF!,"=4") -> #REF! | N43: =+M43+N42 -> #REF! | O43: =+A43*$O$42 -> 20.333333 | P43: =+N43/O43 -> #REF! | Q43: =+I43+E43+C43+M43 -> #REF! | R43: 7 | S43: =+R43+Q43 -> #REF!
A44: =+A43+1 -> 3 | B44: 44348 | C44: =COUNTIF('BASE AA'!#REF!,"=1") -> #REF! | D44: =+C44/$O$37 -> #REF! | E44: =COUNTIF('BASE AA'!#REF!,"=2") -> #REF! | F44: =+F43+E44 -> #REF! | G44: =A44*$G$42 -> 11 | H44: =F44/G44 -> #REF! | I44: =COUNTIF('BASE AA'!#REF!,"=3") -> #REF! | J44: =+J43+I44 -> #REF! | K44: =A44*$K$42 -> 31 | L44: =J44/K44 -> #REF! | M44: =COUNTIF('BASE AA'!#REF!,"=4") -> #REF! | N44: =+M44+N43 -> #REF! | O44: =+A44*$O$42 -> 30.5 | P44: =+N44/O44 -> #REF! | Q44: =+I44+E44+C44+M44 -> #REF! | R44: 4 | S44: =+R44+Q44 -> #REF!
A45: =+A44+1 -> 4 | B45: 44378 | C45: =COUNTIF('BASE AA'!#REF!,"=1") -> #REF! | D45: =+C45/$O$37 -> #REF! | E45: =COUNTIF('BASE AA'!#REF!,"=2") -> #REF! | F45: =+E45 -> #REF! | G45: =+P37 -> 3.6666667 | H45: =F45/G45 -> #REF! | I45: =COUNTIF('BASE AA'!#REF!,"=3") -> #REF! | J45: =+J44+I45 -> #REF! | K45: =A45*$K$42 -> 41.333333 | L45: =J45/K45 -> #REF! | M45: =COUNTIF('BASE AA'!#REF!,"=4") -> #REF! | N45: =+M45+N44 -> #REF! | O45: =+A45*$O$42 -> 40.666667 | P45: =+N45/O45 -> #REF! | Q45: =+I45+E45+C45+M45 -> #REF! | R45: 8 | S45: =+R45+Q45 -> #REF!
A46: =+A45+1 -> 5 | B46: 44409 | C46: =COUNTIF('BASE AA'!#REF!,"=1") -> #REF! | D46: =+C46/$O$37 -> #REF! | E46: =COUNTIF('BASE AA'!#REF!,"=2") -> #REF! | F46: =+F45+E46 -> #REF! | G46: =+G45*A43 -> 7.3333333 | H46: =F46/G46 -> #REF! | I46: =COUNTIF('BASE AA'!#REF!,"=3") -> #REF! | J46: =+J45+I46 -> #REF! | K46: =A46*$K$42 -> 51.666667 | L46: =J46/K46 -> #REF! | M46: =COUNTIF('BASE AA'!#REF!,"=4") -> #REF! | N46: =+M46+N45 -> #REF! | O46: =+A46*$O$42 -> 50.833333 | P46: =+N46/O46 -> #REF! | Q46: =+I46+E46+C46+M46 -> #REF! | R46: 10 | S46: =+R46+Q46 -> #REF!
A47: =+A46+1 -> 6 | B47: 44440 | C47: =COUNTIF('BASE AA'!#REF!,"=1") -> #REF! | D47: =+C47/$O$37 -> #REF! | E47: 12 | F47: =+F46+E47 -> #REF! | G47: =+G45*A44 -> 11 | H47: =F47/G47 -> #REF! | I47: =COUNTIF('BASE AA'!#REF!,"=3") -> #REF! | J47: =+J46+I47 -> #REF! | K47: =A47*$K$42 -> 62 | L47: =J47/K47 -> #REF! | M47: =COUNTIF('BASE AA'!#REF!,"=4") -> #REF! | N47: =+M47+N46 -> #REF! | O47: =+A47*$O$42 -> 61 | P47: =+N47/O47 -> #REF! | Q47: =+I47+E47+C47+M47 -> #REF! | R47: 19 | S47: =+R47+Q47 -> #REF!
A48: =+A47+1 -> 7 | B48: 44470 | C48: =COUNTIF('BASE AA'!#REF!,"=1") -> #REF! | D48: =+C48/$O$37 -> #REF! | E48: 9 | F48: =+E48 -> 9 | G48: =+P37 -> 3.6666667 | H48: =F48/G48 -> 2.4545455 | I48: =COUNTIF('BASE AA'!#REF!,"=3") -> #REF! | J48: =+I48 -> #REF! | K48: 14 | L48: =J48/K48 -> #REF! | M48: =COUNTIF('BASE AA'!#REF!,"=4") -> #REF! | N48: =+M48+N47 -> #REF! | O48: =+A48*$O$42 -> 71.166667 | P48: =+N48/O48 -> #REF! | Q48: =+I48+E48+C48+M48 -> #REF! | R48: 21 | S48: =+R48+Q48 -> #REF!
A49: =+A48+1 -> 8 | B49: 44501 | C49: =COUNTIF('BASE AA'!#REF!,"=1") -> #REF! | D49: =+C49/$O$37 -> #REF! | E49: =COUNTIF('BASE AA'!#REF!,"=2") -> #REF! | F49: =+F48+E49 -> #REF! | G49: =+G48*A43 -> 7.3333333 | H49: =F49/G49 -> #REF! | I49: =COUNTIF('BASE AA'!#REF!,"=3") -> #REF! | J49: =+J48+I49 -> #REF! | K49: 28 | L49: =J49/K49 -> #REF! | M49: =COUNTIF('BASE AA'!#REF!,"=4") -> #REF! | N49: =+M49+N48 -> #REF! | O49: =+A49*$O$42 -> 81.333333 | P49: =+N49/O49 -> #REF! | Q49: =+I49+E49+C49+M49 -> #REF! | R49: 20 | S49: =+R49+Q49 -> #REF!
A50: =+A49+1 -> 9 | B50: 44531 | C50: =COUNTIF('BASE AA'!#REF!,"=1") -> #REF! | D50: =+C50/$O$37 -> #REF! | E50: =COUNTIF('BASE AA'!#REF!,"=2") -> #REF! | F50: =+F49+E50 -> #REF! | G50: =+G48*A44 -> 11 | H50: =F50/G50 -> #REF! | I50: =COUNTIF('BASE AA'!#REF!,"=3") -> #REF! | J50: =+J49+I50 -> #REF! | K50: 42 | L50: =J50/K50 -> #REF! | M50: =COUNTIF('BASE AA'!#REF!,"=4") -> #REF! | N50: =+M50+N49 -> #REF! | O50: =+A50*$O$42 -> 91.5 | P50: =+N50/O50 -> #REF! | Q50: =+I50+E50+C50+M50 -> #REF! | R50: 17 | S50: =+R50+Q50 -> #REF!
A51: =+A50+1 -> 10 | B51: 44562 | C51: =COUNTIF('BASE AA'!#REF!,"=1") -> #REF! | D51: =+C51/$O$37 -> #REF! | E51: =COUNTIF('BASE AA'!#REF!,"=2") -> #REF! | F51: =+E51 -> #REF! | G51: =+P37 -> 3.6666667 | H51: =F51/G51 -> #REF! | I51: =COUNTIF('BASE AA'!#REF!,"=3") -> #REF! | J51: =+J50+I51 -> #REF! | K51: 56 | L51: =J51/K51 -> #REF! | M51: =COUNTIF('BASE AA'!#REF!,"=4") -> #REF! | N51: =+M51+N50 -> #REF! | O51: =+A51*$O$42 -> 101.66667 | P51: =+N51/O51 -> #REF! | Q51: =+I51+E51+C51+M51 -> #REF! | R51: 21 | S51: =+R51+Q51 -> #REF!
A52: =+A51+1 -> 11 | B52: 44593 | C52: =COUNTIF('BASE AA'!#REF!,"=1") -> #REF! | D52: =+C52/$O$37 -> #REF! | E52: =COUNTIF('BASE AA'!#REF!,"=2") -> #REF! | F52: =+F51+E52 -> #REF! | G52: =+G51*A43 -> 7.3333333 | H52: =F52/G52 -> #REF! | I52: =COUNTIF('BASE AA'!#REF!,"=3") -> #REF! | J52: =+J51+I52 -> #REF! | K52: 70 | L52: =J52/K52 -> #REF! | M52: =COUNTIF('BASE AA'!#REF!,"=4") -> #REF! | N52: =+M52+N51 -> #REF! | O52: =+A52*$O$42 -> 111.83333 | P52: =+N52/O52 -> #REF! | Q52: =+I52+E52+C52+M52 -> #REF! | R52: 17 | S52: =+R52+Q52 -> #REF!
A53: =+A52+1 -> 12 | B53: 44621 | C53: =COUNTIF('BASE AA'!#REF!,"=1") -> #REF! | D53: =+C53/$O$37 -> #REF! | E53: =COUNTIF('BASE AA'!#REF!,"=2") -> #REF! | F53: =+F52+E53 -> #REF! | G53: =+G51*A44 -> 11 | H53: =F53/G53 -> #REF! | I53: =COUNTIF('BASE AA'!#REF!,"=3") -> #REF! | J53: =+J52+I53 -> #REF! | K53: 84 | L53: =J53/K53 -> #REF! | M53: =COUNTIF('BASE AA'!#REF!,"=4") -> #REF! | N53: =+M53+N52 -> #REF! | O53: =+A53*$O$42 -> 122 | P53: =+N53/O53 -> #REF! | Q53: =+I53+E53+C53+M53 -> #REF! | R53: =COUNTIF(CORRECTIVOS!B:F,CORRECTIVOS!A$5) -> 0 | S53: =+R53+Q53 -> #REF!
A54: 1 | B54: 44652 | C54: =COUNTIF('BASE AA'!#REF!,"=1") -> #REF! | D54: =+C54/$O$37 -> #REF! | E54: =COUNTIF('BASE AA'!#REF!,"=2") -> #REF! | F54: =+E54 -> #REF! | G54: =+$P$37 -> 3.6666667 | H54: =F54/G54 -> #REF! | I54: =COUNTIF('BASE AA'!#REF!,"=3") -> #REF! | J54: =+I54 -> #REF! | K54: =+$Q$37 -> 10.333333 | L54: =J54/K54 -> #REF! | M54: =COUNTIF('BASE AA'!#REF!,"=4") -> #REF! | N54: =+M54 -> #REF! | O54: =+$R$37 -> 10.166667 | P54: =+N54/O54 -> #REF! | Q54: =+I54+E54+C54+M54 -> #REF! | R54: 13 | S54: =+R54+Q54 -> #REF!
A55: =+A54+1 -> 2 | B55: 44682 | C55: =COUNTIF('BASE AA'!#REF!,"=1") -> #REF! | D55: =+C55/$O$37 -> #REF! | E55: =COUNTIF('BASE AA'!#REF!,"=2") -> #REF! | F55: =+F54+E55 -> #REF! | G55: =2*$P$37 -> 7.3333333 | H55: =F55/G55 -> #REF! | I55: =COUNTIF('BASE AA'!#REF!,"=3") -> #REF! | J55: =+J54+I55 -> #REF! | K55: =2*$Q$37 -> 20.666667 | L55: =J55/K55 -> #REF! | M55: =COUNTIF('BASE AA'!#REF!,"=4") -> #REF! | N55: =+M55+N54 -> #REF! | O55: =+A55*$R$37 -> 20.333333 | P55: =+N55/O55 -> #REF! | Q55: =+I55+E55+C55+M55 -> #REF! | R55: 13 | S55: =+R55+Q55 -> #REF!
A56: =+A55+1 -> 3 | B56: 44713 | C56: =COUNTIF('BASE AA'!#REF!,"=1") -> #REF! | D56: =+C56/$O$37 -> #REF! | E56: =COUNTIF('BASE AA'!#REF!,"=2") -> #REF! | F56: =+F55+E56 -> #REF! | G56: =3*$P$37 -> 11 | H56: =F56/G56 -> #REF! | I56: =COUNTIF('BASE AA'!#REF!,"=3") -> #REF! | J56: =+J55+I56 -> #REF! | K56: =3*$Q$37 -> 31 | L56: =J56/K56 -> #REF! | M56: =COUNTIF('BASE AA'!#REF!,"=4") -> #REF! | N56: =+M56+N55 -> #REF! | O56: =+A56*$R$37 -> 30.5 | P56: =+N56/O56 -> #REF! | Q56: =+I56+E56+C56+M56 -> #REF! | R56: 9 | S56: =+R56+Q56 -> #REF!
A57: =+A56+1 -> 4 | B57: 44743 | C57: =COUNTIF('BASE AA'!#REF!,"=1") -> #REF! | D57: =+C57/$O$37 -> #REF! | E57: =COUNTIF('BASE AA'!#REF!,"=2") -> #REF! | F57: =+E57 -> #REF! | G57: =+$P$37 -> 3.6666667 | H57: =F57/G57 -> #REF! | I57: =COUNTIF('BASE AA'!#REF!,"=3") -> #REF! | J57: =+J56+I57 -> #REF! | K57: =4*$Q$37 -> 41.333333 | L57: =J57/K57 -> #REF! | M57: =COUNTIF('BASE AA'!#REF!,"=4") -> #REF! | N57: =+M57+N56 -> #REF! | O57: =+A57*$R$37 -> 40.666667 | P57: =+N57/O57 -> #REF! | Q57: =+I57+E57+C57+M57 -> #REF! | R57: 10 | S57: =+R57+Q57 -> #REF!
A58: =+A57+1 -> 5 | B58: 44774 | C58: =COUNTIF('BASE AA'!#REF!,"=1") -> #REF! | D58: =+C58/$O$37 -> #REF! | E58: =COUNTIF('BASE AA'!#REF!,"=2") -> #REF! | F58: =+F57+E58 -> #REF! | G58: =2*$P$37 -> 7.3333333 | H58: =F58/G58 -> #REF! | I58: =COUNTIF('BASE AA'!#REF!,"=3") -> #REF! | J58: =+J57+I58 -> #REF! | K58: =5*$Q$37 -> 51.666667 | L58: =J58/K58 -> #REF! | M58: =COUNTIF('BASE AA'!#REF!,"=4") -> #REF! | N58: =+M58+N57 -> #REF! | O58: =+A58*$R$37 -> 50.833333 | P58: =+N58/O58 -> #REF! | Q58: =+I58+E58+C58+M58 -> #REF! | R58: 9 | S58: =+R58+Q58 -> #REF!
A59: =+A58+1 -> 6 | B59: 44805 | C59: =COUNTIF('BASE AA'!#REF!,"=1") -> #REF! | D59: =+C59/$O$37 -> #REF! | E59: =COUNTIF('BASE AA'!#REF!,"=2") -> #REF! | F59: =+F58+E59 -> #REF! | G59: =3*$P$37 -> 11 | H59: =F59/G59 -> #REF! | I59: =COUNTIF('BASE AA'!#REF!,"=3") -> #REF! | J59: =+J58+I59 -> #REF! | K59: =6*$Q$37 -> 62 | L59: =J59/K59 -> #REF! | M59: =COUNTIF('BASE AA'!#REF!,"=4") -> #REF! | N59: =+M59+N58 -> #REF! | O59: =+A59*$R$37 -> 61 | P59: =+N59/O59 -> #REF! | Q59: =+I59+E59+C59+M59 -> #REF! | R59: 5 | S59: =+R59+Q59 -> #REF!
A60: =+A59+1 -> 7 | B60: 44835 | C60: =COUNTIF('BASE AA'!#REF!,"=1") -> #REF! | D60: =+C60/$O$37 -> #REF! | E60: =COUNTIF('BASE AA'!#REF!,"=2") -> #REF! | F60: =+E60 -> #REF! | G60: =+$P$37 -> 3.6666667 | H60: =F60/G60 -> #REF! | I60: =COUNTIF('BASE AA'!#REF!,"=3") -> #REF! | J60: =+I60 -> #REF! | K60: =+$Q$37 -> 10.333333 | L60: =J60/K60 -> #REF! | M60: =COUNTIF('BASE AA'!#REF!,"=4") -> #REF! | N60: =+M60+N59 -> #REF! | O60: =+A60*$R$37 -> 71.166667 | P60: =+N60/O60 -> #REF! | Q60: =+I60+E60+C60+M60 -> #REF! | R60: 8 | S60: =+R60+Q60 -> #REF!
A61: =+A60+1 -> 8 | B61: 44866 | C61: =COUNTIF('BASE AA'!#REF!,"=1") -> #REF! | D61: =+C61/$O$37 -> #REF! | E61: =COUNTIF('BASE AA'!#REF!,"=2") -> #REF! | F61: =+F60+E61 -> #REF! | G61: =2*$P$37 -> 7.3333333 | H61: =F61/G61 -> #REF! | I61: =COUNTIF('BASE AA'!#REF!,"=3") -> #REF! | J61: =+J60+I61 -> #REF! | K61: =2*$Q$37 -> 20.666667 | L61: =J61/K61 -> #REF! | M61: =COUNTIF('BASE AA'!#REF!,"=4") -> #REF! | N61: =+M61+N60 -> #REF! | O61: =+A61*$R$37 -> 81.333333 | P61: =+N61/O61 -> #REF! | Q61: =+I61+E61+C61+M61 -> #REF! | R61: 7 | S61: =+R61+Q61 -> #REF!
A62: =+A61+1 -> 9 | B62: 44896 | C62: =COUNTIF('BASE AA'!#REF!,"=1") -> #REF! | D62: =+C62/$O$37 -> #REF! | E62: =COUNTIF('BASE AA'!#REF!,"=2") -> #REF! | F62: =+F61+E62 -> #REF! | G62: =3*$P$37 -> 11 | H62: =F62/G62 -> #REF! | I62: =COUNTIF('BASE AA'!#REF!,"=3") -> #REF! | J62: =+J61+I62 -> #REF! | K62: =3*$Q$37 -> 31 | L62: =J62/K62 -> #REF! | M62: =COUNTIF('BASE AA'!#REF!,"=4") -> #REF! | N62: =+M62+N61 -> #REF! | O62: =+A62*$R$37 -> 91.5 | P62: =+N62/O62 -> #REF! | Q62: =+I62+E62+C62+M62 -> #REF! | R62: 14 | S62: =+R62+Q62 -> #REF!
A63: =+A62+1 -> 10 | B63: 44927 | C63: =COUNTIF('BASE AA'!#REF!,"=1") -> #REF! | D63: =+C63/$O$37 -> #REF! | E63: =COUNTIF('BASE AA'!#REF!,"=2") -> #REF! | F63: =+E63 -> #REF! | G63: =+$P$37 -> 3.6666667 | H63: =F63/G63 -> #REF! | I63: =COUNTIF('BASE AA'!#REF!,"=3") -> #REF! | J63: =+J62+I63 -> #REF! | K63: =4*$Q$37 -> 41.333333 | L63: =J63/K63 -> #REF! | M63: =COUNTIF('BASE AA'!#REF!,"=4") -> #REF! | N63: =+M63+N62 -> #REF! | O63: =+A63*$R$37 -> 101.66667 | P63: =+N63/O63 -> #REF! | Q63: =+I63+E63+C63+M63 -> #REF! | R63: 16 | S63: =+R63+Q63 -> #REF!
A64: =+A63+1 -> 11 | B64: 44958 | C64: =COUNTIF('BASE AA'!#REF!,"=1") -> #REF! | D64: =+C64/$O$37 -> #REF! | E64: =COUNTIF('BASE AA'!#REF!,"=2") -> #REF! | F64: =+F63+E64 -> #REF! | G64: =2*$P$37 -> 7.3333333 | H64: =F64/G64 -> #REF! | I64: =COUNTIF('BASE AA'!#REF!,"=3") -> #REF! | J64: =+J63+I64 -> #REF! | K64: =5*$Q$37 -> 51.666667 | L64: =J64/K64 -> #REF! | M64: =COUNTIF('BASE AA'!#REF!,"=4") -> #REF! | N64: =+M64+N63 -> #REF! | O64: =+A64*$R$37 -> 111.83333 | P64: =+N64/O64 -> #REF! | Q64: =+I64+E64+C64+M64 -> #REF! | R64: 11 | S64: =+R64+Q64 -> #REF!
A65: =+A64+1 -> 12 | B65: 44986 | C65: =COUNTIF('BASE AA'!#REF!,"=1") -> #REF! | D65: =+C65/$O$37 -> #REF! | E65: =COUNTIF('BASE AA'!#REF!,"=2") -> #REF! | F65: =+F64+E65 -> #REF! | G65: =3*$P$37 -> 11 | H65: =F65/G65 -> #REF! | I65: =COUNTIF('BASE AA'!#REF!,"=3") -> #REF! | J65: =+J64+I65 -> #REF! | K65: =6*$Q$37 -> 62 | L65: =J65/K65 -> #REF! | M65: =COUNTIF('BASE AA'!#REF!,"=4") -> #REF! | N65: =+M65+N64 -> #REF! | O65: =+A65*$R$37 -> 122 | P65: =+N65/O65 -> #REF! | Q65: =+I65+E65+C65+M65 -> #REF! | R65: =COUNTIF(CORRECTIVOS!B:F,CORRECTIVOS!A$5) -> 0 | S65: =+R65+Q65 -> #REF!
A66: 1 | B66: 45962 | C66: =COUNTIF('BASE AA'!U2:U317,"=1") -> 36 | D66: =+C66/36 -> 1 | E66: =COUNTIF('BASE AA'!U2:U317,"=2") -> 0 | F66: =+E66+F77 -> 3 | G66: =2*P$37 -> 7.3333333 | H66: =F66/G66 -> 0.40909091 | I66: =COUNTIF('BASE AA'!U2:U317,"=3") -> 5 | J66: =+I66+J77 -> 11 | K66: =+Q$37*A66 -> 10.333333 | L66: =J66/K66 -> 1.0645161 | M66: =COUNTIF('BASE AA'!U2:IU317,"=4") -> 13 | N66: =+M66+N77 -> 80 | O66: =+$R$37*8 -> 81.333333 | P66: =+N66/O66 -> 0.98360656 | Q66: =+I66+E66+C66+M66 -> 54 | S66: =+R66+Q66 -> 54
A67: =+A66+1 -> 2 | B67: 45992 | C67: =COUNTIF('BASE AA'!V3:V318,"=1") -> 36 | D67: =+C67/36 -> 1 | E67: =COUNTIF('BASE AA'!V3:V318,"=2") -> 4 | F67: =+E67+F66 -> 7 | G67: =3*P$37 -> 11 | H67: =F67/G67 -> 0.63636364 | I67: =COUNTIF('BASE AA'!V3:V318,"=3") -> 3 | J67: =+I67+J66 -> 14 | K67: =+Q$37*A67 -> 20.666667 | L67: =J67/K67 -> 0.67741935 | M67: =COUNTIF('BASE AA'!V3:IV318,"=4") -> 4 | N67: =+M67+N66 -> 84 | O67: =+$R$37*9 -> 91.5 | P67: =+N67/O67 -> 0.91803279 | Q67: =+I67+E67+C67+M67 -> 47 | R67: 14 | S67: =+Q67+R67 -> 61
A68: =+A67+1 -> 3 | B68: 46023 | C68: =COUNTIF('BASE AA'!W4:W319,"=1") -> 21 | D68: =+C68/36 -> 0.58333333 | E68: =COUNTIF('BASE AA'!W4:W319,"=2") -> 0 | F68: =+E68 -> 0 | G68: =1*P$37 -> 3.6666667 | H68: =F68/G68 -> 0 | I68: =COUNTIF('BASE AA'!W4:W319,"=3") -> 0 | J68: =+I68+J67 -> 14 | K68: =+Q$37*A68 -> 31 | L68: =+J68/K68 -> 0.4516129 | M68: =COUNTIF('BASE AA'!W4:X319,"=4") -> 3 | N68: =+M68+N67 -> 87 | O68: =+$R$37*10 -> 101.66667 | P68: =+N68/O68 -> 0.8557377 | Q68: =+I68+E68+C68+M68 -> 24 | R68: 15 | S68: =+Q68+R68 -> 39
A69: =+A68+1 -> 4 | B69: 46054 | C69: =COUNTIF('BASE AA'!X5:X320,"=1") -> 11 | D69: =+C69/36 -> 0.30555556 | E69: =COUNTIF('BASE AA'!X5:X320,"=2") -> 0 | F69: =+E69+F68 -> 0 | G69: =2*P$37 -> 7.3333333 | H69: =F69/G69 -> 0 | I69: =COUNTIF('BASE AA'!X5:X320,"=3") -> 0 | J69: =+I69+J68 -> 14 | K69: =+Q$37*A69 -> 41.333333 | L69: =+J69/K69 -> 0.33870968 | M69: =COUNTIF('BASE AA'!X5:X320,"=4") -> 3 | N69: =+M69+N68 -> 90 | O69: =+$R$37*11 -> 111.83333 | P69: =+N69/O69 -> 0.804769 | Q69: =+I69+E69+C69+M69 -> 14 | R69: 16 | S69: =+Q69+R69 -> 30
A70: =+A69+1 -> 5 | B70: 46082 | E70: =COUNTIF('BASE AA'!W6:W321,"=2") -> 0
A71: =+A70+1 -> 6 | B71: 45748 | C71: =COUNTIF('BASE AA'!N5:N320,"=1") -> 36 | D71: =+C71/36 -> 1 | E71: =COUNTIF('BASE AA'!N7:N322,"=2") -> 4 | F71: =+F70+E71 -> 4 | G71: =+A71*P$37 -> 22 | H71: =F71/G71 -> 0.18181818 | I71: =COUNTIF('BASE AA'!N7:N322,"=3") -> 5 | J71: =+I71 -> 5 | K71: =+Q$37*A71 -> 62 | L71: =J71/K71 -> 0.080645161 | M71: =COUNTIF('BASE AA'!N7:N322,"=4") -> 1 | N71: =+M71 -> 1 | O71: =+$R$37*A71 -> 61 | P71: =+N71/O71 -> 0.016393443 | Q71: =+I71+E71+C71+M71 -> 46 | S71: =+R71+Q71 -> 46
A72: =+A71+1 -> 7 | B72: 45778 | C72: =COUNTIF('BASE AA'!O6:O321,"=1") -> 36 | D72: =+C72/36 -> 1 | E72: =COUNTIF('BASE AA'!O8:O323,"=2") -> 4 | F72: =+F71+E72 -> 8 | G72: =+A72*P$37 -> 25.666667 | H72: =F72/G72 -> 0.31168831 | I72: =COUNTIF('BASE AA'!O8:O323,"=3") -> 15 | J72: =+J71+I72 -> 20 | K72: =+Q$37*A72 -> 72.333333 | L72: =J72/K72 -> 0.2764977 | M72: =COUNTIF('BASE AA'!O3:O323,"=4") -> 15 | N72: =+N71+M72 -> 16 | O72: =+$R$37*A72 -> 71.166667 | P72: =+N72/O72 -> 0.22482436 | Q72: =+I72+E72+C72+M72 -> 70 | S72: =+R72+Q72 -> 70
A73: =+A72+1 -> 8 | B73: 45809 | C73: =COUNTIF('BASE AA'!P2:P322,"=1") -> 36 | D73: =+C73/36 -> 1 | E73: =COUNTIF('BASE AA'!P2:P320,"=2") -> 2 | F73: =+F72+E73 -> 10 | G73: =+A73*P$37 -> 29.333333 | H73: =F73/G73 -> 0.34090909 | I73: =COUNTIF('BASE AA'!P2:P320,"=3") -> 12 | J73: =+J72+I73 -> 32 | K73: =+Q$37*A73 -> 82.666667 | L73: =J73/K73 -> 0.38709677 | M73: =COUNTIF('BASE AA'!P24:P320,"=4") -> 10 | N73: =+N72+M73 -> 26 | O73: =+$R$37*A73 -> 81.333333 | P73: =+N73/O73 -> 0.31967213 | Q73: =+I73+E73+C73+M73 -> 60 | S73: =+R73+Q73 -> 60
A74: =+A73+1 -> 9 | B74: 45839 | C74: =COUNTIF('BASE AA'!Q3:Q323,"=1") -> 36 | D74: =+C74/36 -> 1 | E74: =COUNTIF('BASE AA'!Q3:Q321,"=2") -> 4 | F74: =+E74 -> 4 | G74: =+A74*P$37 -> 33 | H74: =F74/G74 -> 0.12121212 | I74: =COUNTIF('BASE AA'!Q3:Q321,"=3") -> 6 | J74: =+J73+I74 -> 38 | K74: =+Q$37*A74 -> 93 | L74: =J74/K74 -> 0.40860215 | M74: =COUNTIF('BASE AA'!Q25:Q321,"=4") -> 7 | N74: =+N73+M74 -> 33 | O74: =+$R$37*A74 -> 91.5 | P74: =+N74/O74 -> 0.36065574 | Q74: =+I74+E74+C74+M74 -> 53 | S74: =+R74+Q74 -> 53
A75: =+A74+1 -> 10 | B75: 45870 | C75: =COUNTIF('BASE AA'!R4:R324,"=1") -> 36 | D75: =+C75/36 -> 1 | E75: =COUNTIF('BASE AA'!R4:R322,"=2") -> 4 | F75: =+E75+F74 -> 8 | G75: =2*P$37 -> 7.3333333 | H75: =F75/G75 -> 1.0909091 | I75: =COUNTIF('BASE AA'!R4:R322,"=3") -> 12 | J75: =+J74+I75 -> 50 | K75: =+Q$37*5 -> 51.666667 | L75: =J75/K75 -> 0.96774194 | M75: =COUNTIF('BASE AA'!R26:R322,"=4") -> 13 | N75: =+N74+M75 -> 46 | O75: =+$R$37*5 -> 50.833333 | P75: =+N75/O75 -> 0.90491803 | Q75: =+I75+E75+C75+M75 -> 65 | S75: =+R75+Q75 -> 65
A76: =+A75+1 -> 11 | B76: 45901 | C76: =COUNTIF('BASE AA'!S2:S325,"=1") -> 36 | D76: =+C76/36 -> 1 | E76: =COUNTIF('BASE AA'!S2:S323,"=2") -> 3 | F76: =+E76+F75 -> 11 | G76: =2*P$37 -> 7.3333333 | H76: =F76/G76 -> 1.5 | I76: =COUNTIF('BASE AA'!S2:S323,"=3") -> 3 | J76: =+J75+I76 -> 53 | K76: =+Q$37*5 -> 51.666667 | L76: =J76/K76 -> 1.0258065 | M76: =COUNTIF('BASE AA'!S2:S323,"=4") -> 13 | N76: =+N75+M76 -> 59 | O76: =+$R$37*6 -> 61 | P76: =+N76/O76 -> 0.96721311 | Q76: =+I76+E76+C76+M76 -> 55 | S76: =+R76+Q76 -> 55
A77: =+A76+1 -> 12 | B77: 45931 | C77: =COUNTIF('BASE AA'!T3:T326,"=1") -> 36 | D77: =+C77/36 -> 1 | E77: =COUNTIF('BASE AA'!T3:T324,"=2") -> 3 | F77: =+E77 -> 3 | G77: =P$37 -> 3.6666667 | H77: =F77/G77 -> 0.81818182 | I77: =COUNTIF('BASE AA'!T3:T324,"=3") -> 6 | J77: =I77 -> 6 | K77: =+Q37 -> 10.333333 | L77: =J77/K77 -> 0.58064516 | M77: =COUNTIF('BASE AA'!T3:T324,"=4") -> 8 | N77: =+N76+M77 -> 67 | O77: =+$R$37*7 -> 71.166667 | P77: =+N77/O77 -> 0.94145199 | Q77: =+I77+E77+C77+M77 -> 53 | S77: =+R77+Q77 -> 53
A83: % CUMPLIMINETO ELECTRICO | D83: =+(D126+H126+L126+P126)/4 -> 0.47535014 | N83: OBJETIVO | O83: MENSUAL | P83: TRIMESTRALES | Q83: SEMESTRAL | R83: ANUAL | S83: TOTAL/MES
A84: % DE INCIDENCIA DEL SERVICIO | D84: 0.4 | N84: Celulosa | O84: =8+1 -> 9 | P84: 2 | Q84: 3 | R84: 94 | S84: =+SUM(O84:R84) -> 108
N85: Bossetti | O85: 4 | R85: 1
N86: Garita Rta 12 | O86: 6 | R86: 1
N87: Y-Pora | O87: =8+4 -> 12 | R87: 1
N88: Piray | O88: 15 | Q88: 2 | R88: 22 | S88: =+SUM(O88:R88) -> 39
N89: TOTAL/MES | O89: =SUM(O84:O88) -> 46 | P89: =+SUM(P84:P88)/3 -> 0.66666667 | Q89: =+SUM(Q84:Q88)/6 -> 0.83333333 | R89: =+SUM(R84:R88)/12 -> 9.9166667 | S89: =+SUM(S84:S88) -> 147
N90: INTERVENCIONES POR DIA | S90: =+S89/20 -> 7.35
A91: INTERVENSIONES ELECTRICAS
A92: N° | B92: MES | C92: MENSUALES 46 | E92: TRIMESTRALES 2 intervenciones | I92: SEMESTRALES 5 intervenciones | M92: ANUALES 8 intervenciones | Q92: INTERVENSIONES
C93: INTER | D93: CUMPL | E93: INTER | F93: ACUM | G93: ACUM PLA | H93: CUMPL | I93: Intervensiones | J93: Acumulado | K93: Acum. Plan. | L93: Cumplimiento | M93: Intervensiones | N93: Acumulado | O93: Acum. Plan. | P93: Cumplimiento | Q93: Planificadas | R93: No Planif | S93: TOTAL
A94: 1 | B94: 44287 | C94: =COUNTIF('BASE ELEC'!#REF!,"=1") -> #REF! | D94: =+C94/$O$89 -> #REF! | E94: =COUNTIF('BASE ELEC'!#REF!,"=2") -> #REF! | F94: =+E94 -> #REF! | G94: =+P$89 -> 0.66666667 | H94: =+(F94/G94) -> #REF! | I94: =COUNTIF('BASE ELEC'!#REF!,"=3") -> #REF! | J94: =+I94 -> #REF! | K94: =+Q89 -> 0.83333333 | L94: =J94/K94 -> #REF! | M94: =COUNTIF('BASE ELEC'!#REF!,"=4") -> #REF! | N94: =+M94 -> #REF! | O94: =+R89 -> 9.9166667 | P94: =+N94/O94 -> #REF! | Q94: =+I94+E94+C94+M94 -> #REF! | R94: =COUNTIF(CORRECTIVOS!B:F,CORRECTIVOS!#REF!) -> 0 | S94: =+R94+Q94 -> #REF!
A95: =+A94+1 -> 2 | B95: 44317 | C95: =COUNTIF('BASE ELEC'!#REF!,"=1") -> #REF! | D95: =+C95/$O$89 -> #REF! | E95: =COUNTIF('BASE ELEC'!#REF!,"=2") -> #REF! | F95: =+E95+F94 -> #REF! | G95: =+P$89+A$95 -> 2.6666667 | H95: =F95/G95 -> #REF! | I95: =COUNTIF('BASE ELEC'!#REF!,"=3") -> #REF! | J95: =+J94+I95 -> #REF! | K95: =A95*$Q$89 -> 1.6666667 | L95: =J95/K95 -> #REF! | M95: =COUNTIF('BASE ELEC'!#REF!,"=4") -> #REF! | N95: =+M95+N94 -> #REF! | O95: =+A95*$R$89 -> 19.833333 | P95: =+N95/O95 -> #REF! | Q95: =+I95+E95+C95+M95 -> #REF! | R95: 24 | S95: =+R95+Q95 -> #REF!
A96: =+A95+1 -> 3 | B96: 44348 | C96: =COUNTIF('BASE ELEC'!#REF!,"=1") -> #REF! | D96: =+C96/$O$89 -> #REF! | E96: =COUNTIF('BASE ELEC'!#REF!,"=2") -> #REF! | F96: =+F95+E96 -> #REF! | G96: =+P$89+A$96 -> 3.6666667 | H96: 1 | I96: =COUNTIF('BASE ELEC'!#REF!,"=3") -> #REF! | J96: =+J95+I96 -> #REF! | K96: =A96*$Q$89 -> 2.5 | L96: =J96/K96 -> #REF! | M96: =COUNTIF('BASE ELEC'!#REF!,"=4") -> #REF! | N96: =+M96+N95 -> #REF! | O96: =+A96*$R$89 -> 29.75 | P96: =+N96/O96 -> #REF! | Q96: =+I96+E96+C96+M96 -> #REF! | R96: 26 | S96: =+R96+Q96 -> #REF!
A97: =+A96+1 -> 4 | B97: 44378 | C97: =COUNTIF('BASE ELEC'!#REF!,"=1") -> #REF! | D97: =+C97/$O$89 -> #REF! | E97: =COUNTIF('BASE ELEC'!#REF!,"=2") -> #REF! | F97: =+E97 -> #REF! | G97: =+P$89 -> 0.66666667 | H97: =F97/G97 -> #REF! | I97: =COUNTIF('BASE ELEC'!#REF!,"=3") -> #REF! | J97: =+J96+I97 -> #REF! | K97: =A97*$Q$89 -> 3.3333333 | L97: =J97/K97 -> #REF! | M97: =COUNTIF('BASE ELEC'!#REF!,"=4") -> #REF! | N97: =+M97+N96 -> #REF! | O97: =+A97*$R$89 -> 39.666667 | P97: =+N97/O97 -> #REF! | Q97: =+I97+E97+C97+M97 -> #REF! | R97: 22 | S97: =+R97+Q97 -> #REF!
A98: =+A97+1 -> 5 | B98: 44409 | C98: =COUNTIF('BASE ELEC'!#REF!,"=1") -> #REF! | D98: =+C98/$O$89 -> #REF! | E98: =COUNTIF('BASE ELEC'!#REF!,"=2") -> #REF! | F98: =+F97+E98 -> #REF! | G98: =+P$89+A$95 -> 2.6666667 | H98: =F98/G98 -> #REF! | I98: =COUNTIF('BASE ELEC'!#REF!,"=3") -> #REF! | J98: =+J97+I98 -> #REF! | K98: =A98*$Q$89 -> 4.1666667 | L98: =J98/K98 -> #REF! | M98: =COUNTIF('BASE ELEC'!#REF!,"=4") -> #REF! | N98: =+M98+N97 -> #REF! | O98: =+A98*$R$89 -> 49.583333 | P98: =+N98/O98 -> #REF! | Q98: =+I98+E98+C98+M98 -> #REF! | R98: 15 | S98: =+R98+Q98 -> #REF!
A99: =+A98+1 -> 6 | B99: 44440 | C99: =COUNTIF('BASE ELEC'!#REF!,"=1") -> #REF! | D99: =+C99/$O$89 -> #REF! | E99: =COUNTIF('BASE ELEC'!#REF!,"=2") -> #REF! | F99: =+F98+E99 -> #REF! | G99: =+P$89+A$96 -> 3.6666667 | H99: 1 | I99: =COUNTIF('BASE ELEC'!#REF!,"=3") -> #REF! | J99: =+J98+I99 -> #REF! | K99: =A99*$Q$89 -> 5 | L99: 1 | M99: =COUNTIF('BASE ELEC'!#REF!,"=4") -> #REF! | N99: =+M99+N98 -> #REF! | O99: =+A99*$R$89 -> 59.5 | P99: =+N99/O99 -> #REF! | Q99: =+I100+E99+C99+M99 -> #REF! | R99: 23 | S99: =+R99+Q99 -> #REF!
A100: =+A99+1 -> 7 | B100: 44470 | C100: =COUNTIF('BASE ELEC'!#REF!,"=1") -> #REF! | D100: =+C100/$O$89 -> #REF! | E100: =COUNTIF('BASE ELEC'!#REF!,"=2") -> #REF! | F100: =+E100 -> #REF! | G100: 1 | H100: =F100/G100 -> #REF! | I100: 3 | J100: =+I100+I99 -> #REF! | K100: =+Q89 -> 0.83333333 | L100: =J100/K100 -> #REF! | M100: =COUNTIF('BASE ELEC'!#REF!,"=4") -> #REF! | N100: =+M100+N99 -> #REF! | O100: =+A100*$R$89 -> 69.416667 | P100: =+N100/O100 -> #REF! | Q100: =+I100+E100+C100+M100 -> #REF! | R100: 20 | S100: =+R100+Q100 -> #REF!
A101: =+A100+1 -> 8 | B101: 44501 | C101: =COUNTIF('BASE ELEC'!#REF!,"=1") -> #REF! | D101: =+C101/$O$89 -> #REF! | E101: =COUNTIF('BASE ELEC'!#REF!,"=2") -> #REF! | F101: =+F100+E101 -> #REF! | G101: 3 | H101: =F101/G101 -> #REF! | I101: =COUNTIF('BASE ELEC'!#REF!,"=3") -> #REF! | J101: =+J100+I101 -> #REF! | K101: =A95*$Q$89 -> 1.6666667 | L101: =J101/K101 -> #REF! | M101: =COUNTIF('BASE ELEC'!#REF!,"=4") -> #REF! | N101: =+M101+N100 -> #REF! | O101: =+A101*$R$89 -> 79.333333 | P101: =+N101/O101 -> #REF! | Q101: =+I101+E101+C101+M101 -> #REF! | R101: 20 | S101: =+R101+Q101 -> #REF!
A102: =+A101+1 -> 9 | B102: 44531 | C102: =COUNTIF('BASE ELEC'!#REF!,"=1") -> #REF! | D102: =+C102/$O$89 -> #REF! | E102: =COUNTIF('BASE ELEC'!#REF!,"=2") -> #REF! | F102: =+F101+E102 -> #REF! | G102: 4 | H102: =F102/G102 -> #REF! | I102: =COUNTIF('BASE ELEC'!#REF!,"=3") -> #REF! | J102: =+J101+I102 -> #REF! | K102: =A96*$Q$89 -> 2.5 | L102: =J102/K102 -> #REF! | M102: =COUNTIF('BASE ELEC'!#REF!,"=4") -> #REF! | N102: =+M102+N101 -> #REF! | O102: =+A102*$R$89 -> 89.25 | P102: =+N102/O102 -> #REF! | Q102: =+I102+E102+C102+M102 -> #REF! | R102: 22 | S102: =+R102+Q102 -> #REF!
A103: =+A102+1 -> 10 | B103: 44562 | C103: =COUNTIF('BASE ELEC'!#REF!,"=1") -> #REF! | D103: =+C103/$O$89 -> #REF! | E103: =COUNTIF('BASE ELEC'!#REF!,"=2") -> #REF! | F103: =+E103 -> #REF! | G103: 1 | H103: =F103/G103 -> #REF! | I103: =COUNTIF('BASE ELEC'!#REF!,"=3") -> #REF! | J103: =+J102+I103 -> #REF! | K103: =A97*$Q$89 -> 3.3333333 | L103: =J103/K103 -> #REF! | M103: =COUNTIF('BASE ELEC'!#REF!,"=4") -> #REF! | N103: =+M103+N102 -> #REF! | O103: =+A103*$R$89 -> 99.166667 | P103: =+N103/O103 -> #REF! | Q103: =+I103+E103+C103+M103 -> #REF! | R103: 20 | S103: =+R103+Q103 -> #REF!
A104: =+A103+1 -> 11 | B104: 44593 | C104: =COUNTIF('BASE ELEC'!#REF!,"=1") -> #REF! | D104: =+C104/$O$89 -> #REF! | E104: =COUNTIF('BASE ELEC'!#REF!,"=2") -> #REF! | F104: =+F103+E104 -> #REF! | G104: 3 | H104: =F104/G104 -> #REF! | I104: =COUNTIF('BASE ELEC'!#REF!,"=3") -> #REF! | J104: =+J103+I104 -> #REF! | K104: =A98*$Q$89 -> 4.1666667 | L104: =J104/K104 -> #REF! | M104: =COUNTIF('BASE ELEC'!#REF!,"=4") -> #REF! | N104: =+M104+N103 -> #REF! | O104: =+A104*$R$89 -> 109.08333 | P104: =+N104/O104 -> #REF! | Q104: =+I104+E104+C104+M104 -> #REF! | R104: 21 | S104: =+R104+Q104 -> #REF!
A105: =+A104+1 -> 12 | B105: 44621 | C105: =COUNTIF('BASE ELEC'!#REF!,"=1") -> #REF! | D105: =+C105/$O$89 -> #REF! | E105: =COUNTIF('BASE ELEC'!#REF!,"=2") -> #REF! | F105: =+F104+E105 -> #REF! | G105: 4 | H105: =F105/G105 -> #REF! | I105: =COUNTIF('BASE ELEC'!#REF!,"=3") -> #REF! | J105: =+J104+I105 -> #REF! | K105: =A99*$Q$89 -> 5 | L105: =J105/K105 -> #REF! | M105: =COUNTIF('BASE ELEC'!#REF!,"=4") -> #REF! | N105: =+M105+N104 -> #REF! | O105: =+A105*$R$89 -> 119 | P105: =+N105/O105 -> #REF! | Q105: =+I105+E105+C105+M105 -> #REF! | R105: =COUNTIF(CORRECTIVOS!B:F,CORRECTIVOS!A$6) -> 0 | S105: =+R105+Q105 -> #REF!
A106: 1 | B106: 44652 | C106: =COUNTIF('BASE ELEC'!#REF!,"=1") -> #REF! | D106: =+C106/$O$89 -> #REF! | E106: =COUNTIF('BASE ELEC'!#REF!,"=2") -> #REF! | F106: =+E106 -> #REF! | G106: =+$P$89 -> 0.66666667 | H106: =+(F106/G106) -> #REF! | I106: =COUNTIF('BASE ELEC'!#REF!,"=3") -> #REF! | J106: =+I106 -> #REF! | K106: =+$Q$89 -> 0.83333333 | L106: =J106/K106 -> #REF! | M106: =COUNTIF('BASE ELEC'!#REF!,"=4") -> #REF! | N106: =+M106 -> #REF! | O106: =+R101 -> 20 | P106: =+N106/O106 -> #REF! | Q106: =+I106+E106+C106+M106 -> #REF! | R106: 33 | S106: =+R106+Q106 -> #REF!
A107: =+A106+1 -> 2 | B107: 44682 | C107: =COUNTIF('BASE ELEC'!#REF!,"=1") -> #REF! | D107: =+C107/$O$89 -> #REF! | E107: =COUNTIF('BASE ELEC'!#REF!,"=2") -> #REF! | F107: =+E107+F106 -> #REF! | G107: =+P$89+$A$107 -> 2.6666667 | H107: =F107/G107 -> #REF! | I107: =COUNTIF('BASE ELEC'!#REF!,"=3") -> #REF! | J107: =+J106+I107 -> #REF! | K107: =$A$107*$Q$89 -> 1.6666667 | L107: =J107/K107 -> #REF! | M107: =COUNTIF('BASE ELEC'!#REF!,"=4") -> #REF! | N107: =+M107+N106 -> #REF! | O107: =+A107*$R$89 -> 19.833333 | P107: =+N107/O107 -> #REF! | Q107: =+I107+E107+C107+M107 -> #REF! | R107: 42 | S107: =+R107+Q107 -> #REF!
A108: =+A107+1 -> 3 | B108: 44713 | C108: =COUNTIF('BASE ELEC'!#REF!,"=1") -> #REF! | D108: =+C108/$O$89 -> #REF! | E108: =COUNTIF('BASE ELEC'!#REF!,"=2") -> #REF! | F108: =+F107+E108 -> #REF! | G108: =+$P$89+$A$108 -> 3.6666667 | H108: =F108/G108 -> #REF! | I108: =COUNTIF('BASE ELEC'!#REF!,"=3") -> #REF! | J108: =+J107+I108 -> #REF! | K108: =$A$108*$Q$89 -> 2.5 | L108: =J108/K108 -> #REF! | M108: =COUNTIF('BASE ELEC'!#REF!,"=4") -> #REF! | N108: =+M108+N107 -> #REF! | O108: =+A108*$R$89 -> 29.75 | P108: =+N108/O108 -> #REF! | Q108: =+I108+E108+C108+M108 -> #REF! | R108: 22 | S108: =+R108+Q108 -> #REF!
A109: =+A108+1 -> 4 | B109: 44743 | C109: =COUNTIF('BASE ELEC'!#REF!,"=1") -> #REF! | D109: =+C109/$O$89 -> #REF! | E109: =COUNTIF('BASE ELEC'!#REF!,"=2") -> #REF! | F109: =+E109 -> #REF! | G109: =+$P$89 -> 0.66666667 | H109: =F109/G109 -> #REF! | I109: =COUNTIF('BASE ELEC'!#REF!,"=3") -> #REF! | J109: =+J108+I109 -> #REF! | K109: =$A$109*$Q$89 -> 3.3333333 | L109: =J109/K109 -> #REF! | M109: =COUNTIF('BASE ELEC'!#REF!,"=4") -> #REF! | N109: =+M109+N108 -> #REF! | O109: =+A109*$R$89 -> 39.666667 | P109: =+N109/O109 -> #REF! | Q109: =+I109+E109+C109+M109 -> #REF! | R109: 29 | S109: =+R109+Q109 -> #REF!
A110: =+A109+1 -> 5 | B110: 44774 | C110: =COUNTIF('BASE ELEC'!#REF!,"=1") -> #REF! | D110: =+C110/$O$89 -> #REF! | E110: =COUNTIF('BASE ELEC'!#REF!,"=2") -> #REF! | F110: =+F109+E110 -> #REF! | G110: =+P$89+$A$107 -> 2.6666667 | H110: =F110/G110 -> #REF! | I110: =COUNTIF('BASE ELEC'!#REF!,"=3") -> #REF! | J110: =+J109+I110 -> #REF! | K110: =$A$110*$Q$89 -> 4.1666667 | L110: =J110/K110 -> #REF! | M110: =COUNTIF('BASE ELEC'!#REF!,"=4") -> #REF! | N110: =+M110+N109 -> #REF! | O110: =+A110*$R$89 -> 49.583333 | P110: =+N110/O110 -> #REF! | Q110: =+I110+E110+C110+M110 -> #REF! | R110: 30 | S110: =+R110+Q110 -> #REF!
A111: =+A110+1 -> 6 | B111: 44805 | C111: =COUNTIF('BASE ELEC'!#REF!,"=1") -> #REF! | D111: =+C111/$O$89 -> #REF! | E111: =COUNTIF('BASE ELEC'!#REF!,"=2") -> #REF! | F111: =+F110+E111 -> #REF! | G111: =+$P$89+$A$108 -> 3.6666667 | H111: =F111/G111 -> #REF! | I111: =COUNTIF('BASE ELEC'!#REF!,"=3") -> #REF! | J111: =+J110+I111 -> #REF! | K111: =$A$111*$Q$89 -> 5 | L111: =J111/K111 -> #REF! | M111: =COUNTIF('BASE ELEC'!#REF!,"=4") -> #REF! | N111: =+M111+N110 -> #REF! | O111: =+A111*$R$89 -> 59.5 | P111: =+N111/O111 -> #REF! | Q111: =+I112+E111+C111+M111 -> #REF! | R111: 32 | S111: =+R111+Q111 -> #REF!
A112: =+A111+1 -> 7 | B112: 44835 | C112: =COUNTIF('BASE ELEC'!#REF!,"=1") -> #REF! | D112: =+C112/$O$89 -> #REF! | E112: =COUNTIF('BASE ELEC'!#REF!,"=2") -> #REF! | F112: =+E112 -> #REF! | G112: =+$P$89 -> 0.66666667 | H112: =F112/G112 -> #REF! | I112: =COUNTIF('BASE ELEC'!#REF!,"=3") -> #REF! | J112: 0 | K112: =+$Q$89 -> 0.83333333 | L112: =J112/K112 -> 0 | M112: =COUNTIF('BASE ELEC'!#REF!,"=4") -> #REF! | N112: =+M112+N111 -> #REF! | O112: =+A112*$R$89 -> 69.416667 | P112: =+N112/O112 -> #REF! | Q112: =+I112+E112+C112+M112 -> #REF! | R112: 31 | S112: =+R112+Q112 -> #REF!
A113: =+A112+1 -> 8 | B113: 44866 | C113: =COUNTIF('BASE ELEC'!#REF!,"=1") -> #REF! | D113: =+C113/$O$89 -> #REF! | E113: =COUNTIF('BASE ELEC'!#REF!,"=2") -> #REF! | F113: =+F112+E113 -> #REF! | G113: =+P$89+$A$107 -> 2.6666667 | H113: =F113/G113 -> #REF! | I113: =COUNTIF('BASE ELEC'!#REF!,"=3") -> #REF! | J113: =+J112+I113 -> #REF! | K113: =$A$107*$Q$89 -> 1.6666667 | L113: =J113/K113 -> #REF! | M113: =COUNTIF('BASE ELEC'!#REF!,"=4") -> #REF! | N113: =+M113+N112 -> #REF! | O113: =+A113*$R$89 -> 79.333333 | P113: =+N113/O113 -> #REF! | Q113: =+I113+E113+C113+M113 -> #REF! | R113: 18 | S113: =+R113+Q113 -> #REF!
A114: =+A113+1 -> 9 | B114: 44896 | C114: =COUNTIF('BASE ELEC'!#REF!,"=1") -> #REF! | D114: =+C114/$O$89 -> #REF! | E114: =COUNTIF('BASE ELEC'!#REF!,"=2") -> #REF! | F114: =+F113+E114 -> #REF! | G114: =+$P$89+$A$108 -> 3.6666667 | H114: =F114/G114 -> #REF! | I114: =COUNTIF('BASE ELEC'!#REF!,"=3") -> #REF! | J114: =+J113+I114 -> #REF! | K114: =$A$108*$Q$89 -> 2.5 | L114: =J114/K114 -> #REF! | M114: =COUNTIF('BASE ELEC'!#REF!,"=4") -> #REF! | N114: =+M114+N113 -> #REF! | O114: =+A114*$R$89 -> 89.25 | P114: =+N114/O114 -> #REF! | Q114: =+I114+E114+C114+M114 -> #REF! | R114: 35 | S114: =+R114+Q114 -> #REF!
...

Sheet CORRECTIVOS
B3: Aviso | C3: CECO | D3: UT | E3: Tarea | F3: Actividad | G3: Fecha | H3: Planificado | I3: Cumplido | J3: No planificado
F4: Electrico | G4: 46056 | H4: 1 | I4: SÍ
F5: Electrico | G5: 46057 | H5: 1 | I5: SÍ
F6: Hidrogrua | G6: 46057 | H6: 1 | I6: SÍ
F7: Electrico | G7: 46058 | H7: 1 | I7: SÍ
F8: Electrico | G8: 46058 | H8: 1 | I8: SÍ
F9: Electrico | G9: 46059 | H9: 1 | I9: SÍ
F10: Grupo Gen | G10: 46061 | I10: SÍ | J10: 1
F11: Electrico | G11: 46062 | H11: 1 | I11: SÍ
F12: Electrico | G12: 46062 | H12: 1 | I12: SÍ
F13: Grupo Gen | G13: 46062 | I13: SÍ | J13: 1
F14: Electrico | G14: 46063 | H14: 1 | I14: SÍ
F15: Electrico | G15: 46064 | H15: 1 | I15: SÍ
F16: Electrico | G16: 46064 | H16: 1 | I16: SÍ
F17: Electrico | G17: 46064 | H17: 1 | I17: SÍ
F18: Aire | G18: 46064 | I18: SÍ | J18: 1
F19: Electrico | G19: 46065 | H19: 1 | I19: SÍ
F20: Electrico | G20: 46065 | I20: SÍ | J20: 1
F21: Aire | G21: 46065 | H21: 1 | I21: SÍ
F22: Electrico | G22: 46066 | I22: SÍ | J22: 1
F23: Aire | G23: 46071 | H23: 1 | I23: SÍ
F24: Aire | G24: 46073 | H24: 1 | I24: SÍ
F25: Grupo Gen | G25: 46074 | I25: SÍ | J25: 1
F26: Aire | G26: 46076 | H26: 1 | I26: SÍ
F27: Electrico | G27: 46078 | H27: 1 | I27: SÍ
F28: Electrico | G28: 46078 | H28: 1 | I28: SÍ
F29: Aire | G29: 46078 | H29: 1 | I29: SÍ
F30: Aire | G30: 46078 | I30: SÍ | J30: 1
F31: Aire | G31: 46079 | H31: 1 | I31: SÍ
F32: Electrico | G32: 46080 | H32: 1 | I32: SÍ
F33: Electrico | G33: 46080 | H33: 1 | I33: SÍ
H35: =COUNT(H4:H33) -> 23 | I35: =+COUNTIF(I4:I34,"Sí") -> 30 | J35: =SUM(J4:J33) -> 7
H36: Porc. Cumplimiento
H37: =(+H35+J35)/I35 -> 1

Sheet BASE AA
A1: LOCALIDAD | B1: SEDE | C1: AREA | D1: CECO | E1: SECTOR/USUARIO | F1: DESCRIPCIÓN | G1: COD. NUEVO | H1: FREC | I1: 45597 | J1: 45627 | K1: 45658 | L1: 45689 | M1: 45717 | N1: 45748 | O1: 45778 | P1: 45809 | Q1: 45839 | R1: 45870 | S1: 45901 | T1: 45931 | U1: 45962 | V1: 45992 | W1: 46023 | X1: 46054 | Y1: 46082
A2: ESPERANZA | B2: PLANTA CELULOSA | C2: ADMINISTRACIÓN | D2: APOBA1-871 | E2: ESPE-ESP-CEL-ADMIN1-OFRRHH01 | F2: OF. RRHH CELULOSA | G2: CEL-AD1-1 | H2: 3 | P2: 3
A3: ESPERANZA | B3: PLANTA CELULOSA | C3: ADMINISTRACIÓN | D3: APOBA1-871 | E3: ESPE-ESP-CEL-ADMIN1-OFMASSO3 | F3: OF. JEFE DE SEGURIDAD. GRACIELA BENITEZ | G3: CEL-AD1-11 | H3: 4
A4: ESPERANZA | B4: PLANTA CELULOSA | C4: ADMINISTRACIÓN | D4: APOBA1-871 | E4: ESPE-ESP-CEL-ADMIN1-OFCOSTO1 | F4: Of. Costos (Auxiliares) | G4: CEL-AD1-9 | H4: 4 | O4: 4
A5: ESPERANZA | B5: PLANTA CELULOSA | C5: ADMINISTRACIÓN | D5: APOBA1-871 | E5: ESPE-ESP-CEL-ADMIN1-OFMASSO5 | F5: MASSO SALA DE REUNIONES | G5: CEL-AD1-13 | H5: 4
A6: ESPERANZA | B6: PLANTA CELULOSA | C6: ADMINISTRACIÓN | D6: APOBA1-871 | E6: ESPE-ESP-CEL-ADMIN1-OFMASSO4 | F6: Of. Supervisor Seguridad y Salud E CABRERA | G6: CEL-AD1-12 | H6: 4
A7: ESPERANZA | B7: PLANTA CELULOSA | C7: ADMINISTRACIÓN | D7: APOBA1-871 | E7: ESPE-ESP-CEL-ADMIN1-OFMASSO4 | F7: Of. Medio Ambiente (Auxiliares) | G7: CEL-AD1-14 | H7: 4 | P7: 4
A8: ESPERANZA | B8: PLANTA CELULOSA | C8: ADMINISTRACIÓN | D8: APOBA1-871 | E8: ESPE-ESP-CEL-ADMIN1-OFMASSO3 | F8: DANIEL CABRERA | G8: CEL-AD1-8 | H8: 4 | T8: 4
A9: ESPERANZA | B9: PLANTA CELULOSA | C9: ADMINISTRACIÓN | D9: APOBA1-871 | E9: ESPE-ESP-CEL-ADMIN1-OFSESUBA | F9: Of. Jefe de Costos ESCALADA LIZANDRO | G9: CEL-AD1-23 | H9: 4 | I9: 4
A10: ESPERANZA | B10: PLANTA CELULOSA | C10: ADMINISTRACIÓN | D10: APOBA1-871 | E10: ESPE-ESP-CEL-ADMIN1 | F10: Of. Tesorería | G10: CEL-AD1-20 | H10: 4 | O10: 4
A11: ESPERANZA | B11: PLANTA CELULOSA | C11: ADMINISTRACIÓN | D11: APOBA1-871 | E11: ESPE-ESP-CEL-ADMIN1-OFGEREOP | F11: OF. GERENTE OPERACIONES. | G11: CEL-AD1-25 | H11: 3 | O11: 3
A12: ESPERANZA | B12: PLANTA CELULOSA | C12: ADMINISTRACIÓN | D12: APOBA1-871 | E12: ESPE-ESP-CEL-ADMIN1-OFSECGTE | F12: Of. Secretaria Gte. | G12: CEL-AD1-26 | H12: 3 | N12: 3 | T12: 3
A13: ESPERANZA | B13: PLANTA CELULOSA | C13: ADMINISTRACIÓN | D13: APOBA1-871 | E13: ESPE-ESP-CEL-ADMIN1-OFRRHH01 | F13: Of. RRHH (Auxiliares) 2 | G13: CEL-AD1-2 | H13: 3 | P13: 3
A14: ESPERANZA | B14: PLANTA CELULOSA | C14: ADMINISTRACIÓN | D14: APOBA1-871 | E14: ESPE-ESP-CEL-ADMIN1-OFSGTEAD | F14: OF.SUBG.ADMINISTRACION. | G14: CEL-AD1-22 | H14: 4 | O14: 4
A15: ESPERANZA | B15: PLANTA CELULOSA | C15: ADMINISTRACIÓN | D15: APOBA1-871 | E15: ESPE-ESP-CEL-ADMIN1-OFSGTEMT | F15: Of. SubGerente de Mantenimiento | G15: CEL-AD1-21 | H15: 4 | O15: 4
A16: ESPERANZA | B16: PLANTA CELULOSA | C16: ADMINISTRACIÓN | D16: APOBA1-871 | E16: ESPE-ESP-CEL-ADMIN1-OFSGTEPR | F16: Of. SubGerente de Producción | G16: CEL-AD1-24 | H16: 4 | J16: 4
A17: ESPERANZA | B17: PLANTA CELULOSA | C17: ADMINISTRACIÓN | D17: APOBA1-871 | E17: ESPE-ESP-CEL-ADMIN1-ENFERME3 | F17: CONSULTORIO 1 | G17: PC01AD115 | H17: 1 | I17: 1 | J17: 1 | K17: 1 | L17: 1 | M17: 1 | N17: 1 | O17: 1 | P17: 1 | Q17: 1 | R17: 1 | S17: 1 | T17: 1 | U17: 1 | V17: 1 | W17: 1
A18: ESPERANZA | B18: PLANTA CELULOSA | C18: ADMINISTRACIÓN | D18: APOBA1-871 | E18: ESPE-ESP-CEL-ADMIN1-ENFERME3 | F18: CONSULTORIO 2 | G18: PC01AD116 | H18: 1 | I18: 1 | J18: 1 | K18: 1 | L18: 1 | M18: 1 | N18: 1 | O18: 1 | P18: 1 | Q18: 1 | R18: 1 | S18: 1 | T18: 1 | U18: 1 | V18: 1 | W18: 1
A19: ESPERANZA | B19: PLANTA CELULOSA | C19: ADMINISTRACIÓN | D19: APOBA1-871 | E19: ESPE-ESP-CEL-ADMIN1-ENFERME3 | F19: RECEPCIÓN ENFERMERIA. | G19: PC01AD118 | H19: 1 | I19: 1 | J19: 1 | K19: 1 | L19: 1 | M19: 1 | N19: 1 | O19: 1 | P19: 1 | Q19: 1 | R19: 1 | S19: 1 | T19: 1 | U19: 1 | V19: 1 | W19: 1
A20: ESPERANZA | B20: PLANTA CELULOSA | C20: ADMINISTRACIÓN | D20: APOBA1-871 | E20: ESPE-ESP-CEL-ADMIN1-ENFERME4 | F20: CONSULTORIO ENFERMERIA | G20: PC01AD117 | H20: 1 | I20: 1 | J20: 1 | K20: 1 | L20: 1 | M20: 1 | N20: 1 | O20: 1 | P20: 1 | Q20: 1 | R20: 1 | S20: 1 | T20: 1 | U20: 1 | V20: 1 | W20: 1
A21: ESPERANZA | B21: PLANTA CELULOSA | C21: ADMINISTRACIÓN | D21: APOBA1-871 | E21: ESPE-ESP-CEL-ADMIN1-SALREU01 | F21: SALA DE REUNIONES RR.HH. | G21: CEL-AD1-3 | H21: 3 | O21: 3
A22: ESPERANZA | B22: PLANTA CELULOSA | C22: ADMINISTRACIÓN | D22: APOBA1-871 | E22: ESPE-ESP-CEL-ADMIN1-OFJEFERH | F22: Of. Jefe de Área RRHH | G22: CEL-AD1-4 | H22: 4 | T22: 4
A23: ESPERANZA | B23: PLANTA CELULOSA | C23: ADMINISTRACIÓN | D23: APOBA1-871 | E23: ESPE-ESP-CEL-ADMIN1-OFAUINT1 | F23: Of. Jefe Auditoría Interna | G23: CEL-AD1-5 | H23: 4 | Q23: 4
A24: ESPERANZA | B24: PLANTA CELULOSA | C24: ADMINISTRACIÓN | D24: APOBA1-871 | E24: ESPE-ESP-CEL-ADMIN1-OFAUINT2 | F24: Of. Auditoría Interna (Auxiliar) | G24: CEL-AD1-6 | H24: 4 | Q24: 4
A25: ESPERANZA | B25: PLANTA CELULOSA | C25: ADMINISTRACIÓN | D25: APOBA1-871 | E25: ESPE-ESP-CEL-ADMIN1-OFCONPRO | F25: Of. Control de Producción | G25: CEL-AD1-10 | H25: 4 | T25: 4
A26: ESPERANZA | B26: PLANTA CELULOSA | C26: ADMINISTRACIÓN | D26: APOBA1-871 | E26: ESPE-ESP-CEL-ADMIN1-OFCONFO2 | F26: Of. Control Forestal (Auxiliares) | G26: CEL-AD1-7 | H26: 4 | P26: 4
A27: ESPERANZA | B27: PLANTA CELULOSA | C27: ADMINISTRACIÓN | D27: APOBA1-871 | E27: ESPE-ESP-CEL-ADMIN1-OFMASSO2 | F27: Of. MASSO (Auxiliar SySO) | G27: CEL-AD1-19 | H27: 4 | P27: 4
A28: ESPERANZA | B28: PLANTA CELULOSA | C28: ADMINISTRACIÓN | D28: APOBA1-871 | E28: ESPE-ESP-CEL-ADMIN1 | F28: OFICINA DE VICITAS GERENCIA | G28: CEL-AD1-28 | H28: 4 | S28: 4
A29: ESPERANZA | B29: PLANTA CELULOSA | C29: ADMINISTRACIÓN | D29: APOBA1-871 | E29: ESPE-ESP-CEL-ADMIN1-EXAPUNTADORES | F29: OFICINAS SOEP | G29: CEL-AD1-27 | H29: 4
A30: ESPERANZA | B30: PLANTA CELULOSA | C30: ADMINISTRACIÓN 2 | D30: APOBA1-871 | E30: ESPE-ESP-CEL-ADMIN2-OFICINA1 | F30: Of. SSGG (Supervisor) | G30: CEL-AD2-1 | H30: 4 | O30: 4
A31: ESPERANZA | B31: PLANTA CELULOSA | C31: ADMINISTRACIÓN 2 | D31: APOBA1-871 | E31: ESPE-ESP-CEL-ADMIN2-OFCOYOB2 | F31: Of. Contratos y Obras (Auxiliares) | G31: CEL-AD2-10 | H31: 4 | R31: 4
A32: ESPERANZA | B32: PLANTA CELULOSA | C32: ADMINISTRACIÓN 2 | D32: APOBA1-871 | E32: ESPE-ESP-CEL-ADMIN2-OFJEFCYO | F32: Of. Jefe Contratos y Obras | G32: CEL-AD2-11 | H32: 4 | K32: 4 | R32: 4
A33: ESPERANZA | B33: PLANTA CELULOSA | C33: ADMINISTRACIÓN 2 | D33: APOBA1-871 | E33: ESPE-ESP-CEL-ADMIN2-OFCOYOB3 | F33: Of. Jefe Contrataciones Forestales | G33: CEL-AD2-12 | H33: 4 | R33: 4 | X33: 4
A34: ESPERANZA | B34: PLANTA CELULOSA | C34: ADMINISTRACIÓN 2 | D34: APOBA1-871 | E34: ESPE-ESP-CEL-ADMIN2-OFCOYOB1 | F34: Sala de reuniones Contratos y Obras | G34: CEL-AD2-13 | H34: 4 | R34: 4
A35: ESPERANZA | B35: PLANTA CELULOSA | C35: ADMINISTRACIÓN 2 | D35: APOBA1-871 | E35: ESPE-ESP-CEL-ADMIN2-SALCAP01 | F35: SALA DE CAPACITACIÓN CEL-AD2-14 | G35: CEL-AD2-14 | H35: 3 | O35: 3
A36: ESPERANZA | B36: PLANTA CELULOSA | C36: ADMINISTRACIÓN 2 | D36: APOBA1-871 | E36: ESPE-ESP-CEL-ADMIN2-SALCAP02 | F36: SALA DE CAPACITACIÓN CEL-AD2-15 | G36: CEL-AD2-15 | H36: 3 | O36: 3
A37: ESPERANZA | B37: PLANTA CELULOSA | C37: ADMINISTRACIÓN 2 | D37: APOBA1-871 | E37: ESPE-ESP-CEL-ADMIN2-SALCAP03 | F37: SALA DE CAPACITACIÓN CHICA CEL-AD2-16 | G37: CEL-AD2-16 | H37: 3 | O37: 3
A38: ESPERANZA | B38: PLANTA CELULOSA | C38: ADMINISTRACIÓN 2 | D38: APOBA1-871 | E38: ESPE-ESP-CEL-ADMIN2-OFCOSTOS | F38: Of. Jefe Cuentas a Pagar | G38: CEL-AD2-2 | H38: 4 | U38: 4
A39: ESPERANZA | B39: PLANTA CELULOSA | C39: ADMINISTRACIÓN 2 | D39: APOBA1-871 | E39: ESPE-ESP-CEL-ADMIN2-OFSGMOVI | F39: Of. SSGG (Auxiliares 1) | G39: CEL-AD2-3 | H39: 4 | T39: 4 | X39: 4
A40: ESPERANZA | B40: PLANTA CELULOSA | C40: ADMINISTRACIÓN 2 | D40: APOBA1-871 | E40: ESPE-ESP-CEL-ADMIN2-OFSGMOVI | F40: Of. SSGG (Movilidad) | G40: CEL-AD2-4 | H40: 4 | O40: 4
A41: ESPERANZA | B41: PLANTA CELULOSA | C41: ADMINISTRACIÓN 2 | D41: APOBA1-871 | E41: ESPE-ESP-CEL-ADMIN2-ARCHIVO1 | F41: Of. Archivo Técnico | G41: CEL-AD2-5 | H41: 4 | I41: 4
A42: ESPERANZA | B42: PLANTA CELULOSA | C42: ADMINISTRACIÓN 2 | D42: APOBA1-871 | E42: ESPE-ESP-CEL-ADMIN2-OFCOCO01 | F42: Of. Control de Contratistas (Auxiliares) | G42: CEL-AD2-6 | H42: 4 | R42: 4 | U42: 4
A43: ESPERANZA | B43: PLANTA CELULOSA | C43: ADMINISTRACIÓN 2 | D43: APOBA1-871 | E43: ESPE-ESP-CEL-ADMIN2-OFJEFECC | F43: Of. Jefe Control de Contratistas | G43: CEL-AD2-7 | H43: 4 | K43: 4 | U43: 4
A44: ESPERANZA | B44: PLANTA CELULOSA | C44: ADMINISTRACIÓN 2 | D44: APOBA1-871 | E44: ESPE-ESP-CEL-ADMIN2-OFCENPAG | F44: Of. Cuentas a Pagar (Auxiliares) 1 | G44: CEL-AD2-8 | H44: 4 | K44: 4
A45: ESPERANZA | B45: PLANTA CELULOSA | C45: ADMINISTRACIÓN 2 | D45: APOBA1-871 | E45: ESPE-ESP-CEL-ADMIN2 | F45: Deposito de cafeteria e insumos | G45: CEL-AD2-17 | H45: 4 | X45: 4
A46: ESPERANZA | B46: PLANTA CELULOSA | C46: ADMINISTRACIÓN 2 | D46: APOBA1-871 | E46: ESPE-ESP-CEL-ADMIN2-OFCENPAG | F46: Of. Cuentas a Pagar (Auxiliares) 2 | G46: CEL-AD2-9 | H46: 4 | K46: 4
A47: ESPERANZA | B47: PLANTA CELULOSA | C47: BALANZA | D47: APOBA1-871 | E47: ESPE-ESP-CEL-BALANZ-OFOPERA2 | F47: Balanza C3 | G47: PC01BAL01 | H47: 1 | I47: 1 | J47: 1 | K47: 1 | L47: 1 | M47: 1 | N47: 1 | O47: 1 | P47: 1 | Q47: 1 | R47: 1 | S47: 1 | T47: 1 | U47: 1 | V47: 1 | W47: 1
A48: ESPERANZA | B48: PLANTA CELULOSA | C48: BALANZA | D48: APOBA1-871 | E48: ESPE-ESP-CEL-BALANZ-OFOPERA1 | F48: Balanza A1 - B2 | G48: PC01BAL02 | H48: 1 | I48: 1 | J48: 1 | K48: 1 | L48: 1 | M48: 1 | N48: 1 | O48: 1 | P48: 1 | Q48: 1 | R48: 1 | S48: 1 | T48: 1 | U48: 1 | V48: 1 | W48: 1
A49: ESPERANZA | B49: PLANTA CELULOSA | C49: COMEDOR | D49: APOBA1-871 | E49: ESPE-ESP-CEL-COMEDO-MTTOAA01 | F49: MTTO AA 01 | G49: PC01COM01 | H49: 1 | I49: 1 | J49: 1 | K49: 1 | L49: 1 | M49: 1 | N49: 1 | O49: 1 | P49: 1 | Q49: 1 | R49: 1 | S49: 1 | T49: 1 | U49: 1 | V49: 1 | W49: 1
A50: ESPERANZA | B50: PLANTA CELULOSA | C50: COMEDOR | D50: APOBA1-871 | E50: ESPE-ESP-CEL-COMEDO-MTTOAA02 | F50: MTTO AA 02 | G50: PC01COM02 | H50: 1 | I50: 1 | J50: 1 | K50: 1 | L50: 1 | M50: 1 | N50: 1 | O50: 1 | P50: 1 | Q50: 1 | R50: 1 | S50: 1 | T50: 1 | U50: 1 | V50: 1 | W50: 1
A51: ESPERANZA | B51: PLANTA CELULOSA | C51: COMEDOR | D51: APOBA1-871 | E51: ESPE-ESP-CEL-COMEDO-MTTOAA03 | F51: MTTO AA 03 | G51: PC01COM03 | H51: 1 | I51: 1 | J51: 1 | K51: 1 | L51: 1 | M51: 1 | N51: 1 | O51: 1 | P51: 1 | Q51: 1 | R51: 1 | S51: 1 | T51: 1 | U51: 1 | V51: 1 | W51: 1
A52: ESPERANZA | B52: PLANTA CELULOSA | C52: COMEDOR | D52: APOBA1-871 | E52: ESPE-ESP-CEL-COMEDO-MTTOAA04 | F52: MTTO AA 04 | G52: PC01COM04 | H52: 1 | I52: 1 | J52: 1 | K52: 1 | L52: 1 | M52: 1 | N52: 1 | O52: 1 | P52: 1 | Q52: 1 | R52: 1 | S52: 1 | T52: 1 | U52: 1 | V52: 1 | W52: 1
A53: ESPERANZA | B53: PLANTA CELULOSA | C53: COMEDOR | D53: APOBA1-871 | E53: ESPE-ESP-CEL-COMEDO-MTTOAA05 | F53: MTTO AA 05 | G53: PC01COM05 | H53: 1 | I53: 1 | J53: 1 | K53: 1 | L53: 1 | M53: 1 | N53: 1 | O53: 1 | P53: 1 | Q53: 1 | R53: 1 | S53: 1 | T53: 1 | U53: 1 | V53: 1 | W53: 1
A54: ESPERANZA | B54: PLANTA CELULOSA | C54: COMEDOR | D54: APOBA1-871 | E54: ESPE-ESP-CEL-COMEDO-MTTOAA06 | F54: MTTO AA 06 | G54: PC01COM06 | H54: 1 | I54: 1 | J54: 1 | K54: 1 | L54: 1 | M54: 1 | N54: 1 | O54: 1 | P54: 1 | Q54: 1 | R54: 1 | S54: 1 | T54: 1 | U54: 1 | V54: 1 | W54: 1
A55: ESPERANZA | B55: PLANTA CELULOSA | C55: CONTROL TÉCNICO | D55: APOBA1-871 | E55: ESPE-ESP-CEL-LABORA-OFIC0001 | F55: OFICINA JEFE CONTROL TECNICO | G55: CEL-COTE-1 | H55: 4 | P55: 4
A56: ESPERANZA | B56: PLANTA CELULOSA | C56: CONTROL TÉCNICO | D56: APOBA1-871 | E56: ESPE-ESP-CEL-LABORA-OFIC0012 | F56: OFICINA ING. EN PROCESO | G56: CEL-COTE-2 | H56: 4 | P56: 4
A57: ESPERANZA | B57: PLANTA CELULOSA | C57: CONTROL TÉCNICO | D57: APOBA1-871 | E57: ESPE-ESP-CEL-LABORA-LABORASE | F57: LABORATORIO SALA AMBIENTADA | G57: CEL-COTE-3 | H57: 4 | P57: 4
A58: ESPERANZA | B58: PLANTA CELULOSA | C58: CONTROL TÉCNICO | D58: APOBA1-871 | E58: ESPE-ESP-CEL-LABORA-OFIC0019 | F58: OFICINA SUPERVISOR LAB. AGUAS/EFLUENTES | G58: CEL-COTE-4 | H58: 4 | O58: 4
A59: ESPERANZA | B59: PLANTA CELULOSA | C59: CONTROL TÉCNICO | D59: APOBA1-871 | E59: ESPE-ESP-CEL-LABORA-AGUAEFLU | F59: LABORATORIO AGUAS Y EFLUENTES | G59: CEL-COTE-5 | H59: 4 | O59: 4
A60: ESPERANZA | B60: PLANTA CELULOSA | C60: CONTROL TÉCNICO | D60: APOBA1-871 | E60: ESPE-ESP-CEL-LABORA-OFIC0001 | F60: OFICINA ANALISTA LABORATORIO | G60: CEL-COTE-6 | H60: 4 | P60: 4
A61: ESPERANZA | B61: PLANTA CELULOSA | C61: TRANSPORTE FORESTAL | D61: APOBA1-871 | E61: ESPE-ESP-CEL-FOREST-OFRECLOG | F61: Of. Auxiliares | G61: PC01FOR01 | H61: 2 | I61: 2 | L61: 2 | O61: 2 | S61: 2 | V61: 2
A62: ESPERANZA | B62: PLANTA CELULOSA | C62: TRANSPORTE FORESTAL | D62: APOBA1-871 | E62: ESPE-ESP-CEL-FOREST-OFJETRAN | F62: Of. Jefe de Carga y Transporte | G62: PC01FOR02 | H62: 2 | I62: 2 | O62: 2 | R62: 2 | V62: 2
A63: ESPERANZA | B63: PLANTA CELULOSA | C63: TRANSPORTE FORESTAL | D63: APOBA1-871 | E63: ESPE-ESP-CEL-FOREST-SALREU01 | F63: Sala de reuniones (al lado de Recepción) | G63: PC01FOR03 | H63: 2 | I63: 2 | L63: 2 | O63: 2 | R63: 2 | V63: 2
A64: ESPERANZA | B64: PLANTA CELULOSA | C64: TRANSPORTE FORESTAL | D64: APOBA1-871 | E64: Of. Recepción | G64: PC01FOR04 | H64: 2 | L64: 2 | O64: 2 | R64: 2 | V64: 2
A65: ESPERANZA | B65: PLANTA CELULOSA | C65: LOGISTICA | D65: APOBA1-871 | E65: ESPE-ESP-CEL-LOGIST-OFAUXLOG | F65: Of. Trafico/Logistica 1 | G65: CEL-LOG-1 | H65: 3 | N65: 3 | U65: 3
A66: ESPERANZA | B66: PLANTA CELULOSA | C66: LOGISTICA | D66: APOBA1-871 | E66: ESPE-ESP-CEL-LOGIST-OFAUXLOG | F66: Of. Trafico/Logistica 1 | G66: CEL-LOG-2 | H66: 3 | N66: 3 | U66: 3
A67: ESPERANZA | B67: PLANTA CELULOSA | C67: LOGISTICA | D67: APOBA1-871 | E67: ESPE-ESP-CEL-LOGIST-OFJEFLOG | F67: Of. Jefe Logistica. | G67: CEL-LOG-3 | H67: 3 | O67: 3
A68: ESPERANZA | B68: PLANTA CELULOSA | C68: LOGISTICA | D68: APOBA1-871 | E68: ESPE-ESP-CEL-LOGIST | F68: Of. Planificacion Trafico/Logistica. | G68: CEL-LOG-4 | H68: 3 | R68: 3 | U68: 3
A69: ESPERANZA | B69: PLANTA CELULOSA | C69: LOGISTICA | D69: APOBA1-871 | E69: ESPE-ESP-CEL-LOGIST-SALREU01 | F69: Sala de Reunion | G69: CEL-LOG-5 | H69: 3 | J69: 3 | R69: 3
A70: ESPERANZA | B70: PLANTA CELULOSA | C70: LOGISTICA | D70: APOBA1-871 | E70: ESPE-ESP-CEL-LOGIST | F70: QUINCHO DE CAMONEROS | G70: CEL-LOG-6 | H70: 3 | K70: 3 | S70: 3
A71: ESPERANZA | B71: PLANTA CELULOSA | C71: LOGISTICA | D71: APOBA1-871 | E71: ESPE-ESP-CEL-LOGIST | F71: QUINCHO DE CAMONEROS | G71: CEL-LOG-7 | H71: 3 | K71: 3 | S71: 3
A72: ESPERANZA | B72: PLANTA CELULOSA | C72: PORTERÍA | D72: APOBA1-871 | E72: ESPE-ESP-CEL-VIGILA-COMEDOR1 | F72: Comedor | G72: CEL-POR-1 | H72: 4 | Q72: 4
A73: ESPERANZA | B73: PLANTA CELULOSA | C73: PORTERÍA | D73: APOBA1-871 | E73: ESPE-ESP-CEL-PORTER-MTTOAA02 | F73: PORTERIA (ARCHIVO RACK CAMARAS) | G73: PC01VIG02 | H73: 1 | I73: 1 | J73: 1 | K73: 1 | L73: 1 | N73: 1 | O73: 1 | P73: 1 | Q73: 1 | R73: 1 | S73: 1 | T73: 1 | U73: 1 | V73: 1 | W73: 1
A74: ESPERANZA | B74: PLANTA CELULOSA | C74: PORTERÍA | D74: APOBA1-871 | E74: ESPE-ESP-CEL-PORTER-MTTOAA03 | G74: PC01VIG03 | H74: 1 | I74: 1 | J74: 1 | K74: 1 | L74: 1 | N74: 1 | O74: 1 | P74: 1 | Q74: 1 | R74: 1 | S74: 1 | T74: 1 | U74: 1 | V74: 1 | W74: 1
A75: ESPERANZA | B75: PLANTA CELULOSA | C75: PORTERÍA | D75: APOBA1-871 | E75: ESPE-ESP-CEL-PORTER-MTTOAA04 | F75: OF. DE EXPEDICIÓN | G75: PC01VIG04 | H75: 1 | I75: 1 | J75: 1 | K75: 1 | L75: 1 | N75: 1 | O75: 1 | P75: 1 | Q75: 1 | R75: 1 | S75: 1 | T75: 1 | U75: 1 | V75: 1 | W75: 1
A76: ESPERANZA | B76: PLANTA CELULOSA | C76: PORTERÍA | D76: APOBA1-871 | E76: ESPE-ESP-CEL-VIGILA-OFJEFEQU | F76: Of. Jefe de Equipo. | G76: CEL-POR-5 | H76: 4 | Q76: 4
A77: ESPERANZA | B77: PLANTA CELULOSA | C77: SISTEMAS | D77: APOBA1-871 | E77: ESPE-ESP-CEL-SISTEM-OFICINA1 | F77: CENTRO DE COMPUTOS 1 | G77: PC01SITE1 | H77: 1 | I77: 1 | J77: 1 | K77: 1 | L77: 1 | M77: 1 | N77: 1 | O77: 1 | P77: 1 | Q77: 1 | R77: 1 | S77: 1 | T77: 1 | U77: 1 | V77: 1 | W77: 1
A78: ESPERANZA | B78: PLANTA CELULOSA | C78: SISTEMAS | D78: APOBA1-871 | E78: ESPE-ESP-CEL-SISTEM-OFICINA2 | F78: CENTRO DE COMPUTOS 2 | G78: PC01SITE2 | H78: 1 | I78: 1 | J78: 1 | K78: 1 | L78: 1 | M78: 1 | N78: 1 | O78: 1 | P78: 1 | Q78: 1 | R78: 1 | S78: 1 | T78: 1 | U78: 1 | V78: 1 | W78: 1
A79: ESPERANZA | B79: PLANTA CELULOSA | C79: SISTEMAS | D79: APOBA1-871 | E79: ESPE-ESP-CEL-SISTEM-OFICINA3 | F79: CENTRAL TELEFÓNICA | G79: PC01AD129 | H79: 1 | I79: 1 | J79: 1 | K79: 1 | L79: 1 | M79: 1 | N79: 1 | O79: 1 | P79: 1 | Q79: 1 | R79: 1 | S79: 1 | T79: 1 | U79: 1 | V79: 1 | W79: 1
A80: ESPERANZA | B80: PLANTA CELULOSA | C80: SISTEMAS | D80: APOBA1-871 | E80: ESPE-ESP-CEL-SISTEM-SUBGTEIN | F80: Oficina Jefe de Informática | G80: CEL-SIST-4 | H80: 4 | L80: 4 | U80: 4
A81: ESPERANZA | B81: PLANTA CELULOSA | C81: SISTEMAS | D81: APOBA1-871 | E81: ESPE-ESP-CEL-SISTEM | F81: Oficina Analistas Informática | G81: CEL-SIST-5 | H81: 4 | L81: 4 | U81: 4
A82: ESPERANZA | B82: PTO. BOSSETTI | C82: BALANZA | D82: APOBA1-872 | E82: BOSS-BOS-ADM-BALANZ-OFOPERAD | F82: Of. Operadores | G82: PM02BAL01 | H82: 1 | I82: 1 | J82: 1 | K82: 1 | L82: 1 | N82: 1 | O82: 1 | P82: 1 | Q82: 1 | R82: 1 | S82: 1 | T82: 1 | U82: 1 | V82: 1 | X82: 1
A83: ESPERANZA | B83: PTO. BOSSETTI | C83: BALANZA | D83: APOBA1-872 | E83: BOSS-BOS-ADM-BALANZ-OFOPERAD | F83: Of. Operadores | G83: PM02BAL02 | H83: 1 | I83: 1 | J83: 1 | K83: 1 | L83: 1 | N83: 1 | O83: 1 | P83: 1 | Q83: 1 | R83: 1 | S83: 1 | T83: 1 | U83: 1 | V83: 1 | X83: 1
A84: ESPERANZA | B84: PTO. BOSSETTI | C84: VIGILANCIA | D84: APOBA1-872 | E84: BOSS-BOS-ADM-VIGILA-OFICINA1 | F84: OFICINA PUESTO VIGILANCIA | G84: CLO-VIG-1 | H84: 2 | P84: 2 | Q84: 2 | T84: 2
A85: ESPERANZA | B85: PTO. BOSSETTI | C85: CHALET | D85: APOBA1-872 | E85: BOSS-BOS-ADM-CHALET-HABIT001 | F85: Habitacion 1 | G85: CLO-CHA-1 | H85: 4 | S85: 4
A86: ESPERANZA | B86: PTO. BOSSETTI | C86: CHALET | D86: APOBA1-872 | E86: BOSS-BOS-ADM-CHALET-HABIT002 | F86: Habitacion 2 | G86: CLO-CHA-2 | H86: 4 | S86: 4
A87: ESPERANZA | B87: PTO. BOSSETTI | C87: CHALET | D87: APOBA1-872 | E87: BOSS-BOS-ADM-CHALET-HABIT003 | F87: Habitacion 3 | G87: CLO-CHA-3 | H87: 4 | S87: 4
A88: ESPERANZA | B88: PTO. BOSSETTI | C88: CHALET | D88: APOBA1-872 | E88: BOSS-BOS-ADM-CHALET-HABIT004 | F88: Habitacion 4 | G88: CLO-CHA-4 | H88: 4 | U88: 4
A89: ESPERANZA | B89: PTO. BOSSETTI | C89: CHALET | D89: APOBA1-872 | E89: BOSS-BOS-ADM-CHALET-HABIT005 | F89: Habitacion 5 | G89: CLO-CHA-5 | H89: 4 | U89: 4
A90: ESPERANZA | B90: PTO. BOSSETTI | C90: CHALET | D90: APOBA1-872 | E90: BOSS-BOS-ADM-CHALET-HABIT006 | F90: Habitacion 6 | G90: CLO-CHA-6 | H90: 4 | U90: 4
A91: ESPERANZA | B91: PTO. BOSSETTI | C91: CHALET | D91: APOBA1-872 | E91: BOSS-BOS-ADM-CHALET-LIVING01 | F91: Living Comedor | G91: CLO-CHA-7 | H91: 4 | S91: 4
A92: ESPERANZA | B92: PTO. BOSSETTI | C92: CHALET | D92: APOBA1-872 | E92: BOSS-BOS-ADM-CASACU-CASACUID | F92: Casa Cuidador. | G92: CLO-CHA-8 | H92: 4 | Q92: 4
A93: ESPERANZA | B93: PTO. BOSSETTI | C93: CHALET | D93: APOBA1-872 | E93: BOSS-BOS-ADM-CHALET-COCINA01 | F93: COCINA 01 | G93: CLO-CHA-9 | H93: 4 | Q93: 4
A94: ESPERANZA | B94: PTO. BOSSETTI | C94: CHALET | D94: APOBA1-872 | E94: BOSS-BOS-ADM-CASACU-HABITAC01 | F94: HABITACION 1 | G94: CLO-CHA-10 | H94: 4 | Q94: 4
A95: ESPERANZA | B95: PTO. BOSSETTI | C95: COMEDOR | D95: APOBA1-872 | E95: BOSS-BOS-ADM-COMEDO-COMEDOR1 | F95: Salón Comedor | G95: CLO-COM-1 | H95: 3 | J95: 3 | P95: 3
A96: ESPERANZA | B96: PTO. BOSSETTI | C96: COMEDOR | D96: APOBA1-872 | E96: BOSS-BOS-ADM-COMEDO-COMEDOR1 | F96: Salón Comedor | G96: CLO-COM-2 | H96: 3 | J96: 3 | P96: 3
A97: ESPERANZA | B97: PTO. BOSSETTI | C97: ENFERMERÍA | D97: APOBA1-872 | E97: BOSS-BOS-ADM-ENFERM-CONSULTO | F97: Consultorio | G97: CLO-ENF-1 | H97: 0
A98: ESPERANZA | B98: PTO. BOSSETTI | C98: EXPEDICIÓN | D98: APOBA1-872 | E98: BOSS-BOS-ADM-EXPEDI-OFIC0001 | F98: Of. Planificador (Martinez) | G98: CLO-EXP-1 | H98: 3 | J98: 3 | P98: 3
A99: ESPERANZA | B99: PTO. BOSSETTI | C99: EXPEDICIÓN | D99: APOBA1-872 | E99: BOSS-BOS-ADM-EXPEDI-OFIC0002 | F99: Of. Planificador (al lado Martinez) | G99: CLO-EXP-2 | H99: 3 | J99: 3 | P99: 3
A100: ESPERANZA | B100: PTO. BOSSETTI | C100: EXPEDICIÓN | D100: APOBA1-872 | E100: BOSS-BOS-ADM-EXPEDI-QUINCAMI | F100: QUINCHO DE CAMIONEROS | G100: CLO-EXP-3 | H100: 3 | N100: 3
...

Sheet PROG AA
B1: Equipo | D1: abril | E1: mayo | F1: junio | G1: julio | H1: agosto | I1: septiembre | J1: octubre | K1: noviembre | L1: diciembre | M1: enero | N1: febrero | O1: marzo
A2: TRIMESTRALES | B2: CEL-FOR-1 | C2: 2 | D2: x | G2: x | J2: x | M2: x
B3: CEL-FOR-2 | C3: 2 | D3: x | G3: x | J3: x | M3: x
B4: CEL-FOR-3 | C4: 2 | D4: x | G4: x | J4: x | M4: x
B5: CEL-FOR-4 | C5: 2 | D5: x | G5: x | J5: x | M5: x
B6: CLO-VIG-1 | C6: 2 | F6: x | I6: x | L6: x | O6: x
B7: LOG-LOG-1 | C7: 2 | D7: x | G7: x | J7: x | M7: x
B8: MDF-AD1-10 | C8: 2 | E8: x | H8: x | K8: x | N8: x
B9: MDF-AD1-11 | C9: 2 | E9: x | H9: x | K9: x | N9: x
B10: MDF-AD1-16 | C10: 2 | E10: x | H10: x | K10: x | N10: x
B11: MDF-AD1-17 | C11: 2 | E11: x | H11: x | K11: x | N11: x
B12: MDF-AD1-18 | C12: 2 | F12: x | I12: x | L12: x | O12: x
B13: MDF-AD1-3 | C13: 2 | F13: x | I13: x | L13: x | O13: x
B14: MDF-AD1-6 | C14: 2 | F14: x | I14: x | L14: x | O14: x
B15: MDF-AD1-7 | C15: 2 | F15: x | I15: x | L15: x | O15: x
B16: MDF-AD1-8 | C16: 2 | F16: x | I16: x | L16: x | O16: x
B17: MDF-AD1-9 | C17: 2 | F17: x | I17: x | L17: x | O17: x
B18: MDF-AD2-2 | C18: 2 | D18: x | G18: x | J18: x | M18: x
B19: MDF-EXP-1 | C19: 2 | D19: x | G19: x | J19: x | M19: x
B20: MDF-EXP-2 | C20: 2 | D20: x | G20: x | J20: x | M20: x
B21: MDF-EXP-3 | C21: 2 | D21: x | G21: x | J21: x | M21: x
B22: MDF-LAB-1 | C22: 2 | E22: x | H22: x | K22: x | N22: x
B23: PYP-AD1-23 | C23: 2 | F23: x | I23: x | L23: x | O23: x
B24: PYP-AD1-29 | C24: 2 | E24: x | H24: x | K24: x | N24: x
B25: PYP-HOS-21 | C25: 2 | E25: x | H25: x | K25: x | N25: x
B26: PYP-POR-6 | C26: 2 | E26: x | H26: x | K26: x | N26: x
B27: PYP-SME-2 | C27: 2 | E27: x | H27: x | K27: x | N27: x
A30: SEMESTRALES | B30: Equipo | D30: abril | E30: mayo | F30: junio | G30: julio | H30: agosto | I30: septiembre | J30: octubre | K30: noviembre | L30: diciembre | M30: enero | N30: febrero | O30: marzo
B31: CEL-AD1-1 | C31: 3 | H31: X | N31: X
B32: CEL-AD1-25 | C32: 3 | E32: X | K32: X
B33: CEL-AD1-26 | C33: 3 | H33: X | N33: X
B34: CEL-AD1-2 | C34: 3 | E34: X | K34: X
B35: CEL-AD1-3 | C35: 3 | E35: X | K35: X
B36: CEL-AD2-14 | C36: 3 | E36: X | K36: X
B37: CEL-AD2-15 | C37: 3 | E37: X | K37: X
B38: CEL-AD2-16 | C38: 3 | E38: X | K38: X
B39: CEL-LOG-1 | C39: 3 | D39: X | J39: X
B40: CEL-LOG-2 | C40: 3 | D40: X | J40: X
B41: CEL-LOG-3 | C41: 3 | D41: X | J41: X
B42: CEL-LOG-4 | C42: 3 | D42: X | J42: X
B43: CEL-LOG-5 | C43: 3 | D43: X | J43: X
B44: CEL-LOG-6 | C44: 3 | D44: X | J44: X
B45: CEL-LOG-7 | C45: 3 | D45: X | J45: X
B46: CEL-POR-3 | C46: 3 | G46: X | M46: X
B47: CLO-COM-1 | C47: 3 | I47: X | O47: X
B48: CLO-COM-2 | C48: 3 | I48: X | O48: X
B49: CLO-EXP-1 | C49: 3 | I49: X | O49: X
B50: CLO-EXP-2 | C50: 3 | I50: X | O50: X
B51: CLO-EXP-3 | C51: 3 | I51: X | O51: X
B52: CLO-SYC-2 | C52: 3 | I52: X | O52: X
B53: HPP-COM-20 | C53: 3 | D53: x | J53: x
B54: HPP-COM-21 | C54: 3 | D54: x | J54: x
B55: HPP-COM-22 | C55: 3 | D55: x | J55: x
B56: HPP-LIV-17 | C56: 3 | G56: X | M56: X
B57: HPP-LIV-18 | C57: 3 | G57: X | M57: X
B58: HPP-LIV-19 | C58: 3 | G58: X | M58: X
B59: MDF-AD1-1 | C59: 3 | I59: X | O59: X
B60: MDF-AD1-12 | C60: 3 | I60: X | O60: X
B61: MDF-AD1-13 | C61: 3 | I61: X | O61: X
B62: MDF-AD1-4 | C62: 3 | I62: X | O62: X
B63: MDF-AD1-5 | C63: 3 | I63: X | O63: X
B64: MDF-AD2-17 | C64: 3 | G64: X | M64: X
B65: MDF-AD2-18 | C65: 3 | G65: X | M65: X
B66: MDF-AD2-19 | C66: 3 | G66: X | M66: X
B67: MDF-AD2-25 | C67: 3 | F67: X | L67: X
B68: MDF-AD2-26 | C68: 3 | F68: X | L68: X
B69: MDF-AD2-27 | C69: 3 | F69: X | L69: X
B70: MDF-ALM-1 | C70: 3 | D70: X | J70: X
B71: MDF-ALM-3 | C71: 3 | H71: X | N71: X
B72: MDF-BAL-2 | C72: 3 | D72: X | J72: X
B73: MDF-ENF-3 | C73: 3 | I73: X | O73: X
B74: ASE-ADU-1 | C74: 3 | I74: X | O74: X
B75: ASE-ADU-2 | C75: 3 | I75: X | O75: X
B76: MDF-MAN-15 | C76: 3 | D76: X | J76: X
B77: MDF-MAN-16 | C77: 3 | D77: X | J77: X
B78: MDF-PTE-1 | C78: 3 | E78: X | K78: X
B79: MDF-PTE-2 | C79: 3 | E79: X | K79: X
B80: MDF-PTE-3 | C80: 3 | E80: X | K80: X
B81: MDF-PTE-4 | C81: 3 | E81: X | K81: X
B82: MDF-PTE-5 | C82: 3 | E82: X | K82: X
B83: PYP-AD1-3 | C83: 3 | F83: X | L83: X
B84: PYP-AD1-4 | C84: 3 | F84: X | L84: X
B85: PYP-AD1-28 | C85: 3 | F85: X | L85: X
B86: PYP-AD1-1 | C86: 3 | F86: X | L86: X
B87: PYP-HOS-4 | C87: 3 | H87: X | N87: X
B88: PYP-HOS-5 | C88: 3 | H88: X | N88: X
B89: PYP-HOS-6 | C89: 3 | H89: X | N89: X
B90: PYP-HOS-7 | C90: 3 | H90: X | N90: X
B91: PYP-HOS-8 | C91: 3 | H91: X | N91: X
B92: PYP-HOS-9 | C92: 3 | H92: X | N92: X
B93: PYP-HOS-10 | C93: 3 | H93: X | N93: X
B94: PYP-HOS-11 | C94: 3 | H94: X | N94: X
B95: PYP-HOS-12 | C95: 3 | F95: X | L95: X
B96: PYP-HOS-13 | C96: 3 | F96: X | L96: X
B97: PYP-HOS-14 | C97: 3 | F97: X | L97: X
B98: PYP-HOS-15 | C98: 3 | F98: X | L98: X
B99: PYP-HOS-16 | C99: 3 | F99: X | L99: X
B100: PYP-HOS-17 | C100: 3 | F100: X | L100: X
B101: PYP-HOS-18 | C101: 3 | F101: X | L101: X
B102: PYP-HOS-19 | C102: 3 | G102: X | M102: X
...

Sheet  avisos AA 
A1: Frecuencia | B1: Fecha de aviso | C1: Fin deseado | D1: Aviso | E1: Orden | F1: Status usuario | G1: Denominación | H1: Descripción | I1: Centro coste | J1: Ubicac.técnica | K1: Centro PtoTbjo
A2: Mensuales
A38: Trimestrales
A42: Semestrales
A45: Anuales | D45: 11284060
D46: 11283966
D47: 11283969
A48: Correctivos | D48: 11365329
D49: 11361131
D50: 11343931
D51: 11347328
D52: 11349605
D53: 11363343
D54: 11365323
D55: 11353566

Sheet BASE ELEC
A1: LOCALIDAD | B1: SEDE | C1: AREA | E1: TAREA | F1: CECO | G1: FREC | H1: 45597 | I1: 45627 | J1: 45658 | K1: 45689 | L1: 45717 | M1: 45748 | N1: 45778 | O1: 45809 | P1: 45839 | Q1: 45870 | R1: 45901 | S1: 45931 | T1: 45962 | U1: 45992 | V1: 46023 | W1: 46054 | X1: 46082
A2: ESPERANZA | B2: Garita R 12 | C2: SECTORES COMUNES | D2: GARI-GAR-RUT-ADMIN1 | E2: * Iluminación de espacios Comunes | F2: APOBA1-885 | G2: 1 | H2: 1 | I2: 1 | J2: 1 | K2: 1 | L2: 1 | M2: 1 | N2: 1 | O2: 1 | P2: 1 | Q2: 1 | R2: 1 | S2: 1 | T2: 1 | U2: 1 | V2: 1 | W2: 46082
A3: ESPERANZA | B3: Garita R 12 | C3: OFICINAS | D3: GARI-GAR-RUT-ADMIN1-OFCAMTRA | E3: * Iluminación y tomas de oficinas, estac tech | F3: APFES1-711 | G3: 1 | H3: 1 | I3: 1 | J3: 1 | K3: 1 | L3: 1 | M3: 1 | N3: 1 | O3: 1 | P3: 1 | Q3: 1 | R3: 1 | S3: 1 | T3: 1 | U3: 1 | V3: 1 | W3: 46113
A4: ESPERANZA | B4: Garita R 12 | C4: COMEDOR | D4: GARI-GAR-RUT-ADMIN1-COMEDOR1 | E4: *Iluminación y tomas de Comedor | F4: APFES1-711 | G4: 1 | H4: 1 | I4: 1 | J4: 1 | K4: 1 | L4: 1 | M4: 1 | N4: 1 | O4: 1 | P4: 1 | Q4: 1 | R4: 1 | S4: 1 | T4: 1 | U4: 1 | V4: 1 | W4: 46143
A5: ESPERANZA | B5: Garita R 12 | C5: SALA DE CAPACITACION | D5: GARI-GAR-RUT-ADMIN1-SALCAP01 | E5: *Iluminación y tomas de sala de capacitación | F5: APFES1-711 | G5: 1 | H5: 1 | I5: 1 | J5: 1 | K5: 1 | L5: 1 | M5: 1 | N5: 1 | O5: 1 | P5: 1 | Q5: 1 | R5: 1 | S5: 1 | T5: 1 | U5: 1 | V5: 1 | W5: 46174
A6: ESPERANZA | B6: Garita R 12 | C6: SECTORES COMUNES | D6: GARI-GAR-RUT-ADMIN1 | E6: TABLEROS PRINCIPALES Y SECCIONALES | F6: APOBA1-885 | G6: 4 | L6: 4 | W6: 46204
A7: ESPERANZA | B7: Garita R 12 | C7: SECTORES COMUNES | D7: GARI-GAR-RUT-ADMIN1-BAADMIN1 | E7: * Iluminación y tomas de baños | F7: APOBA1-885 | G7: 1 | H7: 1 | I7: 1 | J7: 1 | K7: 1 | L7: 1 | M7: 1 | N7: 1 | O7: 1 | P7: 1 | Q7: 1 | R7: 1 | S7: 1 | T7: 1 | U7: 1 | V7: 1 | W7: 46235
A8: ESPERANZA | B8: Garita R 12 | C8: OFICINAS | D8: GARI-GAR-RUT-ADMIN1-VIVGUAPA | E8: * Iluminación y tomas casa de guarda parque | F8: APFES1-711 | G8: 1 | H8: 1 | I8: 1 | J8: 1 | K8: 1 | L8: 1 | M8: 1 | N8: 1 | O8: 1 | P8: 1 | Q8: 1 | R8: 1 | S8: 1 | T8: 1 | U8: 1 | V8: 1 | W8: 46266
A9: ESPERANZA | B9: C L Bossetti | C9: CHALET | D9: BOSS-BOS-ADM-CHALET | E9: Tomas e iluminacion Interior del chalet | F9: APOBA1-872 | G9: 1 | H9: 1 | I9: 1 | J9: 1 | K9: 1 | L9: 1 | M9: 1 | N9: 1 | O9: 1 | P9: 1 | Q9: 1 | R9: 1 | S9: 1 | T9: 1 | U9: 1 | V9: 1 | W9: 46296
A10: ESPERANZA | B10: C L Bossetti | C10: CHALET | D10: BOSS-BOS-ADM-CHALET-PILETA01 | E10: Tomas e ilumina exterior del Chalet | F10: APOBA1-872 | G10: 1 | H10: 1 | I10: 1 | J10: 1 | K10: 1 | L10: 1 | M10: 1 | N10: 1 | O10: 1 | P10: 1 | Q10: 1 | R10: 1 | S10: 1 | T10: 1 | U10: 1 | V10: 1 | W10: 46327
A11: ESPERANZA | B11: C L Bossetti | C11: CHALET | D11: BOSS-BOS-ADM-CHALET-TABLEROS | E11: Rotulado de tablero | F11: APOBA1-872 | G11: 4 | W11: 46357
A12: ESPERANZA | B12: C L Bossetti | C12: CHALET | D12: BOSS-BOS-ADM-CASACU | E12: Iluminación ext perim casa cuidador | F12: APOBA1-872 | G12: 1 | H12: 1 | I12: 1 | J12: 1 | K12: 1 | L12: 1 | M12: 1 | N12: 1 | O12: 1 | P12: 1 | Q12: 1 | R12: 1 | S12: 1 | T12: 1 | U12: 1 | V12: 1 | W12: 46388
A13: ESPERANZA | B13: C L Bossetti | C13: SECTORES COMUNES | D13: BOSS-BOS-ADM-ADMIN1 | E13: Iluminación ext sector ex administración | F13: APOBA1-872 | G13: 1 | H13: 1 | I13: 1 | J13: 1 | K13: 1 | L13: 1 | M13: 1 | N13: 1 | O13: 1 | P13: 1 | Q13: 1 | R13: 1 | S13: 1 | T13: 1 | U13: 1 | V13: 1 | W13: 46419
A14: ESPERANZA | B14: Club Residencia | C14: SECTORES COMUNES | D14: ESPE-ESP-CLU-CLUBRE | E14: Ilum de calles internas CLUB | F14: APOBA1-886 | G14: 2 | J14: 2 | M14: 2 | P14: 2 | S14: 2 | V14: 2 | W14: 46447
A15: ESPERANZA | B15: PREDIO YPORA | C15: SECTORES COMUNES | D15: YPOR-YPO | E15: Iluminacion de calles internas | F15: APOBA1-886 | G15: 1 | H15: 1 | I15: 1 | J15: 1 | K15: 1 | L15: 1 | M15: 1 | N15: 1 | O15: 1 | P15: 1 | Q15: 1 | R15: 1 | S15: 1 | T15: 1 | U15: 1 | V15: 1 | W15: 46478
A16: ESPERANZA | B16: PREDIO YPORA | C16: OFICINAS | D16: YPOR-YPO-GOF-ADMIN1 | E16: tomas e ilum de oficinas de GOF | F16: APFES1-701 | G16: 1 | H16: 1 | I16: 1 | J16: 1 | K16: 1 | L16: 1 | M16: 1 | N16: 1 | O16: 1 | P16: 1 | Q16: 1 | R16: 1 | S16: 1 | T16: 1 | U16: 1 | V16: 1 | W16: 46508
A17: ESPERANZA | B17: PREDIO YPORA | C17: OFICINAS | D17: YPOR-YPO-GOF-VIGILA | E17: Tomas e iluminación de vigilancia | F17: APOBA1-895 | G17: 1 | H17: 1 | I17: 1 | J17: 1 | K17: 1 | L17: 1 | M17: 1 | N17: 1 | O17: 1 | P17: 1 | Q17: 1 | R17: 1 | S17: 1 | T17: 1 | U17: 1 | V17: 1 | W17: 46539
A18: ESPERANZA | B18: PREDIO YPORA | C18: OFICINAS | D18: YPOR-YPO-GOF-LABORA | E18: Tomas e ilum de Laboratorios | F18: APFES1-714 | G18: 1 | H18: 1 | I18: 1 | J18: 1 | K18: 1 | L18: 1 | M18: 1 | N18: 1 | O18: 1 | P18: 1 | Q18: 1 | R18: 1 | S18: 1 | T18: 1 | U18: 1 | V18: 1 | W18: 46569
A19: ESPERANZA | B19: PREDIO YPORA | C19: HOTEL | D19: YPOR-YPO-HOT-PLANTA-HABIT | E19: Hostería Tomas e ilum | F19: APOBA1-886 | G19: 1 | H19: 1 | I19: 1 | J19: 1 | K19: 1 | L19: 1 | M19: 1 | N19: 1 | O19: 1 | P19: 1 | Q19: 1 | R19: 1 | S19: 1 | T19: 1 | U19: 1 | V19: 1 | W19: 46600
A20: ESPERANZA | B20: PREDIO YPORA | C20: HOTEL | D20: YPOR-YPO-HOT-PLANTA-PASILLO | E20: Hostería Tomas e ilum de pasillos | F20: APOBA1-886 | G20: 1 | H20: 1 | I20: 1 | J20: 1 | K20: 1 | L20: 1 | M20: 1 | N20: 1 | O20: 1 | P20: 1 | Q20: 1 | R20: 1 | S20: 1 | T20: 1 | U20: 1 | V20: 1 | W20: 46631
A21: ESPERANZA | B21: PREDIO YPORA | C21: HOTEL | D21: YPOR-YPO-HOT-HOTEL1-COCINA | E21: Hostería Tomas e ilum cocina | F21: APOBA1-886 | G21: 1 | H21: 1 | I21: 1 | J21: 1 | K21: 1 | L21: 1 | M21: 1 | N21: 1 | O21: 1 | P21: 1 | Q21: 1 | R21: 1 | S21: 1 | T21: 1 | U21: 1 | V21: 1 | W21: 46661
A22: ESPERANZA | B22: PREDIO YPORA | C22: HOTEL | D22: YPOR-YPO-HOT-HOTEL1-SALCOMED | E22: Hostería Tomas e ilum | F22: APOBA1-886 | G22: 1 | H22: 1 | I22: 1 | J22: 1 | K22: 1 | L22: 1 | M22: 1 | N22: 1 | O22: 1 | P22: 1 | Q22: 1 | R22: 1 | S22: 1 | T22: 1 | U22: 1 | V22: 1 | W22: 46692
A23: ESPERANZA | B23: PREDIO YPORA | C23: HOTEL | D23: YPOR-YPO-HOT-HOTEL1-LAVADERO | E23: Hostería Tomas e ilum de sec servicios | F23: APOBA1-886 | G23: 1 | H23: 1 | I23: 1 | J23: 1 | K23: 1 | L23: 1 | M23: 1 | N23: 1 | O23: 1 | P23: 1 | Q23: 1 | R23: 1 | S23: 1 | T23: 1 | U23: 1 | V23: 1 | W23: 46722
A24: ESPERANZA | B24: PREDIO YPORA | C24: HOTEL | D24: YPOR-YPO-HOT-HOTEL1-GIMNASIO | E24: Hostería Tomas e ilum de sector GIM | F24: APOBA1-886 | G24: 1 | H24: 1 | I24: 1 | J24: 1 | K24: 1 | L24: 1 | M24: 1 | N24: 1 | O24: 1 | P24: 1 | Q24: 1 | R24: 1 | S24: 1 | T24: 1 | U24: 1 | V24: 1 | W24: 46753
A25: ESPERANZA | B25: PREDIO YPORA | C25: HOTEL | D25: YPOR-YPO-HOT-HOTEL1-SALA REUN | E25: Hostería Tomas e ilum sec s reuniones | F25: APOBA1-886 | G25: 1 | H25: 1 | I25: 1 | J25: 1 | K25: 1 | L25: 1 | M25: 1 | N25: 1 | O25: 1 | P25: 1 | Q25: 1 | R25: 1 | S25: 1 | T25: 1 | U25: 1 | V25: 1 | W25: 46784
A26: ESPERANZA | B26: PREDIO YPORA | C26: HOTEL | D26: YPOR-YPO-HOT-EXTERN | E26: Hostería sector externo ( iluminación) | F26: APOBA1-886 | G26: 1 | H26: 1 | I26: 1 | J26: 1 | K26: 1 | L26: 1 | M26: 1 | N26: 1 | O26: 1 | P26: 1 | Q26: 1 | R26: 1 | S26: 1 | T26: 1 | U26: 1 | V26: 1 | W26: 46813
A27: ESPERANZA | B27: PREDIO YPORA | C27: HOTEL | D27: YPOR-YPO-HOT-TABLEROS | E27: Verificar tableros y rotular | F27: APOBA1-886 | G27: 4 | L27: 4 | W27: 46844
A28: ESPERANZA | B28: ESPERANZA B | C28: MZ 128 CASA 1 | D28: ESPE-ESP-ESB-MAN128-CASA0001 | E28: VERIFICAR ELEMENTOS DE PROTECCION | F28: APOBA1-886 | G28: 4 | T28: 4 | W28: 46874
A29: ESPERANZA | B29: ESPERANZA B | C29: MZ 128 CASA 2 | D29: ESPE-ESP-ESB-MAN128-CASA0002 | E29: VERIFICAR ELEMENTOS DE PROTECCION | F29: APOBA1-886 | G29: 4 | W29: 46905
A30: ESPERANZA | B30: ESPERANZA B | C30: MZ 128 CASA 3 | D30: ESPE-ESP-ESB-MAN128-CASA0003 | E30: VERIFICAR ELEMENTOS DE PROTECCION | F30: APOBA1-886 | G30: 4 | W30: 46935
A31: ESPERANZA | B31: ESPERANZA B | C31: MZ 129 CASA 1 | D31: ESPE-ESP-ESB-MAN129-CASA0001 | E31: VERIFICAR ELEMENTOS DE PROTECCION | F31: APOBA1-886 | G31: 4 | W31: 46966
A32: ESPERANZA | B32: ESPERANZA B | C32: MZ 129 CASA 2 | D32: ESPE-ESP-ESB-MAN129-CASA0002 | E32: VERIFICAR ELEMENTOS DE PROTECCION | F32: APOBA1-886 | G32: 4 | J32: 4 | W32: 46997
A33: ESPERANZA | B33: ESPERANZA B | C33: MZ 129 CASA 3 | D33: ESPE-ESP-ESB-MAN129-CASA0003 | E33: VERIFICAR ELEMENTOS DE PROTECCION | F33: APOBA1-886 | G33: 4 | P33: 4 | W33: 47027
A34: ESPERANZA | B34: ESPERANZA B | C34: MZ 129 CASA 4 | D34: ESPE-ESP-ESB-MAN129-CASA0004 | E34: VERIFICAR ELEMENTOS DE PROTECCION | F34: APOBA1-886 | G34: 4 | W34: 47058
A35: ESPERANZA | B35: ESPERANZA B | C35: MZ 130 CASA 1 | D35: ESPE-ESP-ESB-MAN130-CASA0001 | E35: VERIFICAR ELEMENTOS DE PROTECCION | F35: APOBA1-886 | G35: 4 | I35: 4 | Q35: 4 | W35: 47088
A36: ESPERANZA | B36: ESPERANZA B | C36: MZ 130 CASA 2 | D36: ESPE-ESP-ESB-MAN130-CASA0002 | E36: VERIFICAR ELEMENTOS DE PROTECCION | F36: APOBA1-886 | G36: 4 | Q36: 4 | W36: 47119
A37: ESPERANZA | B37: ESPERANZA B | C37: MZ 130 CASA 3 | D37: ESPE-ESP-ESB-MAN130-CASA0003 | E37: VERIFICAR ELEMENTOS DE PROTECCION | F37: APOBA1-886 | G37: 4 | K37: 4 | W37: 47150
A38: ESPERANZA | B38: ESPERANZA B | C38: MZ 130 CASA 4 | D38: ESPE-ESP-ESB-MAN130-CASA0004 | E38: VERIFICAR ELEMENTOS DE PROTECCION | F38: APOBA1-886 | G38: 4 | I38: 4 | T38: 4
A39: ESPERANZA | B39: ESPERANZA B | C39: MZ 130 CASA 5 | D39: ESPE-ESP-ESB-MAN130-CASA0005 | E39: VERIFICAR ELEMENTOS DE PROTECCION | F39: APOBA1-886 | G39: 4 | U39: 4
A40: ESPERANZA | B40: ESPERANZA B | C40: MZ 130 CASA 6 | D40: ESPE-ESP-ESB-MAN130-CASA0006 | E40: VERIFICAR ELEMENTOS DE PROTECCION | F40: APOBA1-886 | G40: 4
A41: ESPERANZA | B41: ESPERANZA B | C41: MZ 130 CASA 7 | D41: ESPE-ESP-ESB-MAN130-CASA0007 | E41: VERIFICAR ELEMENTOS DE PROTECCION | F41: APOBA1-886 | G41: 4 | Q41: 4
A42: ESPERANZA | B42: ESPERANZA B | C42: MZ 130 CASA 8 | D42: ESPE-ESP-ESB-MAN130-CASA0008 | E42: VERIFICAR ELEMENTOS DE PROTECCION | F42: APOBA1-886 | G42: 4
A43: ESPERANZA | B43: ESPERANZA B | C43: MZ 130 CASA 9 | D43: ESPE-ESP-ESB-MAN130-CASA0009 | E43: VERIFICAR ELEMENTOS DE PROTECCION | F43: APOBA1-886 | G43: 4 | P43: 4
A44: ESPERANZA | B44: ESPERANZA B | C44: MZ 132 CASA 1 | D44: ESPE-ESP-ESB-MAN132-CASA0001 | E44: VERIFICAR ELEMENTOS DE PROTECCION | F44: APOBA1-886 | G44: 4
A45: ESPERANZA | B45: ESPERANZA B | C45: MZ 132 CASA 2 | D45: ESPE-ESP-ESB-MAN132-CASA0002 | E45: VERIFICAR ELEMENTOS DE PROTECCION | F45: APOBA1-886 | G45: 4
A46: ESPERANZA | B46: ESPERANZA B | C46: MZ 132 CASA 3 | D46: ESPE-ESP-ESB-MAN132-CASA0003 | E46: VERIFICAR ELEMENTOS DE PROTECCION | F46: APOBA1-886 | G46: 4
A47: ESPERANZA | B47: ESPERANZA B | C47: MZ 132 CASA 4 | D47: ESPE-ESP-ESB-MAN132-CASA0004 | E47: VERIFICAR ELEMENTOS DE PROTECCION | F47: APOBA1-886 | G47: 4 | J47: 4
A48: ESPERANZA | B48: ESPERANZA B | C48: MZ 132 CASA 5 | D48: ESPE-ESP-ESB-MAN132-CASA0005 | E48: VERIFICAR ELEMENTOS DE PROTECCION | F48: APOBA1-886 | G48: 4
A49: ESPERANZA | B49: ESPERANZA B | C49: MZ 132 CASA 6 | D49: ESPE-ESP-ESB-MAN132-CASA0006 | E49: VERIFICAR ELEMENTOS DE PROTECCION | F49: APOBA1-886 | G49: 4 | P49: 4
A50: ESPERANZA | B50: ESPERANZA B | C50: MZ 132 CASA 10 | D50: ESPE-ESP-ESB-MAN132-CASA0010 | E50: VERIFICAR ELEMENTOS DE PROTECCION | F50: APOBA1-886 | G50: 4 | O50: 4
A51: ESPERANZA | B51: ESPERANZA B | C51: MZ 133 CASA 1 | D51: ESPE-ESP-ESB-MAN133-CASA0001 | E51: VERIFICAR ELEMENTOS DE PROTECCION | F51: APOBA1-886 | G51: 4
A52: ESPERANZA | B52: ESPERANZA B | C52: MZ 133 CASA 2 | D52: ESPE-ESP-ESB-MAN133-CASA0002 | E52: VERIFICAR ELEMENTOS DE PROTECCION | F52: APOBA1-886 | G52: 4
A53: ESPERANZA | B53: ESPERANZA B | C53: MZ 133 CASA 3 | D53: ESPE-ESP-ESB-MAN133-CASA0003 | E53: VERIFICAR ELEMENTOS DE PROTECCION | F53: APOBA1-886 | G53: 4 | J53: 4
A54: ESPERANZA | B54: ESPERANZA B | C54: MZ 133 CASA 4 | D54: ESPE-ESP-ESB-MAN133-CASA0004 | E54: VERIFICAR ELEMENTOS DE PROTECCION | F54: APOBA1-886 | G54: 4 | Q54: 4
A55: ESPERANZA | B55: ESPERANZA B | C55: MZ 133 CASA 13 | D55: ESPE-ESP-ESB-MAN133-CASA0005 | E55: VERIFICAR ELEMENTOS DE PROTECCION | F55: APOBA1-886 | G55: 4 | I55: 4
A56: ESPERANZA | B56: ESPERANZA B | C56: MZ 133 CASA 14 | D56: ESPE-ESP-ESB-MAN133-CASA0006 | E56: VERIFICAR ELEMENTOS DE PROTECCION | F56: APOBA1-886 | G56: 4 | U56: 4
A57: ESPERANZA | B57: ESPERANZA B | C57: MZ 133 CASA 15 | D57: ESPE-ESP-ESB-MAN133-CASA0007 | E57: VERIFICAR ELEMENTOS DE PROTECCION | F57: APOBA1-886 | G57: 4 | Q57: 4
A58: ESPERANZA | B58: ESPERANZA B | C58: MZ 133 CASA 16 | D58: ESPE-ESP-ESB-MAN133-CASA0008 | E58: VERIFICAR ELEMENTOS DE PROTECCION | F58: APOBA1-886 | G58: 4 | U58: 4
A59: ESPERANZA | B59: ESPERANZA B | C59: MZ 134 CASA 1 | D59: ESPE-ESP-ESB-MAN134-CASA0001 | E59: VERIFICAR ELEMENTOS DE PROTECCION | F59: APOBA1-886 | G59: 4 | M59: 4
A60: ESPERANZA | B60: ESPERANZA B | C60: MZ 134 CASA 2 | D60: ESPE-ESP-ESB-MAN134-CASA0002 | E60: VERIFICAR ELEMENTOS DE PROTECCION | F60: APOBA1-886 | G60: 4
A61: ESPERANZA | B61: ESPERANZA B | C61: MZ 134 CASA 3 | D61: ESPE-ESP-ESB-MAN134-CASA0003 | E61: VERIFICAR ELEMENTOS DE PROTECCION | F61: APOBA1-886 | G61: 4 | P61: 4
A62: ESPERANZA | B62: ESPERANZA B | C62: MZ 134 CASA 4 | D62: ESPE-ESP-ESB-MAN134-CASA0004 | E62: VERIFICAR ELEMENTOS DE PROTECCION | F62: APOBA1-886 | G62: 4 | T62: 4
A63: ESPERANZA | B63: ESPERANZA B | C63: MZ 134 CASA 5 | D63: ESPE-ESP-ESB-MAN134-CASA0005 | E63: VERIFICAR ELEMENTOS DE PROTECCION | F63: APOBA1-886 | G63: 4
A64: ESPERANZA | B64: ESPERANZA B | C64: MZ 134 CASA 6 | D64: ESPE-ESP-ESB-MAN134-CASA0006 | E64: VERIFICAR ELEMENTOS DE PROTECCION | F64: APOBA1-886 | G64: 4 | I64: 4
A65: ESPERANZA | B65: ESPERANZA B | C65: MZ 135 CASA 1 | D65: ESPE-ESP-ESB-MAN135-CASA0001 | E65: VERIFICAR ELEMENTOS DE PROTECCION | F65: APOBA1-886 | G65: 4 | I65: 4
A66: ESPERANZA | B66: ESPERANZA B | C66: MZ 135 CASA 2 | D66: ESPE-ESP-ESB-MAN135-CASA0002 | E66: VERIFICAR ELEMENTOS DE PROTECCION | F66: APOBA1-886 | G66: 4
A67: ESPERANZA | B67: ESPERANZA B | C67: MZ 135 CASA 3 | D67: ESPE-ESP-ESB-MAN135-CASA0003 | E67: VERIFICAR ELEMENTOS DE PROTECCION | F67: APOBA1-886 | G67: 4 | I67: 4 | Q67: 4
A68: ESPERANZA | B68: ESPERANZA B | C68: MZ 135 CASA 4 | D68: ESPE-ESP-ESB-MAN135-CASA0004 | E68: VERIFICAR ELEMENTOS DE PROTECCION | F68: APOBA1-886 | G68: 4
A69: ESPERANZA | B69: ESPERANZA B | C69: MZ 135 CASA 5 | D69: ESPE-ESP-ESB-MAN135-CASA0005 | E69: VERIFICAR ELEMENTOS DE PROTECCION | F69: APOBA1-886 | G69: 4 | J69: 4 | M69: 4
A70: ESPERANZA | B70: ESPERANZA B | C70: MZ 135 CASA 6 | D70: ESPE-ESP-ESB-MAN135-CASA0006 | E70: VERIFICAR ELEMENTOS DE PROTECCION | F70: APOBA1-886 | G70: 4 | Q70: 4
A71: ESPERANZA | B71: ESPERANZA B | C71: MZ 135 CASA 10 | D71: ESPE-ESP-ESB-MAN135-CASA0010 | E71: VERIFICAR ELEMENTOS DE PROTECCION | F71: APOBA1-886 | G71: 4 | Q71: 4
A72: ESPERANZA | B72: ESPERANZA B | C72: MZ 136 CASA 12 | D72: ESPE-ESP-ESB-MAN136-CASA0012 | E72: VERIFICAR ELEMENTOS DE PROTECCION | F72: APOBA1-886 | G72: 4 | I72: 4
A73: ESPERANZA | B73: ESPERANZA B | C73: MZ 136 C 13 DPTO 1 | D73: ESPE-ESP-ESB-MAN136-DEPTO001 | E73: VERIFICAR ELEMENTOS DE PROTECCION | F73: APOBA1-886 | G73: 4
A74: ESPERANZA | B74: ESPERANZA B | C74: MZ 136 C 13 DPTO 2 | D74: ESPE-ESP-ESB-MAN136-DEPTO002 | E74: VERIFICAR ELEMENTOS DE PROTECCION | F74: APOBA1-886 | G74: 4 | K74: 4
A75: ESPERANZA | B75: ESPERANZA B | C75: MZ 136 C 13 DPTO 3 | D75: ESPE-ESP-ESB-MAN136-DEPTO003 | E75: VERIFICAR ELEMENTOS DE PROTECCION | F75: APOBA1-886 | G75: 4 | I75: 4
A76: ESPERANZA | B76: ESPERANZA B | C76: MZ 136 CASA 14 | D76: ESPE-ESP-ESB-MAN136-CASA0014 | E76: VERIFICAR ELEMENTOS DE PROTECCION | F76: APOBA1-886 | G76: 4
A77: ESPERANZA | B77: KM 1 | C77: SECTORES COMUNES | D77: ESPE-ESP-KM1-MANZA1 | E77: Iluminación de calles inter y acceso al barrio | F77: APOBA1-886 | G77: 1 | H77: 1 | I77: 1 | J77: 1 | K77: 1 | M77: 1 | N77: 1 | O77: 1 | P77: 1 | Q77: 1 | R77: 1 | S77: 1 | T77: 1 | U77: 1 | V77: 1
A78: ESPERANZA | B78: KM 1 | C78: SECTORES COMUNES | D78: ESPE-ESP-KM1-MANZA1 | E78: CCM del barrio y rotular | F78: APOBA1-886 | G78: 3 | H78: 3 | N78: 3
A79: ESPERANZA | B79: KM 1 | C79: SECTORES COMUNES | D79: ESPE-ESP-KM1-MANZA1 | E79: Tableros secc VERIFICAR y rotular | F79: APOBA1-886 | G79: 3 | H79: 3 | N79: 3
A80: ESPERANZA | B80: KM 1 | C80: SECTORES COMUNES | D80: ESPE-ESP-KM1-MANZA1 | E80: Tablero sistema bombeo y rotular | F80: APOBA1-886 | G80: 3 | H80: 3 | P80: 3
A81: ESPERANZA | B81: KM 1 | C81: SECTORES COMUNES | D81: ESPE-ESP-KM1-MANZA1 | E81: Sistema auto de bombas y rotular | F81: APOBA1-886 | G81: 2 | J81: 2 | M81: 2 | P81: 2 | V81: 2
A82: ESPERANZA | B82: KM 1 | C82: CASA 1 Y 2 | D82: ESPE-ESP-KM1-MANZA1-CASA0001 | E82: VERIFICAR ELEMENTOS DE PROTECCION | F82: APOBA1-886 | G82: 4 | N82: 4
A83: ESPERANZA | B83: KM 1 | C83: CASA 3 | D83: ESPE-ESP-KM1-MANZA1-CASA0003 | E83: VERIFICAR ELEMENTOS DE PROTECCION | F83: APOBA1-886 | G83: 4
A84: ESPERANZA | B84: KM 1 | C84: CASA 4 | D84: ESPE-ESP-KM1-MANZA1-CASA0004 | E84: VERIFICAR ELEMENTOS DE PROTECCION | F84: APOBA1-886 | G84: 4 | L84: 4
A85: ESPERANZA | B85: KM 1 | C85: CASA 5 | D85: ESPE-ESP-KM1-MANZA1-CASA0005 | E85: VERIFICAR ELEMENTOS DE PROTECCION | F85: APOBA1-886 | G85: 4 | K85: 4 | Q85: 4
A86: ESPERANZA | B86: KM 1 | C86: CASA 6 | D86: ESPE-ESP-KM1-MANZA1-CASA0006 | E86: VERIFICAR ELEMENTOS DE PROTECCION | F86: APOBA1-886 | G86: 4 | T86: 4
A87: ESPERANZA | B87: KM 1 | C87: CASA 7 | D87: ESPE-ESP-KM1-MANZA1-CASA0007 | E87: VERIFICAR ELEMENTOS DE PROTECCION | F87: APOBA1-886 | G87: 4 | H87: 4 | Q87: 4
A88: ESPERANZA | B88: KM 1 | C88: CASA 8 | D88: ESPE-ESP-KM1-MANZA1-CASA0008 | E88: VERIFICAR ELEMENTOS DE PROTECCION | F88: APOBA1-886 | G88: 4 | U88: 4
A89: ESPERANZA | B89: KM 1 | C89: CASA 9 | D89: ESPE-ESP-KM1-MANZA1-CASA0009 | E89: VERIFICAR ELEMENTOS DE PROTECCION | F89: APOBA1-886 | G89: 4 | P89: 4
A90: ESPERANZA | B90: KM 1 | C90: CASA 10 | D90: ESPE-ESP-KM1-MANZA1-CASA0010 | E90: VERIFICAR ELEMENTOS DE PROTECCION | F90: APOBA1-886 | G90: 4 | K90: 4
A91: ESPERANZA | B91: KM 1 | C91: CASA 11 | D91: ESPE-ESP-KM1-MANZA1-CASA0011 | E91: VERIFICAR ELEMENTOS DE PROTECCION | F91: APOBA1-886 | G91: 4
A92: ESPERANZA | B92: KM 1 | C92: CASA 12 | D92: ESPE-ESP-KM1-MANZA1-CASA0012 | E92: VERIFICAR ELEMENTOS DE PROTECCION | F92: APOBA1-886 | G92: 4 | U92: 4
A93: ESPERANZA | B93: KM 1 | C93: CASA 13 | D93: ESPE-ESP-KM1-MANZA1-CASA0013 | E93: VERIFICAR ELEMENTOS DE PROTECCION | F93: APOBA1-886 | G93: 4
A94: ESPERANZA | B94: KM 1 | C94: CASA 14 | D94: ESPE-ESP-KM1-MANZA1-CASA0014 | E94: VERIFICAR ELEMENTOS DE PROTECCION | F94: APOBA1-886 | G94: 4 | M94: 4
A95: ESPERANZA | B95: KM 1 | C95: CASA 15 | D95: ESPE-ESP-KM1-MANZA1-CASA0015 | E95: VERIFICAR ELEMENTOS DE PROTECCION | F95: APOBA1-886 | G95: 4 | T95: 4
A96: ESPERANZA | B96: KM 1 | C96: CASA 16 | D96: ESPE-ESP-KM1-MANZA1-CASA0016 | E96: VERIFICAR ELEMENTOS DE PROTECCION | F96: APOBA1-886 | G96: 4 | T96: 4
A97: ESPERANZA | B97: KM 1 | C97: CASA 17 | D97: ESPE-ESP-KM1-MANZA1-CASA0017 | E97: VERIFICAR ELEMENTOS DE PROTECCION | F97: APOBA1-886 | G97: 4 | P97: 4
A98: ESPERANZA | B98: KM 1 | C98: CASA 18 | D98: ESPE-ESP-KM1-MANZA1-CASA0018 | E98: VERIFICAR ELEMENTOS DE PROTECCION | F98: APOBA1-886 | G98: 4 | L98: 4 | T98: 4
A99: ESPERANZA | B99: KM 1 | C99: CASA 19 | D99: ESPE-ESP-KM1-MANZA1-CASA0019 | E99: VERIFICAR ELEMENTOS DE PROTECCION | F99: APOBA1-886 | G99: 4 | M99: 4
A100: ESPERANZA | B100: KM 1 | C100: CASA 20 | D100: ESPE-ESP-KM1-MANZA1-CASA0020 | E100: VERIFICAR ELEMENTOS DE PROTECCION | F100: APOBA1-886 | G100: 4 | J100: 4
...

Sheet Avisos Elec
A1: Frecuencia | B1: Fecha de aviso | C1: Fin deseado | D1: Aviso | E1: Orden | F1: Status usuario | G1: Denominación | H1: Descripción | I1: Centro coste | J1: Ubicac.técnica | K1: Centro PtoTbjo
A2: MENSUALES
A48: Trimestrales
A50: Semestrales
A52: Anuales
A60: Correctivos | D60: 11359020
D61: 11356980
D62: 11358446
D63: 11358374
D64: 11359585
D65: 11345492
D66: 11358400
D67: 11358450
D68: 11342706
D69: 11342704
D70: 11358981
D71: 11361131
D72: 11338596
... D77: 11362381

Sheet BASE GE
B4: Sede | C4: UT | D4: Detalle | E4: Potencia | F4: Responsable | G4: CODIGO | H4: 45597 | I4: 45627 | J4: 45658 | K4: 45689 | L4: 45717 | M4: 45748 | N4: 45778 | O4: 45809 | P4: 45839 | Q4: 45658 | R4: 45689 | S4: 45717 | T4: 45748 | U4: 45778 | V4: 45809 | W4: 45839 | X4: 45870 | Y4: 45901 | Z4: 45931 | AA4: 45962 | AB4: 45992 | AC4: Fecha realizacion
A5: básico | B5: Bossetti | C5: BOSS-BOS-ADM-VIVERO | D5: Grupo Electrógeno Diésel | E5: 80 KVA | F5: Vivero | G5: GGE-80KVA-VIB | L5: Service | U5: Check | AA5: ** Service | AD5: 45982
A6: básico | B6: Y-Pora | C6: YPOR-YPO-GOF-VIVERO | D6: Grupo Electrógeno Diésel | E6: 132 KVA | F6: Vivero | G6: GGE-132KVA-VIB | H6: Check | T6: Service | AA6: Service | AD6: 45971
A7: básico | B7: Bossetti | C7: BOSS-BOS-ADM-CHALET | D7: Grupo Electrógeno Nafta | E7: 10 kVA | F7: SS.GG. | G7: GGE-12KVA-CHB | M7: Service
A8: básico | B8: Bossetti | C8: BOSS-BOS-ADM-ADMIN1 | D8: Grupo Electrógeno Diésel | E8: 31 kVA | F8: CLB | G8: GGE-31KVA-CLB | I8: Service | X8: Check
A9: básico | B9: Bossetti | C9: BOSS-BOS-ADM-ADMIN1 | D9: Grupo Electrógeno Nafta | E9: 7,5 KVA | F9: CLB | G9: GGE-7,5KVA-CLB | I9: Check | N9: Service | V9: Service | X9: Check
A10: básico | B10: Y-Pora | C10: YPOR-YPO-GOF- | D10: Grupo Electrógeno Diésel | E10: 164 KVA | F10: GOF | G10: GGE-164KVA-VYP | U10: Check | AA10: Check | AD10: 45971
A11: básico | B11: Y-Pora | C11: YPOR-YPO-HOT | D11: Grupo Electrógeno Diésel | E11: 100 KVA | F11: SS.GG. | G11: GGE-100KVA-HYP | L11: Service | T11: Service | AA11: Ckeck | AB11: 46008 | AD11: 45971 | AE11: 17/12/25 se cambio tablero con transferencia nueva
A12: básico | B12: Celulosa | C12: ESPE-ESP-CEL-BALANZ | D12: Grupo Electrógeno Nafta | E12: 10 KVA | F12: SS.GG. | G12: GGE-10KVA-BAC | R12: Check | U12: Service | AA12: Check | AD12: 45975
A13: básico | B13: Piray | C13: PIRA-PIR-MDF-BALANZ | D13: Grupo Electrógeno Nafta | E13: 7,5 KVA | F13: SS.GG. | G13: GGE-7,5KVA-BAP | O13: Service | R13: Ckeck | Z13: Service | AD13: 45931
A14: básico | B14: PALMITOS | C14: YPOR-YPO-GOF | D14: Grupo Electrógeno Diésel | E14: 31,3 KVA | F14: FORESTAL | G14: GGE-31,3KVA-PAL
A15: básico | B15: PALMITOS | C15: YPOR-YPO-GOF | D15: Grupo Electrógeno Nafta | E15: 7,5 KVA | F15: FORESTAL | G15: GGE-7,5KVA-PAL | H15: Service | M15: Service
A16: básico | B16: ELDORADO | C16: PIRA-PIR-ELD-CASGTE-KM8GTECE | D16: Grupo Electrógeno Nafta | E16: 11 KVA | F16: SS.GG. | G16: GGE-11KVA-GCE | H16: Service | V16: Check
A17: Adicional | B17: Celulosa | C17: ESPE-ESP-CEL-ADMIN2-OFSGTECO | D17: Grupo Electrógeno Nafta | E17: 11 KVA | F17: SS.GG. | G17: GGE-11KVA-DSG | N17: Check
A18: Adicional | B18: Bossetti | C18: BOSS-BOS-ADM-VIVERO | D18: Grupo Electrógeno Diésel | E18: 100 KVA | F18: Vivero | G18: GGE-100KVA-VIB | U18: Check | AA18: Service | AD18: 45982
A20: Basico | B20: Bosetti | C20: BOSS-BOS-ADM-CHALET | D20: Grupo Electrógeno Diésel | E20: 40 KVA | F20: Chalet | G20: PM02CLB40KVA | W20: Service
A22: ** correspondia un service, pero a pedido de Diego Olocco no se cambia el aceite

Sheet Avisos Generadores 
A1: Frecuencia | B1: Fecha de aviso | C1: Fin deseado | D1: Aviso | E1: Orden | F1: Status usuario | G1: Denominación | H1: Descripción | I1: Potencia | J1: Ubicac.técnica | K1: Centro PtoTbjo | L1: Fecha realizado

Sheet recursos
B2: Proveedor : SEAM Servicios Eléctricos S.R.L
B3: CM 3100000914
B4: Servicio Básico : Febrero 2026
N6: Planta | O6: (Todas)
A7: Fecha | B7: Día | C7: Mes | D7: Días Hábiles | E7: Clemente A. | F7: Tesari H | G7: Caceres Oscar | H7: Arevalo Oscar | I7: Gerardo | J7: Davalos Cesar
A8: 1 | B8: Domingo | C8: Febrero | N8: Etiquetas de fila | O8: Suma de TotalHs
A9: 2 | B9: Lunes | C9: Febrero | D9: 1 | E9: 1 | F9: 1 | G9: 1 | H9: 1 | I9: 1 | J9: 1 | N9: AQUINO CLEMENTE | O9: 4.5777778
A10: 3 | B10: Martes | C10: Febrero | D10: 1 | E10: 1 | F10: 1 | G10: 1 | H10: 1 | I10: 1 | J10: 1 | N10: AREVALOS OSCAR | O10: 3.2527778
A11: 4 | B11: Miércoles | C11: Febrero | D11: 1 | E11: 1 | F11: 1 | G11: 1 | H11: 1 | I11: 1 | J11: 1 | N11: CACERES OSCAR | O11: 3.2659722
A12: 5 | B12: Jueves | C12: Febrero | D12: 1 | E12: 1 | F12: 1 | G12: 1 | H12: 1 | I12: 1 | J12: 1 | N12: DAVALOS CESAR | O12: 2.9368056
A13: 6 | B13: Viernes | C13: Febrero | D13: 1 | E13: 1 | F13: 1 | G13: 1 | H13: 1 | I13: 1 | N13: DUARTE ANTONIO | O13: 4.5284722
A14: 7 | B14: Sábado | C14: Febrero | F14: 1 | N14: PEREYRA BRUNO | O14: 5.2527778
A15: 8 | B15: Domingo | C15: Febrero | N15: TESARI HECTOR | O15: 3.0520833
A16: 9 | B16: Lunes | C16: Febrero | D16: 1 | E16: 1 | F16: 1 | G16: 1 | H16: 1 | I16: 1 | J16: 1 | N16: WORONOWICZ GERARDO | O16: 7.0055556
A17: 10 | B17: Martes | C17: Febrero | D17: 1 | E17: 1 | F17: 1 | G17: 1 | H17: 1 | I17: 1 | J17: 1 | N17: Total general | O17: 33.872222
A18: 11 | B18: Miércoles | C18: Febrero | D18: 1 | E18: 1 | F18: 1 | G18: 1 | H18: 1 | I18: 1 | J18: 1
A19: 12 | B19: Jueves | C19: Febrero | D19: 1 | E19: 1 | F19: 1 | G19: 1 | H19: 1 | I19: 1 | J19: 1
A20: 13 | B20: Viernes | C20: Febrero | D20: 1 | E20: 1 | F20: 1 | G20: 1 | H20: 1 | I20: 1 | J20: 1
A21: 14 | B21: Sábado | C21: Febrero | F21: 1 | G21: 1 | J21: 1
A22: 15 | B22: Domingo | C22: Febrero
A23: 16 | B23: Lunes | C23: Febrero
A24: 17 | B24: Martes | C24: Febrero | F24: 1 | G24: 1 | J24: 1
A25: 18 | B25: Miércoles | C25: Febrero | D25: 1 | E25: 1 | F25: 1 | G25: 1 | H25: 1 | I25: 1 | J25: 1
A26: 19 | B26: Jueves | C26: Febrero | D26: 1 | E26: 1 | F26: 1 | G26: 1 | H26: 1 | I26: 1 | J26: 1
A27: 20 | B27: Viernes | C27: Febrero | D27: 1 | E27: 1 | F27: 1 | G27: 1 | H27: 1 | I27: 1 | J27: 1
A28: 21 | B28: Sábado | C28: Febrero | E28: 1 | G28: 1 | H28: 1 | J28: 1
A29: 22 | B29: Domingo | C29: Febrero
A30: 23 | B30: Lunes | C30: Febrero | D30: 1 | E30: 1 | F30: 1 | G30: 1 | H30: 1 | I30: 1 | J30: 1
A31: 24 | B31: Martes | C31: Febrero | D31: 1 | E31: 1 | F31: 1 | G31: 1 | H31: 1 | I31: 1 | J31: 1
A32: 25 | B32: Miércoles | C32: Febrero | D32: 1 | E32: 1 | F32: 1 | G32: 1 | H32: 1 | I32: 1 | J32: 1
A33: 26 | B33: Jueves | C33: Febrero | D33: 1 | E33: 1 | F33: 1 | G33: 1 | H33: 1 | I33: 1 | J33: 1
A34: 27 | B34: Viernes | C34: Febrero | D34: 1 | E34: 1 | F34: 1 | G34: 1 | H34: 1 | I34: 1 | J34: 1
A35: 28 | B35: Sábado | C35: Febrero
D37: =SUM(D8:D35) -> 18 | E37: =SUM(E8:E35) -> 19 | F37: =SUM(F8:F35) -> 21 | G37: =SUM(G8:G35) -> 21 | H37: =SUM(H8:H35) -> 19 | I37: =SUM(I8:I35) -> 18 | J37: =SUM(J8:J35) -> 20 | K37: =SUM(K8:K35) -> 0
C39: objetivo | D39: Proporcional por Recurso | K39: %
C40: =+D37 -> 18 | E40: =+E37*0.2 -> 3.8 | F40: =+F37*0.2 -> 4.2 | G40: =+G37*0.2 -> 4.2 | H40: =+H37*0.2 -> 3.8 | I40: =+I37*0.2 -> 3.6 | K40: =+SUM(E40:I40)/C40 -> 1.0888889
B44: Nota; a partir del 10/11/25 ingresan dos roles mas el sr Caceres Oscar (ayudante) y el sr Duarte Antonio (electricista)
D46: 1 | E46: Vacaciones, cubre Tesari Héctor
D47: 1 | E47: Vacaciones, cubre Duarte Antonio

Sheet Digicard
A1: 0000019137-SEAM SERVICIOS ELECTRONICOS S.R.L.
A2: OC 3100000914
A3: Legajo | B3: Empleado | C3: Entrada | D3: Salida | E3: TotalHs | F3: Planta
A4: 1-44279757 | B4: AREVALOS OSCAR | C4: 46029.37 | D4: 46029.379 | E4: 00:13 | F4: Ypora
A5: 1-44279757 | B5: AREVALOS OSCAR | C5: 46035.54 | D5: 46035.68 | E5: 03:22 | F5: Ypora
A6: 1-31472794 | B6: CACERES OSCAR | C6: 46060.785 | D6: 46060.808 | E6: 00:34 | F6: Aserradero Bossetti
A7: 1-31472794 | B7: CACERES OSCAR | C7: 46061.425 | D7: 46061.435 | E7: 00:15 | F7: Aserradero Bossetti
A8: 1-31472794 | B8: CACERES OSCAR | C8: 46066.307 | D8: 46066.633 | E8: 07:50 | F8: Aserradero Bossetti
A9: 1-31472794 | B9: CACERES OSCAR | C9: 46073.506 | D9: 46073.535 | E9: 00:42 | F9: Aserradero Bossetti
A10: 1-22233614 | B10: DAVALOS CESAR | C10: 46057.446 | D10: 46057.46 | E10: 00:20 | F10: Aserradero Bossetti
A11: 1-22233614 | B11: DAVALOS CESAR | C11: 46062.405 | D11: 46062.54 | E11: 03:14 | F11: Aserradero Bossetti
A12: 1-22233614 | B12: DAVALOS CESAR | C12: 46063.377 | D12: 46063.413 | E12: 00:52 | F12: Aserradero Bossetti
A13: 1-22233614 | B13: DAVALOS CESAR | C13: 46066.312 | D13: 46066.634 | E13: 07:43 | F13: Aserradero Bossetti
A14: 1-22233614 | B14: DAVALOS CESAR | C14: 46072.512 | D14: 46072.544 | E14: 00:45 | F14: Aserradero Bossetti
A15: 1-22233614 | B15: DAVALOS CESAR | C15: 46076.371 | D15: 46076.44 | E15: 01:39 | F15: Aserradero Bossetti
... A35: 1-44279757 | B35: AREVALOS OSCAR | C35: 46049.647 | D35: 46049.685 | E35: 00:56 | F35: Ypora
A36: 1-31472794 | B36: CACERES OSCAR | D36: 46055.427 | E36: 00:00 | F36: Piray
A37: 1-31472794 | B37: CACERES OSCAR | C37: 46055.479 | D37: 46055.491 | E37: 00:17 | F37: Piray
A38: 1-31472794 | B38: CACERES OSCAR | D38: 46055.748 | E38: 00:00 | F38: Piray
A39: 1-31472794 | B39: CACERES OSCAR | D39: 46064.406 | E39: 00:00 | F39: Piray
A40: 1-31472794 | B40: CACERES OSCAR | C40: 46064.665 | D40: 46064.672 | E40: 00:11 | F40: Piray
A41: 1-31472794 | B41: CACERES OSCAR | C41: 46064.719 | D41: 46064.726 | E41: 00:10 | F41: Piray
A42: 1-31472794 | B42: CACERES OSCAR | C42: 46071.417 | D42: 46071.422 | E42: 00:08 | F42: Piray
A43: 1-31472794 | B43: CACERES OSCAR | D43: 46071.762 | E43: 00:00 | F43: Piray
A44: 1-26184317 | B44: CENTURION LUCIANO | E44: 00:00 | F44: Piray
A45: 1-26184317 | B45: CENTURION LUCIANO | C45: 46080.382 | D45: 46080.419 | E45: 00:54 | F45: Piray
A46: 1-22233614 | B46: DAVALOS CESAR | C46: 46055.321 | D46: 46055.35 | E46: 00:42 | F46: Piray
A47: 1-22233614 | B47: DAVALOS CESAR | D47: 46055.748 | E47: 00:00 | F47: Piray
A48: 1-22233614 | B48: DAVALOS CESAR | C48: 46064.366 | D48: 46064.392 | E48: 00:38 | F48: Piray
A49: 1-22233614 | B49: DAVALOS CESAR | C49: 46064.719 | D49: 46064.725 | E49: 00:09 | F49: Piray
A50: 1-22233614 | B50: DAVALOS CESAR | D50: 46064.773 | E50: 00:00 | F50: Piray
A51: 1-22233614 | B51: DAVALOS CESAR | D51: 46071.408 | E51: 00:00 | F51: Piray
A52: 1-22233614 | B52: DAVALOS CESAR | D52: 46071.767 | E52: 00:00 | F52: Piray
A53: 1-22233614 | B53: DAVALOS CESAR | D53: 46073.387 | E53: 00:00 | F53: Piray
A54: 1-22233614 | B54: DAVALOS CESAR | D54: 46073.558 | E54: 00:00 | F54: Piray
A55: 1-22233614 | B55: DAVALOS CESAR | D55: 46074.3 | E55: 00:00 | F55: Piray
A56: 1-22233614 | B56: DAVALOS CESAR | D56: 46074.333 | E56: 00:00 | F56: Piray
A57: 1-22233614 | B57: DAVALOS CESAR | D57: 46078.351 | E57: 00:00 | F57: Piray
A58: 1-22233614 | B58: DAVALOS CESAR | C58: 46078.353 | D58: 46078.367 | E58: 00:21 | F58: Piray
A59: 1-22233614 | B59: DAVALOS CESAR | D59: 46078.656 | E59: 00:00 | F59: Piray
A60: 1-20297614 | B60: DUARTE ANTONIO | D60: 46055.427 | E60: 00:00 | F60: Piray
A61: 1-20297614 | B61: DUARTE ANTONIO | C61: 46055.48 | D61: 46055.491 | E61: 00:16 | F61: Piray
A62: 1-20297614 | B62: DUARTE ANTONIO | D62: 46055.748 | E62: 00:00 | F62: Piray
A63: 1-20297614 | B63: DUARTE ANTONIO | D63: 46064.406 | E63: 00:00 | F63: Piray
A64: 1-20297614 | B64: DUARTE ANTONIO | C64: 46064.721 | D64: 46064.725 | E64: 00:06 | F64: Piray
A65: 1-37591299 | B65: PEREYRA BRUNO | C65: 46055.335 | D65: 46055.407 | E65: 01:44 | F65: Piray
A66: 1-37591299 | B66: PEREYRA BRUNO | C66: 46055.421 | D66: 46055.427 | E66: 00:09 | F66: Piray
A67: 1-37591299 | B67: PEREYRA BRUNO | C67: 46055.583 | D67: 46055.649 | E67: 01:35 | F67: Piray
A68: 1-37591299 | B68: PEREYRA BRUNO | D68: 46055.749 | E68: 00:00 | F68: Piray
A69: 1-37591299 | B69: PEREYRA BRUNO | C69: 46057.328 | D69: 46057.708 | E69: 08:00 | F69: Piray
A70: 1-37591299 | B70: PEREYRA BRUNO | C70: 46059.24 | D70: 46059.576 | E70: 08:00 | F70: Piray
A71: 1-37591299 | B71: PEREYRA BRUNO | C71: 46062.326 | D71: 46062.699 | E71: 08:00 | F71: Piray
A72: 1-37591299 | B72: PEREYRA BRUNO | C72: 46063.332 | D72: 46063.581 | E72: 05:58 | F72: Piray
A73: 1-37591299 | B73: PEREYRA BRUNO | C73: 46063.588 | D73: 46063.699 | E73: 02:40 | F73: Piray
A74: 1-37591299 | B74: PEREYRA BRUNO | C74: 46064.33 | D74: 46064.363 | E74: 00:47 | F74: Piray
A75: 1-37591299 | B75: PEREYRA BRUNO | C75: 46064.367 | D75: 46064.412 | E75: 01:06 | F75: Piray
A76: 1-37591299 | B76: PEREYRA BRUNO | C76: 46064.658 | D76: 46064.702 | E76: 01:04 | F76: Piray
A77: 1-37591299 | B77: PEREYRA BRUNO | C77: 46071.335 | D77: 46071.354 | E77: 00:28 | F77: Piray
A78: 1-37591299 | B78: PEREYRA BRUNO | D78: 46071.762 | E78: 00:00 | F78: Piray
A79: 1-37591299 | B79: PEREYRA BRUNO | C79: 46076.327 | D79: 46076.701 | E79: 08:00 | F79: Piray
A80: 1-37591299 | B80: PEREYRA BRUNO | C80: 46078.331 | D80: 46078.701 | E80: 08:00 | F80: Piray
A81: 1-37591299 | B81: PEREYRA BRUNO | C81: 46080.249 | D81: 46080.577 | E81: 07:52 | F81: Piray
A82: 1-34453345 | B82: TESARI HECTOR | D82: 46055.427 | E82: 00:00 | F82: Piray
A83: 1-34453345 | B83: TESARI HECTOR | D83: 46055.748 | E83: 00:00 | F83: Piray
A84: 1-34453345 | B84: TESARI HECTOR | D84: 46064.406 | E84: 00:00 | F84: Piray
A85: 1-34453345 | B85: TESARI HECTOR | C85: 46064.721 | D85: 46064.725 | E85: 00:06 | F85: Piray
A86: 1-34453345 | B86: TESARI HECTOR | C86: 46071.415 | D86: 46071.422 | E86: 00:11 | F86: Piray
A87: 1-34453345 | B87: TESARI HECTOR | D87: 46071.761 | E87: 00:00 | F87: Piray
A88: 1-34453345 | B88: TESARI HECTOR | D88: 46078.358 | E88: 00:00 | F88: Piray
A89: 1-34453345 | B89: TESARI HECTOR | D89: 46078.67 | E89: 00:00 | F89: Piray
A90: 1-44279757 | B90: AREVALOS OSCAR | C90: 46051.567 | D90: 46051.669 | E90: 02:27 | F90: Ypora
A91: 1-44279757 | B91: AREVALOS OSCAR | C91: 46052.497 | D91: 46052.56 | E91: 01:32 | F91: Ypora
A92: 1-44279757 | B92: AREVALOS OSCAR | C92: 46071.31 | D92: 46071.349 | E92: 00:56 | F92: Celulosa
A93: 1-44279757 | B93: AREVALOS OSCAR | C93: 46071.415 | D93: 46071.422 | E93: 00:11 | F93: Piray
A94: 1-31472794 | B94: CACERES OSCAR | C94: 46063.549 | D94: 46063.633 | E94: 02:00 | F94: Vivero Bossetti
A95: 1-31472794 | B95: CACERES OSCAR | C95: 46073.372 | D95: 46073.501 | E95: 03:06 | F95: Vivero Bossetti
A96: 1-31472794 | B96: CACERES OSCAR | C96: 46073.54 | D96: 46073.57 | E96: 00:44 | F96: Vivero Bossetti
A97: 1-20297614 | B97: DUARTE ANTONIO | C97: 46063.548 | D97: 46063.633 | E97: 02:02 | F97: Vivero Bossetti
A98: 1-37591299 | B98: PEREYRA BRUNO | C98: 46072.399 | D98: 46072.508 | E98: 02:37 | F98: Vivero Bossetti
A99: 1-37591299 | B99: PEREYRA BRUNO | C99: 46072.548 | D99: 46072.721 | E99: 04:09 | F99: Vivero Bossetti
A100: 1-37591299 | B100: PEREYRA BRUNO | C100: 46073.325 | D100: 46073.501 | E100: 04:14 | F100: Vivero Bossetti
A101: 1-37591299 | B101: PEREYRA BRUNO | C101: 46073.54 | D101: 46073.592 | E101: 01:16 | F101: Vivero Bossetti
... A105: 1-34453345 | B105: TESARI HECTOR | C105: 46073.54 | D105: 46073.644 | E105: 02:31 | F105: Vivero Bossetti
A106: 1-34453345 | B106: TESARI HECTOR | D106: 46076.447 | E106: 00:00 | F106: Vivero Bossetti
A107: 1-34453345 | B107: TESARI HECTOR | C107: 46080.544 | D107: 46080.567 | E107: 00:33 | F107: Vivero Bossetti
A108: 1-44279757 | B108: AREVALOS OSCAR | C108: 46072.313 | D108: 46072.361 | E108: 01:09 | F108: Celulosa
A109: 1-44279757 | B109: AREVALOS OSCAR | C109: 46072.512 | D109: 46072.544 | E109: 00:45 | F109: Aserradero Bossetti
A110: 1-44279757 | B110: AREVALOS OSCAR | C110: 46072.549 | D110: 46072.721 | E110: 04:07 | F110: Vivero Bossetti
A111: 1-44279757 | B111: AREVALOS OSCAR | C111: 46073.255 | D111: 46073.279 | E111: 00:35 | F111: Celulosa
A112: 1-44279757 | B112: AREVALOS OSCAR | C112: 46073.299 | D112: 46073.501 | E112: 04:52 | F112: Vivero Bossetti
A113: 1-44279757 | B113: AREVALOS OSCAR | C113: 46073.506 | D113: 46073.535 | E113: 00:42 | F113: Aserradero Bossetti
A114: 1-44279757 | B114: AREVALOS OSCAR | C114: 46073.54 | D114: 46073.644 | E114: 02:31 | F114: Vivero Bossetti
A115: 1-44279757 | B115: AREVALOS OSCAR | C115: 46074.292 | D115: 46074.709 | E115: 08:00 | F115: Celulosa
A116: 1-44279757 | B116: AREVALOS OSCAR | C116: 46076.307 | D116: 46076.399 | E116: 02:13 | F116: Celulosa
A117: 1-44279757 | B117: AREVALOS OSCAR | C117: 46076.437 | D117: 46076.574 | E117: 03:18 | F117: Celulosa
A118: 1-44279757 | B118: AREVALOS OSCAR | C118: 46076.681 | D118: 46076.738 | E118: 01:22 | F118: Celulosa
... A123: 1-44279757 | B123: AREVALOS OSCAR | C123: 46079.366 | D123: 46079.679 | E123: 07:31 | F123: Ypora
A124: 1-31472794 | B124: CACERES OSCAR | D124: 46055.308 | E124: 00:00 | F124: Celulosa
A125: 1-31472794 | B125: CACERES OSCAR | C125: 46055.365 | D125: 46055.385 | E125: 00:28 | F125: Celulosa
A126: 1-31472794 | B126: CACERES OSCAR | C126: 46056.311 | D126: 46056.387 | E126: 01:50 | F126: Celulosa
...

Sheet PARA AVISOS
A1: LOCALIDAD | B1: SEDE | C1: AREA | D1: CECO | E1: SECTOR/USUARIO | F1: DESCRIPCIÓN | G1: COD. EQUIPO | H1: FREC | I1: 43556 | J1: 43586 | K1: 43617 | L1: 43647 | M1: 43678 | N1: 43709 | O1: 43739 | P1: 43770 | Q1: 43800 | R1: 43831 | S1: 43862 | T1: 43891
A2: 10854101 | B2: PLANTA CELULOSA | C2: ADMINISTRACIÓN | D2: APOBA1-871 | E2: ESPE-ESP-CEL-ADMIN1-OFCOSTO1 | F2: TESORERIA-COSTOS | G2: CEL-AD1-17 | H2: 3 | O2: 3
A3: 10854106 | B3: PLANTA CELULOSA | C3: ADMINISTRACIÓN | D3: APOBA1-871 | E3: ESPE-ESP-CEL-ADMIN1-OFSECGTE | F3: OF. SECRETARIA GTE. | G3: CEL-AD1-19 | H3: 3 | O3: 3
A4: 10854123 | B4: PLANTA CELULOSA | C4: ADMINISTRACIÓN | D4: APOBA1-871 | E4: ESPE-ESP-CEL-ADMIN1-OFRRHH01 | F4: OF. RRHH CELULOSA | G4: CEL-AD1-2 | H4: 3 | O4: 3
A5: 10854186 | B5: PLANTA CELULOSA | C5: ADMINISTRACIÓN | D5: APOBA1-871 | E5: ESPE-ESP-CEL-ADMIN1-OFSGTEAD | F5: OF.SUBG.ADMINISTRACION. | G5: CEL-AD1-20 | H5: 3 | O5: 3
A6: 10854188 | B6: PLANTA CELULOSA | C6: ADMINISTRACIÓN | D6: APOBA1-871 | E6: ESPE-ESP-CEL-ADMIN1-OFSGTEMT | F6: OF. SUBGERENTE DE MTTO. | G6: CEL-AD1-21 | H6: 3 | O6: 3
A7: 10854202 | B7: PLANTA CELULOSA | C7: ADMINISTRACIÓN | D7: APOBA1-871 | E7: ESPE-ESP-CEL-ADMIN1-OFSGTEPR | F7: OF. SUBGERENTE DE PRODUCCIÓN. | G7: CEL-AD1-22 | H7: 3 | O7: 3
A8: 10854203 | B8: PLANTA CELULOSA | C8: ADMINISTRACIÓN | D8: APOBA1-871 | E8: ESPE-ESP-CEL-ADMIN1-OFJEFERH | F8: OF. JEFE DE RRHH. | G8: CEL-AD1-4 | H8: 3 | O8: 3
A9: 10854204 | B9: PLANTA CELULOSA | C9: ADMINISTRACIÓN | D9: APOBA1-871 | E9: ESPE-ESP-CEL-ADMIN1-OFAUINT1 | F9: OF. AUDITORIA INTERNA 1. | G9: CEL-AD1-5 | H9: 3 | O9: 3
A10: 10854205 | B10: PLANTA CELULOSA | C10: ADMINISTRACIÓN | D10: APOBA1-871 | E10: ESPE-ESP-CEL-ADMIN1-OFCONFO1 | F10: OF. CONTROL FORESTAL 1. | G10: CEL-AD1-8 | H10: 3 | O10: 3
A11: 10854206 | B11: PLANTA CELULOSA | C11: ADMINISTRACIÓN | D11: APOBA1-871 | E11: ESPE-ESP-CEL-ADMIN1-OFMASSO1 | F11: OF. MASSO 1. | G11: CEL-AD1-9 | H11: 3 | O11: 3
A12: 10854207 | B12: PLANTA CELULOSA | C12: ADMINISTRACIÓN 2 | D12: APOBA1-871 | E12: ESPE-ESP-CEL-ADMIN2-OFICINA1 | F12: OF. SUPERVISOR SSGG. | G12: CEL-AD2-1 | H12: 3 | O12: 3
A13: 10854208 | B13: PLANTA CELULOSA | C13: ADMINISTRACIÓN 2 | D13: APOBA1-871 | E13: ESPE-ESP-CEL-ADMIN2-OFCOYOB2 | F13: OF. CONTRATO Y OBRA 1 | G13: CEL-AD2-10 | H13: 3 | O13: 3
... A16: 10854232 | B16: PLANTA CELULOSA | C16: ADMINISTRACIÓN 2 | D16: APOBA1-871 | E16: ESPE-ESP-CEL-ADMIN2-OFCENPAG | F16: OF. CUENTAS A PAGAR | G16: CEL-AD2-2 | H16: 3 | O16: 3
A17: ESPERANZA | B17: PLANTA CELULOSA | C17: ADMINISTRACIÓN 2 | D17: APOBA1-871 | E17: Of. SSGG (Auxiliares 1) | G17: CEL-AD2-3 | H17: 3 | O17: 3
A18: ESPERANZA | B18: PLANTA CELULOSA | C18: ADMINISTRACIÓN 2 | D18: APOBA1-871 | E18: Of. SSGG (Movilidad) | G18: CEL-AD2-4 | H18: 3 | O18: 3
A19: ESPERANZA | B19: PLANTA CELULOSA | C19: ADMINISTRACIÓN 2 | D19: APOBA1-871 | E19: Of. Archivo Técnico | G19: CEL-AD2-5 | H19: 3 | O19: 3
A20: ESPERANZA | B20: PLANTA CELULOSA | C20: ADMINISTRACIÓN 2 | D20: APOBA1-871 | E20: Of. Cuentas a Pagar (Auxiliares) 1 | G20: CEL-AD2-8 | H20: 3 | P20: 3
A21: ESPERANZA | B21: PLANTA CELULOSA | C21: ADMINISTRACIÓN 2 | D21: APOBA1-871 | E21: Of. Cuentas a Pagar (Auxiliares) 2 | G21: CEL-AD2-9 | H21: 3 | P21: 3
A22: ESPERANZA | B22: PLANTA CELULOSA | C22: BALANZA | D22: APOBA1-871 | E22: Balanza A1 - B2 | G22: CEL-BAL-2 | H22: 2
A23: ESPERANZA | B23: PLANTA CELULOSA | C23: COMEDOR | D23: APOBA1-871 | E23: ESPE-ESP-CEL-COMEDO-MTTOAA01 | F23: MTTO AA 01 | G23: CEL-COM-1 | H23: 1 | I23: 1 | J23: 1 | K23: 1 | L23: 1 | M23: 1
A24: ESPERANZA | B24: PLANTA CELULOSA | C24: COMEDOR | D24: APOBA1-871 | E24: ESPE-ESP-CEL-COMEDO-MTTOAA02 | F24: MTTO AA 02 | G24: CEL-COM-2 | H24: 1 | I24: 1 | J24: 1 | K24: 1 | L24: 1 | M24: 1
A25: ESPERANZA | B25: PLANTA CELULOSA | C25: COMEDOR | D25: APOBA1-871 | E25: ESPE-ESP-CEL-COMEDO-MTTOAA03 | F25: MTTO AA 03 | G25: CEL-COM-3 | H25: 1 | I25: 1 | J25: 1 | K25: 1 | L25: 1 | M25: 1
A26: ESPERANZA | B26: PLANTA CELULOSA | C26: COMEDOR | D26: APOBA1-871 | E26: ESPE-ESP-CEL-COMEDO-MTTOAA04 | F26: MTTO AA 04 | G26: CEL-COM-4 | H26: 1 | I26: 1 | J26: 1 | K26: 1 | L26: 1 | M26: 1
A27: ESPERANZA | B27: PLANTA CELULOSA | C27: COMEDOR | D27: APOBA1-871 | E27: ESPE-ESP-CEL-COMEDO-MTTOAA05 | F27: MTTO AA 05 | G27: CEL-COM-5 | H27: 1 | I27: 1 | J27: 1 | K27: 1 | L27: 1 | M27: 1
A28: ESPERANZA | B28: PLANTA CELULOSA | C28: COMEDOR | D28: APOBA1-871 | E28: ESPE-ESP-CEL-COMEDO-MTTOAA06 | F28: MTTO AA 06 | G28: CEL-COM-6 | H28: 1 | K28: 1 | L28: 1 | M28: 1
A29: ESPERANZA | B29: PLANTA CELULOSA | C29: CONTROL TÉCNICO | D29: APOBA1-871 | E29: ESPE-ESP-CEL-LABORA-OFIC0019 | F29: OFICINA SUPERVISOR LAB. AGUAS/EFLUENTES | G29: CEL-COTE-4 | H29: 3 | P29: 3
A30: ESPERANZA | B30: PLANTA CELULOSA | C30: TRANSPORTE FORESTAL | D30: APOBA1-871 | E30: ESPE-ESP-CEL-FOREST-OFRECLOG | F30: Of. Auxiliares | G30: CEL-FOR-1 | H30: 2 | N30: 2
A31: ESPERANZA | B31: PLANTA CELULOSA | C31: TRANSPORTE FORESTAL | D31: APOBA1-871 | E31: ESPE-ESP-CEL-FOREST-OFJETRAN | F31: Of. Jefe de Carga y Transporte | G31: CEL-FOR-2 | H31: 2 | N31: 2
A32: ESPERANZA | B32: PLANTA CELULOSA | C32: TRANSPORTE FORESTAL | D32: APOBA1-871 | E32: ESPE-ESP-CEL-FOREST-SALREU01 | F32: Sala de reuniones (al lado de Recepción) | G32: CEL-FOR-3 | H32: 2 | N32: 2
A33: ESPERANZA | B33: PLANTA CELULOSA | C33: LOGISTICA | D33: APOBA1-871 | E33: Of. Trafico/Logistica 1 | G33: CEL-LOG-1 | H33: 3 | P33: 3
A34: ESPERANZA | B34: PLANTA CELULOSA | C34: LOGISTICA | D34: APOBA1-871 | E34: Of. Trafico/Logistica 1 | G34: CEL-LOG-2 | H34: 3 | P34: 3
A35: ESPERANZA | B35: PLANTA CELULOSA | C35: LOGISTICA | D35: APOBA1-871 | E35: Of. Jefe Logistica. | G35: CEL-LOG-3 | H35: 3 | P35: 3
A36: ESPERANZA | B36: PLANTA CELULOSA | C36: LOGISTICA | D36: APOBA1-871 | E36: Of. Planificacion Trafico/Logistica. | G36: CEL-LOG-4 | H36: 3 | P36: 3
A37: ESPERANZA | B37: PLANTA CELULOSA | C37: LOGISTICA | D37: APOBA1-871 | E37: Sala de Reunion | G37: CEL-LOG-5 | H37: 3 | P37: 3
A38: ESPERANZA | B38: PLANTA CELULOSA | C38: PORTERÍA | D38: APOBA1-871 | E38: Comedor | G38: CEL-POR-1 | H38: 3 | P38: 3
A39: ESPERANZA | B39: PLANTA CELULOSA | C39: PORTERÍA | D39: APOBA1-871 | E39: Of. Jefe de Equipo. | G39: CEL-POR-5 | H39: 3 | P39: 3
A40: ESPERANZA | B40: PLANTA CELULOSA | C40: SISTEMAS | D40: APOBA1-871 | E40: ESPE-ESP-CEL-SISTEM-OFICINA1 | F40: CENTRO DE COMPUTOS 1 | G40: CEL-SIST-1 | H40: 1 | I40: 1 | J40: 1 | K40: 1 | L40: 1 | M40: 1
A41: ESPERANZA | B41: PLANTA CELULOSA | C41: SISTEMAS | D41: APOBA1-871 | E41: ESPE-ESP-CEL-SISTEM-OFICINA2 | F41: CENTRO DE COMPUTOS 2 | G41: CEL-SIST-2 | H41: 1 | I41: 1 | J41: 1 | K41: 1 | L41: 1 | M41: 1
A42: ESPERANZA | B42: PLANTA CELULOSA | C42: SISTEMAS | D42: APOBA1-871 | E42: ESPE-ESP-CEL-SISTEM-OFICINA3 | F42: CENTRAL TELEFÓNICA | G42: CEL-SIST-3 | H42: 1 | I42: 1 | J42: 1 | K42: 1 | L42: 1 | M42: 1
A43: ESPERANZA | B43: PLANTA CELULOSA | C43: SISTEMAS | D43: APOBA1-871 | E43: Oficina Jefe de Informática | G43: CEL-SIST-4 | H43: 3 | P43: 3
A44: ESPERANZA | B44: PLANTA CELULOSA | C44: SISTEMAS | D44: APOBA1-871 | E44: Oficina Analistas Informática | G44: CEL-SIST-5 | H44: 3 | P44: 3
A45: ESPERANZA | B45: PTO. BOSSETTI | C45: BALANZA | D45: APOBA1-872 | E45: Of. Operadores | G45: CLO-BAL-1 | H45: 3 | P45: 3
A46: ESPERANZA | B46: PTO. BOSSETTI | C46: BALANZA | D46: APOBA1-872 | E46: Of. Operadores | G46: CLO-BAL-2 | H46: 3 | P46: 3
A47: ESPERANZA | B47: PTO. BOSSETTI | C47: CHALET | D47: APOBA1-872 | E47: Habitacion 1 | G47: CLO-CHA-1 | H47: 3 | P47: 3
A48: ESPERANZA | B48: PTO. BOSSETTI | C48: CHALET | D48: APOBA1-872 | E48: Habitacion 2 | G48: CLO-CHA-2 | H48: 3 | P48: 3
A49: ESPERANZA | B49: PTO. BOSSETTI | C49: CHALET | D49: APOBA1-872 | E49: Habitacion 3 | G49: CLO-CHA-3 | H49: 3 | P49: 3
A50: ESPERANZA | B50: PTO. BOSSETTI | C50: CHALET | D50: APOBA1-872 | E50: Habitacion 4 | G50: CLO-CHA-4 | H50: 3 | P50: 3
A51: ESPERANZA | B51: PTO. BOSSETTI | C51: CHALET | D51: APOBA1-872 | E51: Habitacion 5 | G51: CLO-CHA-5 | H51: 3 | Q51: 3
A52: ESPERANZA | B52: PTO. BOSSETTI | C52: CHALET | D52: APOBA1-872 | E52: Habitacion 6 | G52: CLO-CHA-6 | H52: 3 | Q52: 3
A53: ESPERANZA | B53: PTO. BOSSETTI | C53: CHALET | D53: APOBA1-872 | E53: Living Comedor | G53: CLO-CHA-7 | H53: 3 | Q53: 3
A54: ESPERANZA | B54: PTO. BOSSETTI | C54: CHALET | D54: APOBA1-872 | E54: Casa Cuidador. | G54: CLO-CHA-8 | H54: 3 | Q54: 3
A55: ESPERANZA | B55: PTO. BOSSETTI | C55: COMEDOR | D55: APOBA1-872 | E55: Salón Comedor | G55: CLO-COM-1 | H55: 3 | Q55: 3
A56: ESPERANZA | B56: PTO. BOSSETTI | C56: COMEDOR | D56: APOBA1-872 | E56: Salón Comedor | G56: CLO-COM-2 | H56: 3 | Q56: 3
A57: ESPERANZA | B57: PTO. BOSSETTI | C57: ENFERMERÍA | D57: APOBA1-872 | E57: Consultorio | G57: CLO-ENF-1 | H57: 3 | Q57: 3
A58: ESPERANZA | B58: PTO. BOSSETTI | C58: EXPEDICIÓN | D58: APOBA1-872 | E58: Of. Planificador (Martinez) | G58: CLO-EXP-1 | H58: 3 | Q58: 3
A59: ESPERANZA | B59: PTO. BOSSETTI | C59: EXPEDICIÓN | D59: APOBA1-872 | E59: Of. Planificador (al lado Martinez) | G59: CLO-EXP-2 | H59: 3 | Q59: 3
A60: ESPERANZA | B60: PTO. BOSSETTI | C60: SISTEMA Y COMUNICACIÓN | D60: APOBA1-872 | E60: BOSS-BOS-ADM-ADMIN1-CASTELEF | F60: CENTRAL TELEFÓNICA | G60: CLO-SYC-1 | H60: 1 | I60: 1 | J60: 1 | K60: 1 | L60: 1 | M60: 1
A61: ESPERANZA | B61: PTO. BOSSETTI | C61: SISTEMA Y COMUNICACIÓN | D61: APOBA1-872 | E61: BOSS-BOS-ADM-ADMIN1-OFSIYCO1 | F61: OFICINA DE SISTEMA Y COMUNICACIONES | G61: CLO-SYC-2 | H61: 1 | I61: 1 | J61: 1 | K61: 1 | L61: 1 | M61: 1
A62: ESPERANZA | B62: PTO. BOSSETTI | C62: SISTEMA Y COMUNICACIÓN | D62: APOBA1-872 | E62: BOSS-BOS-ADM-ADMIN1-DISTRED1 | F62: DEISTRIBUCION DE RED 1 | G62: CLO-SYC-3 | H62: 1 | I62: 1 | J62: 1 | K62: 1 | L62: 1 | M62: 1
A63: ESPERANZA | B63: PTO. BOSSETTI | C63: SISTEMA Y COMUNICACIÓN | D63: APOBA1-872 | E63: BOSS-BOS-ADM-ADMIN1-SALACOM1 | F63: SALA DE COMPUTOS 1 | G63: CLO-SYC-4 | H63: 1 | I63: 1 | J63: 1 | K63: 1 | L63: 1 | M63: 1
A64: ESPERANZA | B64: PTO. BOSSETTI | C64: SISTEMA Y COMUNICACIÓN | D64: APOBA1-872 | E64: BOSS-BOS-ADM-ADMIN1-SALACOM2 | F64: SALA DE COMPUTOS 2 | G64: CLO-SYC-5 | H64: 1 | I64: 1 | J64: 1 | K64: 1 | L64: 1 | M64: 1
A65: PTO. PIRAY | B65: MDF | C65: ADMINISTRACION 1 | D65: APOBA1-874 | E65: PIRA-PIR-MDF-ADMIN1-OFJEFERH | F65: OF. DE JEFE RRHH (Grande Anibal) | G65: MDF-AD1-1 | H65: 1 | J65: 1 | K65: 1 | L65: 1 | M65: 1
A66: PTO. PIRAY | B66: MDF | C66: ADMINISTRACION 1 | D66: APOBA1-874 | E66: PIRA-PIR-MDF-ADMIN1-OFGERGEN | F66: OF. SUBGTE. PRODUCCIÓN (Pablo Riat) | G66: MDF-AD1-10 | H66: 1 | J66: 1 | K66: 1 | L66: 1 | M66: 1
A67: PTO. PIRAY | B67: MDF | C67: ADMINISTRACION 1 | D67: APOBA1-874 | E67: PIRA-PIR-MDF-ADMIN1-OFGEROPE | F67: OF. GTE DE OPERACIONES (Ruben Freiberger) | G67: MDF-AD1-11 | H67: 1 | J67: 1 | K67: 1 | L67: 1 | M67: 1
A68: PTO. PIRAY | B68: MDF | C68: ADMINISTRACION 1 | D68: APOBA1-874 | E68: PIRA-PIR-MDF-ADMIN1-GTERRHH1 | F68: OF. GERENTE RRHH (Meyer Alejandro) | G68: MDF-AD1-12 | H68: 1 | J68: 1 | K68: 1 | L68: 1 | M68: 1
A69: PTO. PIRAY | B69: MDF | C69: ADMINISTRACION 1 | D69: APOBA1-874 | E69: PIRA-PIR-MDF-ADMIN1-OFSUBGAD | F69: OF. SUBGTE ADMINISTRATIVO RN (Ascat S.) | G69: MDF-AD1-13 | H69: 1 | I69: 1 | J69: 1 | K69: 1 | L69: 1 | M69: 1
A70: PTO. PIRAY | B70: MDF | C70: ADMINISTRACION 1 | D70: APOBA1-874 | E70: PIRA-PIR-MDF-ADMIN1-RECEPCIO | F70: RECEPCION MDF | G70: MDF-AD1-14 | H70: 1 | J70: 1 | K70: 1 | L70: 1 | M70: 1
A71: PTO. PIRAY | B71: MDF | C71: ADMINISTRACION 1 | D71: APOBA1-874 | E71: PIRA-PIR-MDF-ADMIN1-OFJEFTUR | F71: OF. JEFE DE TURNO | G71: MDF-AD1-15 | H71: 1 | J71: 1 | K71: 1 | L71: 1 | M71: 1
A72: PTO. PIRAY | B72: MDF | C72: ADMINISTRACION 1 | D72: APOBA1-874 | E72: PIRA-PIR-MDF-ADMIN1-OFMASSO2 | F72: OF. Jefe MASSO (VERONICA CIAPPA) | G72: MDF-AD1-16 | H72: 1 | J72: 1 | K72: 1 | L72: 1 | M72: 1
A73: PTO. PIRAY | B73: MDF | C73: ADMINISTRACION 1 | D73: APOBA1-874 | E73: PIRA-PIR-MDF-ADMIN1-OFMASSO1 | F73: OF. MASSO 1 (Erberich) | G73: MDF-AD1-17 | H73: 1 | J73: 1 | K73: 1 | L73: 1 | M73: 1
A74: PTO. PIRAY | B74: MDF | C74: ADMINISTRACION 1 | D74: APOBA1-874 | E74: PIRA-PIR-MDF-ADMIN1-OFMASSO3 | F74: OF. MASSO 2 (Encina Liliana) | G74: MDF-AD1-18 | H74: 1 | J74: 1 | K74: 1 | L74: 1 | M74: 1
A75: PTO. PIRAY | B75: MDF | C75: ADMINISTRACION 1 | D75: APOBA1-874 | E75: PIRA-PIR-MDF-ADMIN1-SALREU02 | F75: SALA DE CAPACITACIONES | G75: MDF-AD1-19 | H75: 1 | J75: 1 | K75: 1 | L75: 1 | M75: 1
A76: PTO. PIRAY | B76: MDF | C76: ADMINISTRACION 1 | D76: APOBA1-874 | E76: PIRA-PIR-MDF-ADMIN1-OFSECGTE | F76: OF. SECRTARIA DEL GERENTE (Anyela Soto) | G76: MDF-AD1-2 | H76: 1 | J76: 1 | K76: 1 | L76: 1 | M76: 1
A77: PTO. PIRAY | B77: MDF | C77: ADMINISTRACION 1 | D77: APOBA1-874 | E77: PIRA-PIR-MDF-ADMIN1-SALREU01 | F77: SALA DE REUNIONES 01 (Recep. Gerencia) | G77: MDF-AD1-20 | H77: 1 | J77: 1 | K77: 1 | L77: 1 | M77: 1
A78: PTO. PIRAY | B78: MDF | C78: ADMINISTRACION 1 | D78: APOBA1-874 | E78: PIRA-PIR-MDF-ADMIN1-OFAUXRH1 | F78: OF. AUXILIARES RRHH (Morel / Ruiz Diaz) | G78: MDF-AD1-3 | H78: 1 | J78: 1 | K78: 1 | L78: 1 | M78: 1
A79: PTO. PIRAY | B79: MDF | C79: ADMINISTRACION 1 | D79: APOBA1-874 | E79: PIRA-PIR-MDF-ADMIN1-OFTESORE | F79: OF. TESORERIA /COSTO. | G79: MDF-AD1-4 | H79: 1 | J79: 1 | K79: 1 | L79: 1 | M79: 1
A80: PTO. PIRAY | B80: MDF | C80: ADMINISTRACION 1 | D80: APOBA1-874 | E80: PIRA-PIR-MDF-ADMIN1-OFCOSTO1 | F80: OF. JEFE DE COSTOS | G80: MDF-AD1-5 | H80: 1 | J80: 1 | K80: 1 | L80: 1 | M80: 1
A81: PTO. PIRAY | B81: MDF | C81: ADMINISTRACION 1 | D81: APOBA1-874 | E81: PIRA-PIR-MDF-ADMIN1-OFEXEOPE | F81: JEFE DE PRODUCCIÓN (STEVENS) | G81: MDF-AD1-6 | H81: 1 | J81: 1 | K81: 1 | L81: 1 | M81: 1
A82: PTO. PIRAY | B82: MDF | C82: ADMINISTRACION 1 | D82: APOBA1-874 | E82: PIRA-PIR-MDF-ADMIN1-OFPLANIF | F82: OF. DE PLANIFICACION (Orue) | G82: MDF-AD1-7 | H82: 1 | J82: 1 | K82: 1 | L82: 1 | M82: 1
A83: PTO. PIRAY | B83: MDF | C83: ADMINISTRACION 1 | D83: APOBA1-874 | E83: PIRA-PIR-MDF-ADMIN1-OFJEFPRO | F83: ING. EN PROCESO (GOLDNER I) | G83: MDF-AD1-8 | H83: 1 | I83: 1 | J83: 1 | K83: 1 | L83: 1 | M83: 1
A84: PTO. PIRAY | B84: MDF | C84: ADMINISTRACION 1 | D84: APOBA1-874 | E84: PIRA-PIR-MDF-ADMIN1-OFSUBGMA | F84: OF. SUBGTE MANTENIMIENTO (Jose Luis Nuc) | G84: MDF-AD1-9 | H84: 1 | J84: 1 | K84: 1 | L84: 1 | M84: 1
A85: PTO. PIRAY | B85: MDF | C85: ADMINISTRACIÓN 2 | D85: APOBA1-874 | E85: Of. Auditoria Interna | G85: MDF-AD2-1 | H85: 3 | Q85: 3
A86: PTO. PIRAY | B86: MDF | C86: ADMINISTRACIÓN 2 | D86: APOBA1-874 | E86: Of. Subgte Sis y Co. | G86: MDF-AD2-13 | H86: 3 | Q86: 3
A87: PTO. PIRAY | B87: MDF | C87: ADMINISTRACIÓN 2 | D87: APOBA1-874 | E87: PIRA-PIR-MDF-ADMIN2-MTTOAA15 | F87: DEPOSITO INFORMATICA (FRENTE OF. DESA) | G87: MDF-AD2-15 | H87: 2 | N87: 2
A88: PTO. PIRAY | B88: MDF | C88: ADMINISTRACIÓN 2 | D88: APOBA1-874 | E88: PIRA-PIR-MDF-ADMIN2-OFSIYCO7 | F88: OF. DE SISyCOM (Stehr, Eduardo Arturo) | G88: MDF-AD2-16 | H88: 2
A89: PTO. PIRAY | B89: MDF | C89: ADMINISTRACIÓN 2 | D89: APOBA1-874 | E89: PIRA-PIR-MDF-ADMIN2-OFSSGG02 | F89: MTTO DE AA - MOVILIDAD 1 (COORDINADOR) | G89: MDF-AD2-17 | H89: 2 | N89: 2
A90: PTO. PIRAY | B90: MDF | C90: ADMINISTRACIÓN 2 | D90: APOBA1-874 | E90: PIRA-PIR-MDF-ADMIN2-OFSSGG03 | F90: MTTO DE AA - SSGG (ARQUITECTA) | G90: MDF-AD2-18 | H90: 2 | N90: 2
A91: PTO. PIRAY | B91: MDF | C91: ADMINISTRACIÓN 2 | D91: APOBA1-874 | E91: PIRA-PIR-MDF-ADMIN2-OFSSGG04 | F91: MTTO DE AA - SSGG MM (ALVARENGA) | G91: MDF-AD2-19 | H91: 2 | N91: 2
A92: PTO. PIRAY | B92: MDF | C92: ADMINISTRACIÓN 2 | D92: APOBA1-874 | E92: PIRA-PIR-MDF-ADMIN2-OFCOCO01 | F92: OF. CONTROL DE CONTRATISTA (Zena MF.) | G92: MDF-AD2-2 | H92: 3 | Q92: 3
A93: PTO. PIRAY | B93: MDF | C93: ADMINISTRACIÓN 2 | D93: APOBA1-874 | E93: PIRA-PIR-MDF-ADMIN2-OFCONYOB | F93: OF.CONTRATO Y OBRA (Puente Fernando) | G93: MDF-AD2-20 | H93: 2 | N93: 2
A94: PTO. PIRAY | B94: MDF | C94: ADMINISTRACIÓN 2 | D94: APOBA1-874 | E94: PIRA-PIR-MDF-ADMIN2-OFVACIA2 | F94: FORESTAL (SEGURIDAD FORESTAL) | G94: MDF-AD2-21 | H94: 3 | Q94: 3
A95: PTO. PIRAY | B95: MDF | C95: ADMINISTRACIÓN 2 | D95: APOBA1-874 | E95: PIRA-PIR-MDF-ADMIN2-OFJEFCCO | F95: OF. JEFE CONTROL DE CONTRATISTA (Ruiz V) | G95: MDF-AD2-22 | H95: 2
A96: PTO. PIRAY | B96: MDF | C96: ADMINISTRACIÓN 2 | D96: APOBA1-874 | E96: PIRA-PIR-MDF-ADMIN2-OFJEFSG2 | F96: OF. JEFE SERVICIOS GENERALES | G96: MDF-AD2-3 | H96: 2
A97: PTO. PIRAY | B97: MDF | C97: ADMINISTRACIÓN 2 | D97: APOBA1-874 | E97: PIRA-PIR-MDF-ADMIN2-OFFORES1 | F97: OF. FORESTAL (Sequeira A.) | G97: MDF-AD2-5 | H97: 3 | Q97: 3
A98: PTO. PIRAY | B98: MDF | C98: ADMINISTRACIÓN 2 | D98: APOBA1-874 | E98: PIRA-PIR-MDF-ADMIN2-OFFORES2 | F98: OF. FORESTAL (Cristaldo D) | G98: MDF-AD2-6 | H98: 3 | Q98: 3
A99: PTO. PIRAY | B99: MDF | C99: ADMINISTRACIÓN 2 | D99: APOBA1-874 | E99: PIRA-PIR-MDF-ADMIN2-OFSIYCO6 | F99: OF. DE SISyCOM (Centro de Computos). | G99: MDF-AD2-7 | H99: 1 | J99: 1 | K99: 1 | L99: 1 | M99: 1
A100: PTO. PIRAY | B100: MDF | C100: ADMINISTRACIÓN 2 | D100: APOBA1-874 | E100: PIRA-PIR-MDF-ADMIN2-OFSIYCO8 | F100: OF. DE SISyCOM (Diem Norberto) | G100: MDF-AD2-8 | H100: 1 | J100: 1 | K100: 1 | L100: 1 | M100: 1
A101: PTO. PIRAY | B101: MDF | C101: ADMINISTRACIÓN 2 | D101: APOBA1-874 | E101: PIRA-PIR-MDF-ADMIN2-OFVACIA5 | F101: OFICINA DE MONITOREO. | G101: MDF-AD2-9 | H101: 1 | J101: 1 | K101: 1 | L101: 1 | M101: 1
A102: PTO. PIRAY | B102: MDF | C102: ALMACEN | D102: APOBA1-874 | E102: Of. Operadores | G102: MDF-ALM-2 | H102: 3 | Q102: 3
...

Sheet Hoja1
A3: SECTOR/USUARIO | B3: DESCRIPCIÓN | D3: COD. EQUIPO | E3: COD. NUEVO
A4: ESPE-ESP-CEL-ADMIN1-OFRRHH01 | B4: OF. RRHH CELULOSA | D4: CEL-AD1-1 | E4: CEL-AD1-1
A5: Of. RRHH (Auxiliares) 2 | B5: Of. RRHH (Auxiliares) 2 | D5: CEL-AD1-2 | E5: CEL-AD1-2
A6: ESPE-ESP-CEL-ADMIN1-SALREU01 | B6: SALA DE REUNIONES RR.HH. | D6: CEL-AD1-3 | E6: CEL-AD1-3
A7: ESPE-ESP-CEL-ADMIN1-OFJEFERH | B7: Of. Jefe de Área RRHH | D7: CEL-AD1-4 | E7: CEL-AD1-4
A8: ESPE-ESP-CEL-ADMIN1-OFAUINT1 | B8: Of. Jefe Auditoría Interna | D8: CEL-AD1-5 | E8: CEL-AD1-5
A9: ESPE-ESP-CEL-ADMIN1-OFAUINT2 | B9: Of. Auditoría Interna (Auxiliar) | D9: CEL-AD1-6 | E9: CEL-AD1-6
A10: ESPE-ESP-CEL-ADMIN1-OFCONFO2 | B10: Of. Control Forestal (Auxiliares) | D10: CEL-AD1-8 | E10: CEL-AD1-7
A11: ESPE-ESP-CEL-ADMIN1-OFMASSO3 | B11: DANIEL CABRERA | D11: CEL-AD1-15 | E11: CEL-AD1-8
A12: ESPE-ESP-CEL-ADMIN1-OFCOSTO1 | B12: Of. Costos (Auxiliares) | D12: CEL-AD1-11 | E12: CEL-AD1-9
A13: ESPE-ESP-CEL-ADMIN1-OFCONPRO | B13: Of. Control de Producción | D13: CEL-AD1-7 | E13: CEL-AD1-10
A14: ESPE-ESP-CEL-ADMIN1-OFMASSO3 | B14: OF. JEFE DE SEGURIDAD. GRACIELA BENITEZ | D14: CEL-AD1-10 | E14: CEL-AD1-11
... A29: ESPE-ESP-CEL-ADMIN1-OFSECGTE | B29: Of. Secretaria Gte. | D29: CEL-AD1-19 | E29: CEL-AD1-26
B30: OFICINAS SOEP | E30: CEL-AD1-27
B31: OFICINA DE VICITAS GERENCIA | E31: CEL-AD1-28
A34: SECTOR/USUARIO | B34: DESCRIPCIÓN | C34: DESCRIPCION NUEVA | D34: COD. EQUIPO | E34: COD. NUEVO
A35: YPOR-YPO-GOF-ADMIN1-OFIC0010 | B35: OFICINA DEL secretaria GTE FORESTAL | C35: OFICINA 01 SECRETARIA DE GERENCIA | D35: PYP-AD1-10 | E35: PYP-AD1-10
A36: YPOR-YPO-GOF-ADMIN1-OFIC0011 | B36: OFICINA DE SYSO (LANG) | C36: OFICIAN 02 SYSO | D36: PYP-AD1-11 | E36: PYP-AD1-11
A37: YPOR-YPO-GOF-ADMIN1-OFIC0012 | B37: OFICINA DE CARTOGRAFIA | C37: OFICINA 03 CARTOGRAFIA | D37: PYP-AD1-12 | E37: PYP-AD1-12
A38: YPOR-YPO-GOF-ADMIN1 | B38: Of. Abastecimiento - Ventas y Planificación | C38: OFICIANA 04 | D38: PYP-AD1-13 | E38: PYP-AD1-13
A39: YPOR-YPO-GOF-ADMIN1-OFIC0014 | B39: Of. Control de Producción 1 | C39: OFICINA 05 | D39: PYP-AD1-14 | E39: PYP-AD1-14
A40: YPOR-YPO-GOF-ADMIN1-OFIC0015 | B40: Of. Control de Producción 2 (Oficina N° 3) | C40: OFICINA 06 | D40: PYP-AD1-15 | E40: PYP-AD1-15
A41: YPOR-YPO-GOF-ADMIN1 | B41: VACIA | C41: OFICINA 07 | D41: PYP-AD1-16 | E41: PYP-AD1-16
A42: YPOR-YPO-GOF-ADMIN1-OFIC0036 | B42: OF. RRHH (ML BOYCO) | C42: OFICINA 08 BOYCO LORENA | D42: PYP-AD1-17 | E42: PYP-AD1-17
A43: YPOR-YPO-GOF-ADMIN1-OFIC0019 | B43: Of. SySO (Lang Julio) | C43: OFICINA 09 | D43: PYP-AD1-18 | E43: PYP-AD1-18
A44: YPOR-YPO-GOF-ADMIN1-OFIC0020 | B44: Of. Control Forestal | C44: OFICIAN 10 | D44: PYP-AD1-19 | E44: PYP-AD1-19
A45: YPOR-YPO-GOF-ADMIN1-OFIC0020 | B45: Of. De Costos | C45: OFICINA 11 | D45: PYP-AD1-20 | E45: PYP-AD1-20
... A63: YPOR-YPO-GOF-ADMIN1 | B63: Of. De Jefe (De Oliveira A.) | C63: OFICINA 25 | D63: PYP-AD1-9 | E63: PYP-AD1-8
A64: YPOR-YPO-GOF-ADMIN1 | C64: NUEVA ALA TECNICA | E64: PYP-AD1-30
A65: YPOR-YPO-GOF-ADMIN1 | C65: NUEVA ALA TECNICA | E65: PYP-AD1-31
A66: YPOR-YPO-HOT-HOTEL1-HALLINGR | B66: HALL INGRESO | D66: PYP-HOS-1
A67: YPOR-YPO-HOT-PLANTB-HABITA04 | B67: HABITACIÓN 4 | D67: PYP-HOS-10
A68: YPOR-YPO-HOT-PLANTB-HABITA05 | B68: HABITACIÓN 5 | D68: PYP-HOS-11
A69: YPOR-YPO-HOT-PLANTB-HABITA06 | B69: HABITACIÓN 6 | D69: PYP-HOS-12
A70: YPOR-YPO-HOT-PLANTB-HABITA07 | B70: HABITACIÓN 7 | D70: PYP-HOS-7
A71: YPOR-YPO-HOT-PLANTB-HABITA08 | B71: HABITACIÓN 8 | D71: PYP-HOS-8
A72: YPOR-YPO-HOT-PLANTB-HABITA09 | B72: HABITACIÓN 9 | D72: PYP-HOS-9
A73: YPOR-YPO-HOT-PLANTA-HABITA10 | B73: HABITACIÓN 10 | D73: PYP-HOS-16
A74: YPOR-YPO-HOT-PLANTA-HABITA11 | B74: HABITACIÓN 11 | D74: PYP-HOS-17
A75: YPOR-YPO-HOT-PLANTA-HABITA12 | B75: HABITACIÓN 12 | D75: PYP-HOS-18
A76: YPOR-YPO-HOT-PLANTA-HABITA13 | B76: HABITACIÓN 13 | D76: PYP-HOS-19
A77: YPOR-YPO-HOT-HOTEL1-COCINA01 | B77: COCINA | D77: PYP-HOS-2
... A114: YPOR-YPO-GOF-VIVERO | B114: Of. Jefe Distrito (Valenzuela) | D114: PYP-VIV-9
